Workbook

Sheet Übersicht
A1: Übersicht – Solo-Plan bis 10.000 € MRR, danach Ausbau mit Team
A2: Ergebnis vor Steuern. Im Solo-Plan ist das Ergebnis das Einkommen des Gründers (davon 35–40 % für Steuern/Sozialversicherung zurücklegen).
A4: Solo-Plan | B4: Konservativ · Hand | C4: Konservativ · auto | D4: Basis · Hand | E4: Basis · auto | F4: Optimistisch · Hand | G4: Optimistisch · auto
A5: MRR Monat 6 (Apr 27) | B5: ='Solo Konservativ'!G19 -> 5656.8524 | C5: ='Solo Konservativ auto'!G19 -> 5656.8524 | D5: ='Solo Basis'!G19 -> 8633.8798 | E5: ='Solo Basis auto'!G19 -> 9020.6248 | F5: ='Solo Optimistisch'!G19 -> 9555.9017 | G5: ='Solo Optimistisch auto'!G19 -> 12384.397
A6: MRR Monat 12 (Okt 27) | B6: ='Solo Konservativ'!M19 -> 11674.698 | C6: ='Solo Konservativ auto'!M19 -> 12034.975 | D6: ='Solo Basis'!M19 -> 12909.996 | E6: ='Solo Basis auto'!M19 -> 18519.926 | F6: ='Solo Optimistisch'!M19 -> 13119.875 | G6: ='Solo Optimistisch auto'!M19 -> 23122.317
A7: MRR Monat 24 (Okt 28) | B7: ='Solo Konservativ'!Y19 -> 14164.904 | C7: ='Solo Konservativ auto'!Y19 -> 21870.188 | D7: ='Solo Basis'!Y19 -> 14217.816 | E7: ='Solo Basis auto'!Y19 -> 26427.305 | F7: ='Solo Optimistisch'!Y19 -> 14227.379 | G7: ='Solo Optimistisch auto'!Y19 -> 26725.254
A8: Monat, in dem 10.000 € MRR erreicht werden | B8: =IF(MAX('Solo Konservativ'!B19:Y19)>=10000,COUNTIF('Solo Konservativ'!B19:Y19,"<10000")+1,"nicht in 24 Monaten") -> 10 | C8: =IF(MAX('Solo Konservativ auto'!B19:Y19)>=10000,COUNTIF('Solo Konservativ auto'!B19:Y19,"<10000")+1,"nicht in 24 Monaten") -> 10 | D8: =IF(MAX('Solo Basis'!B19:Y19)>=10000,COUNTIF('Solo Basis'!B19:Y19,"<10000")+1,"nicht in 24 Monaten") -> 8 | E8: =IF(MAX('Solo Basis auto'!B19:Y19)>=10000,COUNTIF('Solo Basis auto'!B19:Y19,"<10000")+1,"nicht in 24 Monaten") -> 7 | F8: =IF(MAX('Solo Optimistisch'!B19:Y19)>=10000,COUNTIF('Solo Optimistisch'!B19:Y19,"<10000")+1,"nicht in 24 Monaten") -> 7 | G8: =IF(MAX('Solo Optimistisch auto'!B19:Y19)>=10000,COUNTIF('Solo Optimistisch auto'!B19:Y19,"<10000")+1,"nicht in 24 Monaten") -> 5
A9: Einkommen erste 12 Monate (vor Steuern) | B9: =SUM('Solo Konservativ'!B23:M23) -> 96652.198 | C9: =SUM('Solo Konservativ auto'!B23:M23) -> 96488.323 | D9: =SUM('Solo Basis'!B23:M23) -> 125052.27 | E9: =SUM('Solo Basis auto'!B23:M23) -> 154686.39 | F9: =SUM('Solo Optimistisch'!B23:M23) -> 135249.95 | G9: =SUM('Solo Optimistisch auto'!B23:M23) -> 205965.33
A10: Abschlüsse erste 12 Monate | B10: =SUM('Solo Konservativ'!B11:M11) -> 21.434527 | C10: =SUM('Solo Konservativ auto'!B11:M11) -> 22 | D10: =SUM('Solo Basis'!B11:M11) -> 24.56373 | E10: =SUM('Solo Basis auto'!B11:M11) -> 34 | F10: =SUM('Solo Optimistisch'!B11:M11) -> 25.308961 | G10: =SUM('Solo Optimistisch auto'!B11:M11) -> 43.00575
A11: Belegte Stunden Monat 12 | B11: ='Solo Konservativ'!M25 -> 170 | C11: ='Solo Konservativ auto'!M25 -> 98.227269 | D11: ='Solo Basis'!M25 -> 170 | E11: ='Solo Basis auto'!M25 -> 150.04599 | F11: ='Solo Optimistisch'!M25 -> 170 | G11: ='Solo Optimistisch auto'!M25 -> 170
A13: Ausbau ab 10.000 € MRR (Team) | B13: Wert
A14: Team-Start | B14: ="Jul 27" -> Jul 27
A15: Umsatz erste 12 Team-Monate | B15: ='Ausbau ab 10k'!Q25 -> 821745.77
A16: Ergebnis erste 12 Team-Monate | B16: ='Ausbau ab 10k'!Q37 -> 74129.245
A17: MRR nach 12 Team-Monaten | B17: ='Ausbau ab 10k'!P23 -> 96730.19
A18: Tiefster Kassenstand im Ausbau | B18: =MIN(0,MIN('Ausbau ab 10k'!E38:P38)) -> -4565.8532
A19: Jahresumsatz-Tempo im 12. Team-Monat | B19: ='Ausbau ab 10k'!P26 -> 1798466.3
A22: MRR je Monat (Solo) | B22: Konservativ · Hand | C22: Konservativ · auto | D22: Basis · Hand | E22: Basis · auto | F22: Optimistisch · Hand | G22: Optimistisch · auto
A23: Nov 26 | B23: ='Solo Konservativ'!B19 -> 593 | C23: ='Solo Konservativ auto'!B19 -> 593 | D23: ='Solo Basis'!B19 -> 1186 | E23: ='Solo Basis auto'!B19 -> 1186 | F23: ='Solo Optimistisch'!B19 -> 1779 | G23: ='Solo Optimistisch auto'!B19 -> 1779
A24: Dez 26 | B24: ='Solo Konservativ'!C19 -> 1172.6367 | C24: ='Solo Konservativ auto'!C19 -> 1172.6367 | D24: ='Solo Basis'!C19 -> 2345.2733 | E24: ='Solo Basis auto'!C19 -> 2345.2733 | F24: ='Solo Optimistisch'!C19 -> 3517.91 | G24: ='Solo Optimistisch auto'!C19 -> 3517.91
A25: Jan 27 | B25: ='Solo Konservativ'!D19 -> 2332.227 | C25: ='Solo Konservativ auto'!D19 -> 2332.227 | D25: ='Solo Basis'!D19 -> 4071.4539 | E25: ='Solo Basis auto'!D19 -> 4071.4539 | F25: ='Solo Optimistisch'!D19 -> 5548.5749 | G25: ='Solo Optimistisch auto'!D19 -> 5810.6809
A26: Feb 27 | B26: ='Solo Konservativ'!E19 -> 3465.7167 | C26: ='Solo Konservativ auto'!E19 -> 3465.7167 | D26: ='Solo Basis'!E19 -> 5758.7966 | E26: ='Solo Basis auto'!E19 -> 5758.7966 | F26: ='Solo Optimistisch'!E19 -> 7182.4706 | G26: ='Solo Optimistisch auto'!E19 -> 8051.8766
A27: Mär 27 | B27: ='Solo Konservativ'!F19 -> 4573.7241 | C27: ='Solo Konservativ auto'!F19 -> 4573.7241 | D27: ='Solo Basis'!F19 -> 7351.8158 | E27: ='Solo Basis auto'!F19 -> 7408.2213 | F27: ='Solo Optimistisch'!F19 -> 8497.3991 | G27: ='Solo Optimistisch auto'!F19 -> 10242.718
A28: Apr 27 | B28: ='Solo Konservativ'!G19 -> 5656.8524 | C28: ='Solo Konservativ auto'!G19 -> 5656.8524 | D28: ='Solo Basis'!G19 -> 8633.8798 | E28: ='Solo Basis auto'!G19 -> 9020.6248 | F28: ='Solo Optimistisch'!G19 -> 9555.9017 | G28: ='Solo Optimistisch auto'!G19 -> 12384.397
A29: Mai 27 | B29: ='Solo Konservativ'!H19 -> 6715.6896 | C29: ='Solo Konservativ auto'!H19 -> 6715.6896 | D29: ='Solo Basis'!H19 -> 9665.9583 | E29: ='Solo Basis auto'!H19 -> 10596.882 | F29: ='Solo Optimistisch'!H19 -> 10408.252 | G29: ='Solo Optimistisch auto'!H19 -> 14478.074
A30: Jun 27 | B30: ='Solo Konservativ'!I19 -> 7849.3091 | C30: ='Solo Konservativ auto'!I19 -> 7849.3091 | D30: ='Solo Basis'!I19 -> 10666.913 | E30: ='Solo Basis auto'!I19 -> 12285.596 | F30: ='Solo Optimistisch'!I19 -> 11243.983 | G30: ='Solo Optimistisch auto'!I19 -> 16721.883
A31: Jul 27 | B31: ='Solo Konservativ'!J19 -> 8946.7021 | C31: ='Solo Konservativ auto'!J19 -> 8946.7021 | D31: ='Solo Basis'!J19 -> 11448.477 | E31: ='Solo Basis auto'!J19 -> 13920.246 | F31: ='Solo Optimistisch'!J19 -> 11896.933 | G31: ='Solo Optimistisch auto'!J19 -> 18893.79
A32: Aug 27 | B32: ='Solo Konservativ'!K19 -> 10009.243 | C32: ='Solo Konservativ auto'!K19 -> 10009.243 | D32: ='Solo Basis'!K19 -> 12059.081 | E32: ='Solo Basis auto'!K19 -> 15502.887 | F32: ='Solo Optimistisch'!K19 -> 12407.438 | G32: ='Solo Optimistisch auto'!K19 -> 20670.186
A33: Sep 27 | B33: ='Solo Konservativ'!L19 -> 10944.687 | C33: ='Solo Konservativ auto'!L19 -> 11038.247 | D33: ='Solo Basis'!L19 -> 12536.455 | E33: ='Solo Basis auto'!L19 -> 17035.487 | F33: ='Solo Optimistisch'!L19 -> 12806.924 | G33: ='Solo Optimistisch auto'!L19 -> 22050.05
A34: Okt 27 | B34: ='Solo Konservativ'!M19 -> 11674.698 | C34: ='Solo Konservativ auto'!M19 -> 12034.975 | D34: ='Solo Basis'!M19 -> 12909.996 | E34: ='Solo Basis auto'!M19 -> 18519.926 | F34: ='Solo Optimistisch'!M19 -> 13119.875 | G34: ='Solo Optimistisch auto'!M19 -> 23122.317
A35: Nov 27 | B35: ='Solo Konservativ'!N19 -> 12244.645 | C35: ='Solo Konservativ auto'!N19 -> 13000.631 | D35: ='Solo Basis'!N19 -> 13202.605 | E35: ='Solo Basis auto'!N19 -> 19958.009 | F35: ='Solo Optimistisch'!N19 -> 13365.366 | G35: ='Solo Optimistisch auto'!N19 -> 23955.972
A36: Dez 27 | B36: ='Solo Konservativ'!O19 -> 12689.874 | C36: ='Solo Konservativ auto'!O19 -> 13936.371 | D36: ='Solo Basis'!O19 -> 13432.126 | E36: ='Solo Basis auto'!O19 -> 21351.461 | F36: ='Solo Optimistisch'!O19 -> 13558.261 | G36: ='Solo Optimistisch auto'!O19 -> 24604.523
A37: Jan 28 | B37: ='Solo Konservativ'!P19 -> 13037.922 | C37: ='Solo Konservativ auto'!P19 -> 14843.3 | D37: ='Solo Basis'!P19 -> 13612.462 | E37: ='Solo Basis auto'!P19 -> 22574.762 | F37: ='Solo Optimistisch'!P19 -> 13710.138 | G37: ='Solo Optimistisch auto'!P19 -> 25109.474
A38: Feb 28 | B38: ='Solo Konservativ'!Q19 -> 13310.241 | C38: ='Solo Konservativ auto'!Q19 -> 15722.477 | D38: ='Solo Basis'!Q19 -> 13754.444 | E38: ='Solo Basis auto'!Q19 -> 23525.725 | F38: ='Solo Optimistisch'!Q19 -> 13830.022 | G38: ='Solo Optimistisch auto'!Q19 -> 25503.017
A39: Mär 28 | B39: ='Solo Konservativ'!R19 -> 13523.546 | C39: ='Solo Konservativ auto'!R19 -> 16574.918 | D39: ='Solo Basis'!R19 -> 13866.511 | E39: ='Solo Basis auto'!R19 -> 24265.42 | F39: ='Solo Optimistisch'!R19 -> 13924.942 | G39: ='Solo Optimistisch auto'!R19 -> 25810.122
A40: Apr 28 | B40: ='Solo Konservativ'!S19 -> 13690.856 | C40: ='Solo Konservativ auto'!S19 -> 17401.595 | D40: ='Solo Basis'!S19 -> 13955.239 | E40: ='Solo Basis auto'!S19 -> 24841.214 | F40: ='Solo Optimistisch'!S19 -> 14000.377 | G40: ='Solo Optimistisch auto'!S19 -> 26050.16
A41: Mai 28 | B41: ='Solo Konservativ'!T19 -> 13822.316 | C41: ='Solo Konservativ auto'!T19 -> 18203.44 | D41: ='Solo Basis'!T19 -> 14025.754 | E41: ='Solo Basis auto'!T19 -> 25289.85 | F41: ='Solo Optimistisch'!T19 -> 14060.596 | G41: ='Solo Optimistisch auto'!T19 -> 26238.153
A42: Jun 28 | B42: ='Solo Konservativ'!U19 -> 13925.83 | C42: ='Solo Konservativ auto'!U19 -> 18981.346 | D42: ='Solo Basis'!U19 -> 14082.047 | E42: ='Solo Basis auto'!U19 -> 25639.826 | F42: ='Solo Optimistisch'!U19 -> 14108.927 | G42: ='Solo Optimistisch auto'!U19 -> 26385.755
A43: Jul 28 | B43: ='Solo Konservativ'!V19 -> 14007.554 | C43: ='Solo Konservativ auto'!V19 -> 19736.169 | D43: ='Solo Basis'!V19 -> 14127.23 | E43: ='Solo Basis auto'!V19 -> 25913.25 | F43: ='Solo Optimistisch'!V19 -> 14147.962 | G43: ='Solo Optimistisch auto'!V19 -> 26502.006
A44: Aug 28 | B44: ='Solo Konservativ'!W19 -> 14072.288 | C44: ='Solo Konservativ auto'!W19 -> 20468.731 | D44: ='Solo Basis'!W19 -> 14163.729 | E44: ='Solo Basis auto'!W19 -> 26127.268 | F44: ='Solo Optimistisch'!W19 -> 14179.723 | G44: ='Solo Optimistisch auto'!W19 -> 26593.916
A45: Sep 28 | B45: ='Solo Konservativ'!X19 -> 14123.767 | C45: ='Solo Konservativ auto'!X19 -> 21179.819 | D45: ='Solo Basis'!X19 -> 14193.433 | E45: ='Solo Basis auto'!X19 -> 26295.181 | F45: ='Solo Optimistisch'!X19 -> 14205.786 | G45: ='Solo Optimistisch auto'!X19 -> 26666.926
A46: Okt 28 | B46: ='Solo Konservativ'!Y19 -> 14164.904 | C46: ='Solo Konservativ auto'!Y19 -> 21870.188 | D46: ='Solo Basis'!Y19 -> 14217.816 | E46: ='Solo Basis auto'!Y19 -> 26427.305 | F46: ='Solo Optimistisch'!Y19 -> 14227.379 | G46: ='Solo Optimistisch auto'!Y19 -> 26725.254

Sheet Preise
A1: Preisübersicht und Verdienst je Abschluss
A2: Blaue Werte sind Eingaben. Stunden = alles selbst gemacht, inkl. Vertrieb je Abschluss (Pflege wird mit der Website verkauft).
A3: Vertriebsstunden je Abschluss | B3: 10
A5: Produkt | B5: Einmalig | C5: Monatlich | D5: Std. einmalig | E5: Std. je Monat | F5: Umsatz 1. Jahr | G5: Stunden 1. Jahr | H5: € je Stunde | I5: Hinweis
A6: Website Start | B6: 1490 | C6: 0 | D6: 16 | E6: 0 | F6: =B6+12*C6 -> 1490 | G6: =D6+12*E6+$B$3 -> 26 | H6: =IF(G6>0,F6/G6,0) -> 57.307692 | I6: bis 5 Seiten, fertig in 2–3 Wochen
A7: Website Wachstum | B7: 2990 | C7: 0 | D7: 28 | E7: 0 | F7: =B7+12*C7 -> 2990 | G7: =D7+12*E7+$B$3 -> 38 | H7: =IF(G7>0,F7/G7,0) -> 78.684211 | I7: bis 15 Seiten, Orts- und Karriereseiten
A8: Pflege & Hosting Start | B8: 0 | C8: 49 | D8: 0 | E8: 0.25 | F8: =B8+12*C8 -> 588 | G8: =D8+12*E8+0 -> 3 | H8: =IF(G8>0,F8/G8,0) -> 196 | I8: 12 Monate Laufzeit
A9: Pflege & Hosting Wachstum | B9: 0 | C9: 89 | D9: 0 | E9: 0.5 | F9: =B9+12*C9 -> 1068 | G9: =D9+12*E9+0 -> 6 | H9: =IF(G9>0,F9/G9,0) -> 178 | I9: 12 Monate Laufzeit, inkl. 1 h Änderungen
A10: SEO Lokal | B10: 0 | C10: 390 | D10: 4 | E10: 5 | F10: =B10+12*C10 -> 4680 | G10: =D10+12*E10+$B$3 -> 74 | H10: =IF(G10>0,F10/G10,0) -> 63.243243 | I10: 6 Monate Mindestlaufzeit
A11: SEO Plus | B11: 0 | C11: 690 | D11: 6 | E11: 8 | F11: =B11+12*C11 -> 8280 | G11: =D11+12*E11+$B$3 -> 112 | H11: =IF(G11>0,F11/G11,0) -> 73.928571 | I11: 6 Monate Mindestlaufzeit
A12: Google-Ads-Betreuung | B12: 390 | C12: 290 | D12: 4 | E12: 2.5 | F12: =B12+12*C12 -> 3870 | G12: =D12+12*E12+$B$3 -> 44 | H12: =IF(G12>0,F12/G12,0) -> 87.954545 | I12: zzgl. Werbebudget, monatlich kündbar
A13: Recruiting-Paket | B13: 1490 | C13: 790 | D13: 10 | E13: 7 | F13: =B13+12*C13 -> 10970 | G13: =D13+12*E13+$B$3 -> 104 | H13: =IF(G13>0,F13/G13,0) -> 105.48077 | I13: zzgl. Werbebudget, 3 Monate Mindestlaufzeit
A14: Wachstumsprogramm | B14: 1490 | C14: 1190 | D14: 28 | E14: 13 | F14: =B14+12*C14 -> 15770 | G14: =D14+12*E14+$B$3 -> 194 | H14: =IF(G14>0,F14/G14,0) -> 81.28866 | I14: 12 Monate, Website + SEO Plus + Ads inklusive
A16: Faustregel netto: Vom Gewinn 35–40 % für Einkommensteuer und Sozialversicherung zurücklegen (Steuerberater fragen).

Sheet Annahmen
A1: Annahmen Solo-Plan (Gründer macht Vertrieb und Umsetzung allein)
A2: Blaue Zahlen sind Eingaben. Gelb = wichtigste Hebel. Monat 1 = November 2026.
A4: Annahme | B4: Wert
A5: Ø Website-Auftrag (einmalig) | B5: 2200
A6: Ø Pflege & Hosting / Monat | B6: 69
A7: Wachstumsprogramm / Monat | B7: 1190
A8: Programm-Einrichtung (inkl. Website) | B8: 1490
A9: Ø SEO / Monat | B9: 520
A10: Recruiting-Paket / Monat | B10: 790
A11: Recruiting-Einrichtung | B11: 1490
A12: Anteil Abschlüsse: Website (+ Pflege) | B12: 0.25
A13: Anteil Abschlüsse: Wachstumsprogramm | B13: 0.25
A14: Anteil Abschlüsse: SEO | B14: 0.25
A15: Anteil Abschlüsse: Recruiting | B15: 0.25
A16: Recruiting wird verkauft ab Monat (8 = Jun 27) | B16: 8
... A43: Eigenes Marketing / Monat | B43: 150
A45: Std. je neuem Abschluss (Ø von Hand, alle Produkte, inkl. Vertrieb) | B45: =Annahmen!$B$12*(Annahmen!$B$21+Annahmen!$B$25+Annahmen!$B$29)+Annahmen!$B$13*(Annahmen!$B$22+Annahmen!$B$26+Annahmen!$B$29)+Annahmen!$B$14*(Annahmen!$B$23+Annahmen!$B$27+Annahmen!$B$29)+Annahmen!$B$15*(Annahmen!$B$24+Annahmen!$B$28+Annahmen!$B$29) -> 34.5625
A47: Abschluss-Ziel (Vertriebstempo) | B47: Konservativ | C47: Basis | D47: Optimistisch
A48: Abschlüsse / Monat, Monat 1–2 | B48: 1 | C48: 2 | D48: 3
A49: Abschlüsse / Monat, ab Monat 3 | B49: 2 | C49: 3 | D49: 4

Sheet Solo Konservativ
A1: Solo-Plan · Szenario Konservativ · von Hand (24 Monate ab Nov 2026)
A2: Abschlüsse = Minimum aus Vertriebstempo und freien Stunden. Kundenzahlen sind Erwartungswerte.
A4: Monat | B4: Nov 26 | C4: Dez 26 | D4: Jan 27 | E4: Feb 27 | F4: Mär 27 | G4: Apr 27 | H4: Mai 27 | I4: Jun 27 | J4: Jul 27 | K4: Aug 27 | L4: Sep 27 | M4: Okt 27 | N4: Nov 27 | O4: Dez 27 | P4: Jan 28 | Q4: Feb 28 | R4: Mär 28 | S4: Apr 28 | T4: Mai 28 | U4: Jun 28 | V4: Jul 28 | W4: Aug 28 | X4: Sep 28 | Y4: Okt 28
A5: Abschluss-Ziel (Vertrieb) | B5: =Annahmen!$B$48 -> 1 | C5: =Annahmen!$B$48 -> 1 | D5: =Annahmen!$B$49 -> 2 | E5: =Annahmen!$B$49 -> 2 | F5: =Annahmen!$B$49 -> 2 | G5: =Annahmen!$B$49 -> 2 | H5: =Annahmen!$B$49 -> 2 | I5: =Annahmen!$B$49 -> 2 | J5: =Annahmen!$B$49 -> 2 | K5: =Annahmen!$B$49 -> 2 | ... Y5: =Annahmen!$B$49 -> 2
A6: Recruiting im Verkauf (1 = ja) | B6: =IF(1>=Annahmen!$B$16,1,0) -> 0 | C6: =IF(2>=Annahmen!$B$16,1,0) -> 0 | D6: =IF(3>=Annahmen!$B$16,1,0) -> 0 | E6: =IF(4>=Annahmen!$B$16,1,0) -> 0 | F6: =IF(5>=Annahmen!$B$16,1,0) -> 0 | G6: =IF(6>=Annahmen!$B$16,1,0) -> 0 | H6: =IF(7>=Annahmen!$B$16,1,0) -> 0 | I6: =IF(8>=Annahmen!$B$16,1,0) -> 1 | J6: =IF(9>=Annahmen!$B$16,1,0) -> 1 | K6: =IF(10>=Annahmen!$B$16,1,0) -> 1 | L6: =IF(11>=Annahmen!$B$16,1,0) -> 1 | M6: =IF(12>=Annahmen!$B$16,1,0) -> 1 | N6: =IF(13>=Annahmen!$B$16,1,0) -> 1 | O6: =IF(14>=Annahmen!$B$16,1,0) -> 1 | P6: =IF(15>=Annahmen!$B$16,1,0) -> 1 | Q6: =IF(16>=Annahmen!$B$16,1,0) -> 1 | R6: =IF(17>=Annahmen!$B$16,1,0) -> 1 | S6: =IF(18>=Annahmen!$B$16,1,0) -> 1 | T6: =IF(19>=Annahmen!$B$16,1,0) -> 1 | U6: =IF(20>=Annahmen!$B$16,1,0) -> 1 | V6: =IF(21>=Annahmen!$B$16,1,0) -> 1 | W6: =IF(22>=Annahmen!$B$16,1,0) -> 1 | X6: =IF(23>=Annahmen!$B$16,1,0) -> 1 | Y6: =IF(24>=Annahmen!$B$16,1,0) -> 1
A7: Automatisierung aktiv (1 = ja) | B7: =0 -> 0 | C7: =0 -> 0 | D7: =0 -> 0 | E7: =0 -> 0 | F7: =0 -> 0 | G7: =0 -> 0 | H7: =0 -> 0 | I7: =0 -> 0 | ... Y7: =0 -> 0
A8: Std. je neuem Abschluss | B8: =Annahmen!$B$12/(1-Annahmen!$B$15*(1-B6))*((Annahmen!$B$21+B7*(Annahmen!$B$30-Annahmen!$B$21))+(Annahmen!$B$25+B7*(Annahmen!$B$34-Annahmen!$B$25))+(Annahmen!$B$29+B7*(Annahmen!$B$38-Annahmen!$B$29)))+Annahmen!$B$13/(1-Annahmen!$B$15*(1-B6))*((Annahmen!$B$22+B7*(Annahmen!$B$31-Annahmen!$B$22))+(Annahmen!$B$26+B7*(Annahmen!$B$35-Annahmen!$B$26))+(Annahmen!$B$29+B7*(Annahmen!$B$38-Annahmen!$B$29)))+Annahmen!$B$14/(1-Annahmen!$B$15*(1-B6))*((Annahmen!$B$23+B7*(Annahmen!$B$32-Annahmen!$B$23))+(Annahmen!$B$27+B7*(Annahmen!$B$36-Annahmen!$B$27))+(Annahmen!$B$29+B7*(Annahmen!$B$38-Annahmen!$B$29)))+Annahmen!$B$15*B6*((Annahmen!$B$24+B7*(Annahmen!$B$33-Annahmen!$B$24))+(Annahmen!$B$28+B7*(Annahmen!$B$37-Annahmen!$B$28))+(Annahmen!$B$29+B7*(Annahmen!$B$38-Annahmen!$B$29))) -> 37.083333 | C8: =Annahmen!$B$12/(1-Annahmen!$B$15*(1-C6))*((Annahmen!$B$21+C7*(Annahmen!$B$30-Annahmen!$B$21))+(Annahmen!$B$25+C7*(Annahmen!$B$34-Annahmen!$B$25))+(Annahmen!$B$29+C7*(Annahmen!$B$38-Annahmen!$B$29)))+Annahmen!$B$13/(1-Annahmen!$B$15*(1-C6))*((Annahmen!$B$22+C7*(Annahmen!$B$31-Annahmen!$B$22))+(Annahmen!$B$26+C7*(Annahmen!$B$35-Annahmen!$B$26))+(Annahmen!$B$29+C7*(Annahmen!$B$38-Annahmen!$B$29)))+Annahmen!$B$14/(1-Annahmen!$B$15*(1-C6))*((Annahmen!$B$23+C7*(Annahmen!$B$32-Annahmen!$B$23))+(Annahmen!$B$27+C7*(Annahmen!$B$36-Annahmen!$B$27))+(Annahmen!$B$29+C7*(Annahmen!$B$38-Annahmen!$B$29)))+Annahmen!$B$15*C6*((Annahmen!$B$24+C7*(Annahmen!$B$33-Annahmen!$B$24))+(Annahmen!$B$28+C7*(Annahmen!$B$37-Annahmen!$B$28))+(Annahmen!$B$29+C7*(Annahmen!$B$38-Annahmen!$B$29))) -> 37.083333 | D8: =Annahmen!$B$12/(1-Annahmen!$B$15*(1-D6))*((Annahmen!$B$21+D7*(Annahmen!$B$30-Annahmen!$B$21))+(Annahmen!$B$25+D7*(Annahmen!$B$34-Annahmen!$B$25))+(Annahmen!$B$29+D7*(Annahmen!$B$38-Annahmen!$B$29)))+Annahmen!$B$13/(1-Annahmen!$B$15*(1-D6))*((Annahmen!$B$22+D7*(Annahmen!$B$31-Annahmen!$B$22))+(Annahmen!$B$26+D7*(Annahmen!$B$35-Annahmen!$B$26))+(Annahmen!$B$29+D7*(Annahmen!$B$38-Annahmen!$B$29)))+Annahmen!$B$14/(1-Annahmen!$B$15*(1-D6))*((Annahmen!$B$23+D7*(Annahmen!$B$32-Annahmen!$B$23))+(Annahmen!$B$27+D7*(Annahmen!$B$36-Annahmen!$B$27))+(Annahmen!$B$29+D7*(Annahmen!$B$38-Annahmen!$B$29)))+Annahmen!$B$15*D6*((Annahmen!$B$24+D7*(Annahmen!$B$33-Annahmen!$B$24))+(Annahmen!$B$28+D7*(Annahmen!$B$37-Annahmen!$B$28))+(Annahmen!$B$29+D7*(Annahmen!$B$38-Annahmen!$B$29))) -> 37.083333 | E8: =Annahmen!$B$12/(1-Annahmen!$B$15*(1-E6))*((Annahmen!$B$21+E7*(Annahmen!$B$30-Annahmen!$B$21))+(Annahmen!$B$25+E7*(Annahmen!$B$34-Annahmen!$B$25))+(Annahmen!$B$29+E7*(Annahmen!$B$38-Annahmen!$B$29)))+Annahmen!$B$13/(1-Annahmen!$B$15*(1-E6))*((Annahmen!$B$22+E7*(Annahmen!$B$31-Annahmen!$B$22))+(Annahmen!$B$26+E7*(Annahmen!$B$35-Annahmen!$B$26))+(Annahmen!$B$29+E7*(Annahmen!$B$38-Annahmen!$B$29)))+Annahmen!$B$14/(1-Annahmen!$B$15*(1-E6))*((Annahmen!$B$23+E7*(Annahmen!$B$32-Annahmen!$B$23))+(Annahmen!$B$27+E7*(Annahmen!$B$36-Annahmen!$B$27))+(Annahmen!$B$29+E7*(Annahmen!$B$38-Annahmen!$B$29)))+Annahmen!$B$15*E6*((Annahmen!$B$24+E7*(Annahmen!$B$33-Annahmen!$B$24))+(Annahmen!$B$28+E7*(Annahmen!$B$37-Annahmen!$B$28))+(Annahmen!$B$29+E7*(Annahmen!$B$38-Annahmen!$B$29))) -> 37.083333 | F8: =Annahmen!$B$12/(1-Annahmen!$B$15*(1-F6))*((Annahmen!$B$21+F7*(Annahmen!$B$30-Annahmen!$B$21))+(Annahmen!$B$25+F7*(Annahmen!$B$34-Annahmen!$B$25))+(Annahmen!$B$29+F7*(Annahmen!$B$38-Annahmen!$B$29)))+Annahmen!$B$13/(1-Annahmen!$B$15*(1-F6))*((Annahmen!$B$22+F7*(Annahmen!$B$31-Annahmen!$B$22))+(Annahmen!$B$26+F7*(Annahmen!$B$35-Annahmen!$B$26))+(Annahmen!$B$29+F7*(Annahmen!$B$38-Annahmen!$B$29)))+Annahmen!$B$14/(1-Annahmen!$B$15*(1-F6))*((Annahmen!$B$23+F7*(Annahmen!$B$32-Annahmen!$B$23))+(Annahmen!$B$27+F7*(Annahmen!$B$36-Annahmen!$B$27))+(Annahmen!$B$29+F7*(Annahmen!$B$38-Annahmen!$B$29)))+Annahmen!$B$15*F6*((Annahmen!$B$24+F7*(Annahmen!$B$33-Annahmen!$B$24))+(Annahmen!$B$28+F7*(Annahmen!$B$37-Annahmen!$B$28))+(Annahmen!$B$29+F7*(Annahmen!$B$38-Annahmen!$B$29))) -> 37.083333 | G8: =Annahmen!$B$12/(1-Annahmen!$B$15*(1-G6))*((Annahmen!$B$21+G7*(Annahmen!$B$30-Annahmen!$B$21))+(Annahmen!$B$25+G7*(Annahmen!$B$34-Annahmen!$B$25))+(Annahmen!$B$29+G7*(Annahmen!$B$38-Annahmen!$B$29)))+Annahmen!$B$13/(1-Annahmen!$B$15*(1-G6))*((Annahmen!$B$22+G7*(Annahmen!$B$31-Annahmen!$B$22))+(Annahmen!$B$26+G7*(Annahmen!$B$35-Annahmen!$B$26))+(Annahmen!$B$29+G7*(Annahmen!$B$38-Annahmen!$B$29)))+Annahmen!$B$14/(1-Annahmen!$B$15*(1-G6))*((Annahmen!$B$23+G7*(Annahmen!$B$32-Annahmen!$B$23))+(Annahmen!$B$27+G7*(Annahmen!$B$36-Annahmen!$B$27))+(Annahmen!$B$29+G7*(Annahmen!$B$38-Annahmen!$B$29)))+Annahmen!$B$15*G6*((Annahmen!$B$24+G7*(Annahmen!$B$33-Annahmen!$B$24))+(Annahmen!$B$28+G7*(Annahmen!$B$37-Annahmen!$B$28))+(Annahmen!$B$29+G7*(Annahmen!$B$38-Annahmen!$B$29))) -> 37.083333 | H8: =Annahmen!$B$12/(1-Annahmen!$B$15*(1-H6))*((Annahmen!$B$21+H7*(Annahmen!$B$30-Annahmen!$B$21))+(Annahmen!$B$25+H7*(Annahmen!$B$34-Annahmen!$B$25))+(Annahmen!$B$29+H7*(Annahmen!$B$38-Annahmen!$B$29)))+Annahmen!$B$13/(1-Annahmen!$B$15*(1-H6))*((Annahmen!$B$22+H7*(Annahmen!$B$31-Annahmen!$B$22))+(Annahmen!$B$26+H7*(Annahmen!$B$35-Annahmen!$B$26))+(Annahmen!$B$29+H7*(Annahmen!$B$38-Annahmen!$B$29)))+Annahmen!$B$14/(1-Annahmen!$B$15*(1-H6))*((Annahmen!$B$23+H7*(Annahmen!$B$32-Annahmen!$B$23))+(Annahmen!$B$27+H7*(Annahmen!$B$36-Annahmen!$B$27))+(Annahmen!$B$29+H7*(Annahmen!$B$38-Annahmen!$B$29)))+Annahmen!$B$15*H6*((Annahmen!$B$24+H7*(Annahmen!$B$33-Annahmen!$B$24))+(Annahmen!$B$28+H7*(Annahmen!$B$37-Annahmen!$B$28))+(Annahmen!$B$29+H7*(Annahmen!$B$38-Annahmen!$B$29))) -> 37.083333 | I8: =Annahmen!$B$12/(1-Annahmen!$B$15*(1-I6))*((Annahmen!$B$21+I7*(Annahmen!$B$30-Annahmen!$B$21))+(Annahmen!$B$25+I7*(Annahmen!$B$34-Annahmen!$B$25))+(Annahmen!$B$29+I7*(Annahmen!$B$38-Annahmen!$B$29)))+Annahmen!$B$13/(1-Annahmen!$B$15*(1-I6))*((Annahmen!$B$22+I7*(Annahmen!$B$31-Annahmen!$B$22))+(Annahmen!$B$26+I7*(Annahmen!$B$35-Annahmen!$B$26))+(Annahmen!$B$29+I7*(Annahmen!$B$38-Annahmen!$B$29)))+Annahmen!$B$14/(1-Annahmen!$B$15*(1-I6))*((Annahmen!$B$23+I7*(Annahmen!$B$32-Annahmen!$B$23))+(Annahmen!$B$27+I7*(Annahmen!$B$36-Annahmen!$B$27))+(Annahmen!$B$29+I7*(Annahmen!$B$38-Annahmen!$B$29)))+Annahmen!$B$15*I6*((Annahmen!$B$24+I7*(Annahmen!$B$33-Annahmen!$B$24))+(Annahmen!$B$28+I7*(Annahmen!$B$37-Annahmen!$B$28))+(Annahmen!$B$29+I7*(Annahmen!$B$38-Annahmen!$B$29))) -> 34.5625 | ... Y8: =Annahmen!$B$12/(1-Annahmen!$B$15*(1-Y6))*((Annahmen!$B$21+Y7*(Annahmen!$B$30-Annahmen!$B$21))+(Annahmen!$B$25+Y7*(Annahmen!$B$34-Annahmen!$B$25))+(Annahmen!$B$29+Y7*(Annahmen!$B$38-Annahmen!$B$29)))+Annahmen!$B$13/(1-Annahmen!$B$15*(1-Y6))*((Annahmen!$B$22+Y7*(Annahmen!$B$31-Annahmen!$B$22))+(Annahmen!$B$26+Y7*(Annahmen!$B$35-Annahmen!$B$26))+(Annahmen!$B$29+Y7*(Annahmen!$B$38-Annahmen!$B$29)))+Annahmen!$B$14/(1-Annahmen!$B$15*(1-Y6))*((Annahmen!$B$23+Y7*(Annahmen!$B$32-Annahmen!$B$23))+(Annahmen!$B$27+Y7*(Annahmen!$B$36-Annahmen!$B$27))+(Annahmen!$B$29+Y7*(Annahmen!$B$38-Annahmen!$B$29)))+Annahmen!$B$15*Y6*((Annahmen!$B$24+Y7*(Annahmen!$B$33-Annahmen!$B$24))+(Annahmen!$B$28+Y7*(Annahmen!$B$37-Annahmen!$B$28))+(Annahmen!$B$29+Y7*(Annahmen!$B$38-Annahmen!$B$29))) -> 34.5625
A9: Laufende Stunden (Bestand) | B9: =0*(Annahmen!$B$25+B7*(Annahmen!$B$34-Annahmen!$B$25))+0*(Annahmen!$B$26+B7*(Annahmen!$B$35-Annahmen!$B$26))+0*(Annahmen!$B$27+B7*(Annahmen!$B$36-Annahmen!$B$27))+0*(Annahmen!$B$28+B7*(Annahmen!$B$37-Annahmen!$B$28)) -> 0 | C9: =B14*(Annahmen!$B$25+C7*(Annahmen!$B$34-Annahmen!$B$25))+B15*(Annahmen!$B$26+C7*(Annahmen!$B$35-Annahmen!$B$26))+B16*(Annahmen!$B$27+C7*(Annahmen!$B$36-Annahmen!$B$27))+B17*(Annahmen!$B$28+C7*(Annahmen!$B$37-Annahmen!$B$28)) -> 6.4166667 | D9: =C14*(Annahmen!$B$25+D7*(Annahmen!$B$34-Annahmen!$B$25))+C15*(Annahmen!$B$26+D7*(Annahmen!$B$35-Annahmen!$B$26))+C16*(Annahmen!$B$27+D7*(Annahmen!$B$36-Annahmen!$B$27))+C17*(Annahmen!$B$28+D7*(Annahmen!$B$37-Annahmen!$B$28)) -> 12.685833 | E9: =D14*(Annahmen!$B$25+E7*(Annahmen!$B$34-Annahmen!$B$25))+D15*(Annahmen!$B$26+E7*(Annahmen!$B$35-Annahmen!$B$26))+D16*(Annahmen!$B$27+E7*(Annahmen!$B$36-Annahmen!$B$27))+D17*(Annahmen!$B$28+E7*(Annahmen!$B$37-Annahmen!$B$28)) -> 25.227708 | F9: =E14*(Annahmen!$B$25+F7*(Annahmen!$B$34-Annahmen!$B$25))+E15*(Annahmen!$B$26+F7*(Annahmen!$B$35-Annahmen!$B$26))+E16*(Annahmen!$B$27+F7*(Annahmen!$B$36-Annahmen!$B$27))+E17*(Annahmen!$B$28+F7*(Annahmen!$B$37-Annahmen!$B$28)) -> 37.481578 | G9: =F14*(Annahmen!$B$25+G7*(Annahmen!$B$34-Annahmen!$B$25))+F15*(Annahmen!$B$26+G7*(Annahmen!$B$35-Annahmen!$B$26))+F16*(Annahmen!$B$27+G7*(Annahmen!$B$36-Annahmen!$B$27))+F17*(Annahmen!$B$28+G7*(Annahmen!$B$37-Annahmen!$B$28)) -> 49.45435 | H9: =G14*(Annahmen!$B$25+H7*(Annahmen!$B$34-Annahmen!$B$25))+G15*(Annahmen!$B$26+H7*(Annahmen!$B$35-Annahmen!$B$26))+G16*(Annahmen!$B$27+H7*(Annahmen!$B$36-Annahmen!$B$27))+G17*(Annahmen!$B$28+H7*(Annahmen!$B$37-Annahmen!$B$28)) -> 61.15276 | I9: =H14*(Annahmen!$B$25+I7*(Annahmen!$B$34-Annahmen!$B$25))+H15*(Annahmen!$B$26+I7*(Annahmen!$B$35-Annahmen!$B$26))+H16*(Annahmen!$B$27+I7*(Annahmen!$B$36-Annahmen!$B$27))+H17*(Annahmen!$B$28+I7*(Annahmen!$B$37-Annahmen!$B$28)) -> 72.583375 | J9: =I14*(Annahmen!$B$25+J7*(Annahmen!$B$34-Annahmen!$B$25))+I15*(Annahmen!$B$26+J7*(Annahmen!$B$35-Annahmen!$B$26))+I16*(Annahmen!$B$27+J7*(Annahmen!$B$36-Annahmen!$B$27))+I17*(Annahmen!$B$28+J7*(Annahmen!$B$37-Annahmen!$B$28)) -> 84.044265 | ... Y9: =X14*(Annahmen!$B$25+Y7*(Annahmen!$B$34-Annahmen!$B$25))+X15*(Annahmen!$B$26+Y7*(Annahmen!$B$35-Annahmen!$B$26))+X16*(Annahmen!$B$27+Y7*(Annahmen!$B$36-Annahmen!$B$27))+X17*(Annahmen!$B$28+Y7*(Annahmen!$B$37-Annahmen!$B$28)) -> 147.27621
A10: Möglich nach Stunden | B10: =MAX(0,(Annahmen!$B$41-B9)/B8) -> 4.5842697 | C10: =MAX(0,(Annahmen!$B$41-C9)/C8) -> 4.411236 | D10: =MAX(0,(Annahmen!$B$41-D9)/D8) -> 4.2421798 | E10: =MAX(0,(Annahmen!$B$41-E9)/E8) -> 3.9039719 | F10: =MAX(0,(Annahmen!$B$41-F9)/F8) -> 3.5735305 | G10: =MAX(0,(Annahmen!$B$41-G9)/G8) -> 3.2506692 | H10: =MAX(0,(Annahmen!$B$41-H9)/H8) -> 2.9352065 | I10: =MAX(0,(Annahmen!$B$41-I9)/I8) -> 2.8185642 | ... Y10: =MAX(0,(Annahmen!$B$41-Y9)/Y8) -> 0.65746958
A11: Abschlüsse | B11: =MIN(B5,B10) -> 1 | C11: =MIN(C5,C10) -> 1 | D11: =MIN(D5,D10) -> 2 | E11: =MIN(E5,E10) -> 2 | F11: =MIN(F5,F10) -> 2 | G11: =MIN(G5,G10) -> 2 | H11: =MIN(H5,H10) -> 2 | I11: =MIN(I5,I10) -> 2 | ... Y11: =MIN(Y5,Y10) -> 0.65746958
A12: Abschlüsse kumuliert | B12: =0+B11 -> 1 | C12: =B12+C11 -> 2 | D12: =C12+D11 -> 4 | E12: =D12+E11 -> 6 | F12: =E12+F11 -> 8 | G12: =F12+G11 -> 10 | H12: =G12+H11 -> 12 | I12: =H12+I11 -> 14 | J12: =I12+J11 -> 16 | ... Y12: =X12+Y11 -> 32.010516
A14: Aktive Pflege-Kunden | B14: =0*(1-Annahmen!$B$17)+B11*Annahmen!$B$12/(1-Annahmen!$B$15*(1-B6)) -> 0.33333333 | C14: =B14*(1-Annahmen!$B$17)+C11*Annahmen!$B$12/(1-Annahmen!$B$15*(1-C6)) -> 0.66333333 | D14: =C14*(1-Annahmen!$B$17)+D11*Annahmen!$B$12/(1-Annahmen!$B$15*(1-D6)) -> 1.3233667 | E14: =D14*(1-Annahmen!$B$17)+E11*Annahmen!$B$12/(1-Annahmen!$B$15*(1-E6)) -> 1.9767997 | F14: =E14*(1-Annahmen!$B$17)+F11*Annahmen!$B$12/(1-Annahmen!$B$15*(1-F6)) -> 2.6236983 | G14: =F14*(1-Annahmen!$B$17)+G11*Annahmen!$B$12/(1-Annahmen!$B$15*(1-G6)) -> 3.264128 | H14: =G14*(1-Annahmen!$B$17)+H11*Annahmen!$B$12/(1-Annahmen!$B$15*(1-H6)) -> 3.8981534 | I14: =H14*(1-Annahmen!$B$17)+I11*Annahmen!$B$12/(1-Annahmen!$B$15*(1-I6)) -> 4.3591719 | J14: =I14*(1-Annahmen!$B$17)+J11*Annahmen!$B$12/(1-Annahmen!$B$15*(1-J6)) -> 4.8155802 | ... Y14: =X14*(1-Annahmen!$B$17)+Y11*Annahmen!$B$12/(1-Annahmen!$B$15*(1-Y6)) -> 7.8162486
A15: Aktive Programm-Kunden | B15: =0*(1-Annahmen!$B$18)+B11*Annahmen!$B$13/(1-Annahmen!$B$15*(1-B6)) -> 0.33333333 | C15: =B15*(1-Annahmen!$B$18)+C11*Annahmen!$B$13/(1-Annahmen!$B$15*(1-C6)) -> 0.66 | D15: =C15*(1-Annahmen!$B$18)+D11*Annahmen!$B$13/(1-Annahmen!$B$15*(1-D6)) -> 1.3134667 | E15: =D15*(1-Annahmen!$B$18)+E11*Annahmen!$B$13/(1-Annahmen!$B$15*(1-E6)) -> 1.953864 | F15: =E15*(1-Annahmen!$B$18)+F11*Annahmen!$B$13/(1-Annahmen!$B$15*(1-F6)) -> 2.5814534 | G15: =F15*(1-Annahmen!$B$18)+G11*Annahmen!$B$13/(1-Annahmen!$B$15*(1-G6)) -> 3.196491 | H15: =G15*(1-Annahmen!$B$18)+H11*Annahmen!$B$13/(1-Annahmen!$B$15*(1-H6)) -> 3.7992278 | I15: =H15*(1-Annahmen!$B$18)+I11*Annahmen!$B$13/(1-Annahmen!$B$15*(1-I6)) -> 4.2232433 | J15: =I15*(1-Annahmen!$B$18)+J11*Annahmen!$B$13/(1-Annahmen!$B$15*(1-J6)) -> 4.6387784 | ... Y15: =X15*(1-Annahmen!$B$18)+Y11*Annahmen!$B$13/(1-Annahmen!$B$15*(1-Y6)) -> 6.8030649
A16: Aktive SEO-Kunden | B16: =0*(1-Annahmen!$B$19)+B11*Annahmen!$B$14/(1-Annahmen!$B$15*(1-B6)) -> 0.33333333 | C16: =B16*(1-Annahmen!$B$19)+C11*Annahmen!$B$14/(1-Annahmen!$B$15*(1-C6)) -> 0.65666667 | D16: =C16*(1-Annahmen!$B$19)+D11*Annahmen!$B$14/(1-Annahmen!$B$15*(1-D6)) -> 1.3036333 | E16: =D16*(1-Annahmen!$B$19)+E11*Annahmen!$B$14/(1-Annahmen!$B$15*(1-E6)) -> 1.931191 | F16: =E16*(1-Annahmen!$B$19)+F11*Annahmen!$B$14/(1-Annahmen!$B$15*(1-F6)) -> 2.5399219 | G16: =F16*(1-Annahmen!$B$19)+G11*Annahmen!$B$14/(1-Annahmen!$B$15*(1-G6)) -> 3.1303909 | H16: =G16*(1-Annahmen!$B$19)+H11*Annahmen!$B$14/(1-Annahmen!$B$15*(1-H6)) -> 3.7031459 | I16: =H16*(1-Annahmen!$B$19)+I11*Annahmen!$B$14/(1-Annahmen!$B$15*(1-I6)) -> 4.0920515 | J16: =I16*(1-Annahmen!$B$19)+J11*Annahmen!$B$14/(1-Annahmen!$B$15*(1-J6)) -> 4.46929 | ... Y16: =X16*(1-Annahmen!$B$19)+Y11*Annahmen!$B$14/(1-Annahmen!$B$15*(1-Y6)) -> 5.9372817
A17: Aktive Recruiting-Kunden | B17: =0*(1-Annahmen!$B$20)+B11*Annahmen!$B$15*B6 -> 0 | C17: =B17*(1-Annahmen!$B$20)+C11*Annahmen!$B$15*C6 -> 0 | D17: =C17*(1-Annahmen!$B$20)+D11*Annahmen!$B$15*D6 -> 0 | E17: =D17*(1-Annahmen!$B$20)+E11*Annahmen!$B$15*E6 -> 0 | F17: =E17*(1-Annahmen!$B$20)+F11*Annahmen!$B$15*F6 -> 0 | G17: =F17*(1-Annahmen!$B$20)+G11*Annahmen!$B$15*G6 -> 0 | H17: =G17*(1-Annahmen!$B$20)+H11*Annahmen!$B$15*H6 -> 0 | I17: =H17*(1-Annahmen!$B$20)+I11*Annahmen!$B$15*I6 -> 0.5 | J17: =I17*(1-Annahmen!$B$20)+J11*Annahmen!$B$15*J6 -> 0.975 | ... Y17: =X17*(1-Annahmen!$B$20)+Y11*Annahmen!$B$15*Y6 -> 3.0918346
A19: MRR | B19: =B14*Annahmen!$B$6+B15*Annahmen!$B$7+B16*Annahmen!$B$9+B17*Annahmen!$B$10 -> 593 | C19: =C14*Annahmen!$B$6+C15*Annahmen!$B$7+C16*Annahmen!$B$9+C17*Annahmen!$B$10 -> 1172.6367 | D19: =D14*Annahmen!$B$6+D15*Annahmen!$B$7+D16*Annahmen!$B$9+D17*Annahmen!$B$10 -> 2332.227 | E19: =E14*Annahmen!$B$6+E15*Annahmen!$B$7+E16*Annahmen!$B$9+E17*Annahmen!$B$10 -> 3465.7167 | F19: =F14*Annahmen!$B$6+F15*Annahmen!$B$7+F16*Annahmen!$B$9+F17*Annahmen!$B$10 -> 4573.7241 | G19: =G14*Annahmen!$B$6+G15*Annahmen!$B$7+G16*Annahmen!$B$9+G17*Annahmen!$B$10 -> 5656.8524 | H19: =H14*Annahmen!$B$6+H15*Annahmen!$B$7+H16*Annahmen!$B$9+H17*Annahmen!$B$10 -> 6715.6896 | I19: =I14*Annahmen!$B$6+I15*Annahmen!$B$7+I16*Annahmen!$B$9+I17*Annahmen!$B$10 -> 7849.3091 | ... Y19: =Y14*Annahmen!$B$6+Y15*Annahmen!$B$7+Y16*Annahmen!$B$9+Y17*Annahmen!$B$10 -> 14164.904
A20: Einmalumsatz | B20: =B11*(Annahmen!$B$12/(1-Annahmen!$B$15*(1-B6))*Annahmen!$B$5+Annahmen!$B$13/(1-Annahmen!$B$15*(1-B6))*Annahmen!$B$8+Annahmen!$B$15*B6*Annahmen!$B$11) -> 1230 | C20: =C11*(Annahmen!$B$12/(1-Annahmen!$B$15*(1-C6))*Annahmen!$B$5+Annahmen!$B$13/(1-Annahmen!$B$15*(1-C6))*Annahmen!$B$8+Annahmen!$B$15*C6*Annahmen!$B$11) -> 1230 | D20: =D11*(Annahmen!$B$12/(1-Annahmen!$B$15*(1-D6))*Annahmen!$B$5+Annahmen!$B$13/(1-Annahmen!$B$15*(1-D6))*Annahmen!$B$8+Annahmen!$B$15*D6*Annahmen!$B$11) -> 2460 | E20: =E11*(Annahmen!$B$12/(1-Annahmen!$B$15*(1-E6))*Annahmen!$B$5+Annahmen!$B$13/(1-Annahmen!$B$15*(1-E6))*Annahmen!$B$8+Annahmen!$B$15*E6*Annahmen!$B$11) -> 2460 | F20: =F11*(Annahmen!$B$12/(1-Annahmen!$B$15*(1-F6))*Annahmen!$B$5+Annahmen!$B$13/(1-Annahmen!$B$15*(1-F6))*Annahmen!$B$8+Annahmen!$B$15*F6*Annahmen!$B$11) -> 2460 | G20: =G11*(Annahmen!$B$12/(1-Annahmen!$B$15*(1-G6))*Annahmen!$B$5+Annahmen!$B$13/(1-Annahmen!$B$15*(1-G6))*Annahmen!$B$8+Annahmen!$B$15*G6*Annahmen!$B$11) -> 2460 | H20: =H11*(Annahmen!$B$12/(1-Annahmen!$B$15*(1-H6))*Annahmen!$B$5+Annahmen!$B$13/(1-Annahmen!$B$15*(1-H6))*Annahmen!$B$8+Annahmen!$B$15*H6*Annahmen!$B$11) -> 2460 | I20: =I11*(Annahmen!$B$12/(1-Annahmen!$B$15*(1-I6))*Annahmen!$B$5+Annahmen!$B$13/(1-Annahmen!$B$15*(1-I6))*Annahmen!$B$8+Annahmen!$B$15*I6*Annahmen!$B$11) -> 2590 | ... Y20: =Y11*(Annahmen!$B$12/(1-Annahmen!$B$15*(1-Y6))*Annahmen!$B$5+Annahmen!$B$13/(1-Annahmen!$B$15*(1-Y6))*Annahmen!$B$8+Annahmen!$B$15*Y6*Annahmen!$B$11) -> 851.4231
A21: Umsatz | B21: =B19+B20 -> 1823 | C21: =C19+C20 -> 2402.6367 | D21: =D19+D20 -> 4792.227 | E21: =E19+E20 -> 5925.7167 | F21: =F19+F20 -> 7033.7241 | G21: =G19+G20 -> 8116.8524 | H21: =H19+H20 -> 9175.6896 | I21: =I19+I20 -> 10439.309 | ... Y21: =Y19+Y20 -> 15016.327
A22: Kosten | B22: =Annahmen!$B$42+Annahmen!$B$43+B7*Annahmen!$B$40 -> 355 | C22: =Annahmen!$B$42+Annahmen!$B$43+C7*Annahmen!$B$40 -> 355 | D22: =Annahmen!$B$42+Annahmen!$B$43+D7*Annahmen!$B$40 -> 355 | E22: =Annahmen!$B$42+Annahmen!$B$43+E7*Annahmen!$B$40 -> 355 | F22: =Annahmen!$B$42+Annahmen!$B$43+F7*Annahmen!$B$40 -> 355 | G22: =Annahmen!$B$42+Annahmen!$B$43+G7*Annahmen!$B$40 -> 355 | H22: =Annahmen!$B$42+Annahmen!$B$43+H7*Annahmen!$B$40 -> 355 | I22: =Annahmen!$B$42+Annahmen!$B$43+I7*Annahmen!$B$40 -> 355 | ... Y22: =Annahmen!$B$42+Annahmen!$B$43+Y7*Annahmen!$B$40 -> 355
A23: Ergebnis vor Steuern (= Einkommen Gründer) | B23: =B21-B22 -> 1468 | C23: =C21-C22 -> 2047.6367 | D23: =D21-D22 -> 4437.227 | E23: =E21-E22 -> 5570.7167 | F23: =F21-F22 -> 6678.7241 | G23: =G21-G22 -> 7761.8524 | H23: =H21-H22 -> 8820.6896 | I23: =I21-I22 -> 10084.309 | ... Y23: =Y21-Y22 -> 14661.327
A24: Kasse kumuliert | B24: =B23 -> 1468 | C24: =B24+C23 -> 3515.6367 | D24: =C24+D23 -> 7952.8636 | E24: =D24+E23 -> 13523.58 | F24: =E24+F23 -> 20202.304 | G24: =F24+G23 -> 27964.157 | H24: =G24+H23 -> 36784.846 | I24: =H24+I23 -> 46869.156 | J24: =I24+J23 -> 58050.858 | ... Y24: =X24+Y23 -> 268701.85
A25: Belegte Stunden | B25: =B9+B11*B8 -> 37.083333 | C25: =C9+C11*C8 -> 43.5 | D25: =D9+D11*D8 -> 86.8525 | E25: =E9+E11*E8 -> 99.394375 | F25: =F9+F11*F8 -> 111.64824 | G25: =G9+G11*G8 -> 123.62102 | H25: =H9+H11*H8 -> 135.31943 | I25: =I9+I11*I8 -> 141.70838 | ... Y25: =Y9+Y11*Y8 -> 170

Sheet Solo Konservativ auto
A1: Solo-Plan · Szenario Konservativ · automatisiert ab Kunde 5 (24 Monate ab Nov 2026)
A2: Abschlüsse = Minimum aus Vertriebstempo und freien Stunden. Kundenzahlen sind Erwartungswerte.
A4: Monat | B4: Nov 26 | C4: Dez 26 | D4: Jan 27 | E4: Feb 27 | F4: Mär 27 | G4: Apr 27 | H4: Mai 27 | I4: Jun 27 | J4: Jul 27 | K4: Aug 27 | L4: Sep 27 | M4: Okt 27 | N4: Nov 27 | O4: Dez 27 | P4: Jan 28 | Q4: Feb 28 | R4: Mär 28 | S4: Apr 28 | T4: Mai 28 | U4: Jun 28 | V4: Jul 28 | W4: Aug 28 | X4: Sep 28 | Y4: Okt 28
A5: Abschluss-Ziel (Vertrieb) | B5: =Annahmen!$B$48 -> 1 | C5: =Annahmen!$B$48 -> 1 | D5: =Annahmen!$B$49 -> 2 | E5: =Annahmen!$B$49 -> 2 | F5: =Annahmen!$B$49 -> 2 | G5: =Annahmen!$B$49 -> 2 | H5: =Annahmen!$B$49 -> 2 | I5: =Annahmen!$B$49 -> 2 | J5: =Annahmen!$B$49 -> 2 | K5: =Annahmen!$B$49 -> 2 | ... Y5: =Annahmen!$B$49 -> 2
A6: Recruiting im Verkauf (1 = ja) | B6: =IF(1>=Annahmen!$B$16,1,0) -> 0 | C6: =IF(2>=Annahmen!$B$16,1,0) -> 0 | D6: =IF(3>=Annahmen!$B$16,1,0) -> 0 | E6: =IF(4>=Annahmen!$B$16,1,0) -> 0 | F6: =IF(5>=Annahmen!$B$16,1,0) -> 0 | G6: =IF(6>=Annahmen!$B$16,1,0) -> 0 | H6: =IF(7>=Annahmen!$B$16,1,0) -> 0 | I6: =IF(8>=Annahmen!$B$16,1,0) -> 1 | J6: =IF(9>=Annahmen!$B$16,1,0) -> 1 | K6: =IF(10>=Annahmen!$B$16,1,0) -> 1 | L6: =IF(11>=Annahmen!$B$16,1,0) -> 1 | M6: =IF(12>=Annahmen!$B$16,1,0) -> 1 | N6: =IF(13>=Annahmen!$B$16,1,0) -> 1 | O6: =IF(14>=Annahmen!$B$16,1,0) -> 1 | P6: =IF(15>=Annahmen!$B$16,1,0) -> 1 | Q6: =IF(16>=Annahmen!$B$16,1,0) -> 1 | R6: =IF(17>=Annahmen!$B$16,1,0) -> 1 | S6: =IF(18>=Annahmen!$B$16,1,0) -> 1 | T6: =IF(19>=Annahmen!$B$16,1,0) -> 1 | U6: =IF(20>=Annahmen!$B$16,1,0) -> 1 | V6: =IF(21>=Annahmen!$B$16,1,0) -> 1 | W6: =IF(22>=Annahmen!$B$16,1,0) -> 1 | X6: =IF(23>=Annahmen!$B$16,1,0) -> 1 | Y6: =IF(24>=Annahmen!$B$16,1,0) -> 1
A7: Automatisierung aktiv (1 = ja) | B7: =IF(0>=Annahmen!$B$39-1,1,0) -> 0 | C7: =IF(B12>=Annahmen!$B$39-1,1,0) -> 0 | D7: =IF(C12>=Annahmen!$B$39-1,1,0) -> 0 | E7: =IF(D12>=Annahmen!$B$39-1,1,0) -> 1 | F7: =IF(E12>=Annahmen!$B$39-1,1,0) -> 1 | G7: =IF(F12>=Annahmen!$B$39-1,1,0) -> 1 | H7: =IF(G12>=Annahmen!$B$39-1,1,0) -> 1 | I7: =IF(H12>=Annahmen!$B$39-1,1,0) -> 1 | J7: =IF(I12>=Annahmen!$B$39-1,1,0) -> 1 | ... Y7: =IF(X12>=Annahmen!$B$39-1,1,0) -> 1
A8: Std. je neuem Abschluss | B8: =Annahmen!$B$12/(1-Annahmen!$B$15*(1-B6))*((Annahmen!$B$21+B7*(Annahmen!$B$30-Annahmen!$B$21))+(Annahmen!$B$25+B7*(Annahmen!$B$34-Annahmen!$B$25))+(Annahmen!$B$29+B7*(Annahmen!$B$38-Annahmen!$B$29)))+Annahmen!$B$13/(1-Annahmen!$B$15*(1-B6))*((Annahmen!$B$22+B7*(Annahmen!$B$31-Annahmen!$B$22))+(Annahmen!$B$26+B7*(Annahmen!$B$35-Annahmen!$B$26))+(Annahmen!$B$29+B7*(Annahmen!$B$38-Annahmen!$B$29)))+Annahmen!$B$14/(1-Annahmen!$B$15*(1-B6))*((Annahmen!$B$23+B7*(Annahmen!$B$32-Annahmen!$B$23))+(Annahmen!$B$27+B7*(Annahmen!$B$36-Annahmen!$B$27))+(Annahmen!$B$29+B7*(Annahmen!$B$38-Annahmen!$B$29)))+Annahmen!$B$15*B6*((Annahmen!$B$24+B7*(Annahmen!$B$33-Annahmen!$B$24))+(Annahmen!$B$28+B7*(Annahmen!$B$37-Annahmen!$B$28))+(Annahmen!$B$29+B7*(Annahmen!$B$38-Annahmen!$B$29))) -> 37.083333 | C8: =Annahmen!$B$12/(1-Annahmen!$B$15*(1-C6))*((Annahmen!$B$21+C7*(Annahmen!$B$30-Annahmen!$B$21))+(Annahmen!$B$25+C7*(Annahmen!$B$34-Annahmen!$B$25))+(Annahmen!$B$29+C7*(Annahmen!$B$38-Annahmen!$B$29)))+Annahmen!$B$13/(1-Annahmen!$B$15*(1-C6))*((Annahmen!$B$22+C7*(Annahmen!$B$31-Annahmen!$B$22))+(Annahmen!$B$26+C7*(Annahmen!$B$35-Annahmen!$B$26))+(Annahmen!$B$29+C7*(Annahmen!$B$38-Annahmen!$B$29)))+Annahmen!$B$14/(1-Annahmen!$B$15*(1-C6))*((Annahmen!$B$23+C7*(Annahmen!$B$32-Annahmen!$B$23))+(Annahmen!$B$27+C7*(Annahmen!$B$36-Annahmen!$B$27))+(Annahmen!$B$29+C7*(Annahmen!$B$38-Annahmen!$B$29)))+Annahmen!$B$15*C6*((Annahmen!$B$24+C7*(Annahmen!$B$33-Annahmen!$B$24))+(Annahmen!$B$28+C7*(Annahmen!$B$37-Annahmen!$B$28))+(Annahmen!$B$29+C7*(Annahmen!$B$38-Annahmen!$B$29))) -> 37.083333 | D8: =Annahmen!$B$12/(1-Annahmen!$B$15*(1-D6))*((Annahmen!$B$21+D7*(Annahmen!$B$30-Annahmen!$B$21))+(Annahmen!$B$25+D7*(Annahmen!$B$34-Annahmen!$B$25))+(Annahmen!$B$29+D7*(Annahmen!$B$38-Annahmen!$B$29)))+Annahmen!$B$13/(1-Annahmen!$B$15*(1-D6))*((Annahmen!$B$22+D7*(Annahmen!$B$31-Annahmen!$B$22))+(Annahmen!$B$26+D7*(Annahmen!$B$35-Annahmen!$B$26))+(Annahmen!$B$29+D7*(Annahmen!$B$38-Annahmen!$B$29)))+Annahmen!$B$14/(1-Annahmen!$B$15*(1-D6))*((Annahmen!$B$23+D7*(Annahmen!$B$32-Annahmen!$B$23))+(Annahmen!$B$27+D7*(Annahmen!$B$36-Annahmen!$B$27))+(Annahmen!$B$29+D7*(Annahmen!$B$38-Annahmen!$B$29)))+Annahmen!$B$15*D6*((Annahmen!$B$24+D7*(Annahmen!$B$33-Annahmen!$B$24))+(Annahmen!$B$28+D7*(Annahmen!$B$37-Annahmen!$B$28))+(Annahmen!$B$29+D7*(Annahmen!$B$38-Annahmen!$B$29))) -> 37.083333 | E8: =Annahmen!$B$12/(1-Annahmen!$B$15*(1-E6))*((Annahmen!$B$21+E7*(Annahmen!$B$30-Annahmen!$B$21))+(Annahmen!$B$25+E7*(Annahmen!$B$34-Annahmen!$B$25))+(Annahmen!$B$29+E7*(Annahmen!$B$38-Annahmen!$B$29)))+Annahmen!$B$13/(1-Annahmen!$B$15*(1-E6))*((Annahmen!$B$22+E7*(Annahmen!$B$31-Annahmen!$B$22))+(Annahmen!$B$26+E7*(Annahmen!$B$35-Annahmen!$B$26))+(Annahmen!$B$29+E7*(Annahmen!$B$38-Annahmen!$B$29)))+Annahmen!$B$14/(1-Annahmen!$B$15*(1-E6))*((Annahmen!$B$23+E7*(Annahmen!$B$32-Annahmen!$B$23))+(Annahmen!$B$27+E7*(Annahmen!$B$36-Annahmen!$B$27))+(Annahmen!$B$29+E7*(Annahmen!$B$38-Annahmen!$B$29)))+Annahmen!$B$15*E6*((Annahmen!$B$24+E7*(Annahmen!$B$33-Annahmen!$B$24))+(Annahmen!$B$28+E7*(Annahmen!$B$37-Annahmen!$B$28))+(Annahmen!$B$29+E7*(Annahmen!$B$38-Annahmen!$B$29))) -> 19.033333 | F8: =Annahmen!$B$12/(1-Annahmen!$B$15*(1-F6))*((Annahmen!$B$21+F7*(Annahmen!$B$30-Annahmen!$B$21))+(Annahmen!$B$25+F7*(Annahmen!$B$34-Annahmen!$B$25))+(Annahmen!$B$29+F7*(Annahmen!$B$38-Annahmen!$B$29)))+Annahmen!$B$13/(1-Annahmen!$B$15*(1-F6))*((Annahmen!$B$22+F7*(Annahmen!$B$31-Annahmen!$B$22))+(Annahmen!$B$26+F7*(Annahmen!$B$35-Annahmen!$B$26))+(Annahmen!$B$29+F7*(Annahmen!$B$38-Annahmen!$B$29)))+Annahmen!$B$14/(1-Annahmen!$B$15*(1-F6))*((Annahmen!$B$23+F7*(Annahmen!$B$32-Annahmen!$B$23))+(Annahmen!$B$27+F7*(Annahmen!$B$36-Annahmen!$B$27))+(Annahmen!$B$29+F7*(Annahmen!$B$38-Annahmen!$B$29)))+Annahmen!$B$15*F6*((Annahmen!$B$24+F7*(Annahmen!$B$33-Annahmen!$B$24))+(Annahmen!$B$28+F7*(Annahmen!$B$37-Annahmen!$B$28))+(Annahmen!$B$29+F7*(Annahmen!$B$38-Annahmen!$B$29))) -> 19.033333 | G8: =Annahmen!$B$12/(1-Annahmen!$B$15*(1-G6))*((Annahmen!$B$21+G7*(Annahmen!$B$30-Annahmen!$B$21))+(Annahmen!$B$25+G7*(Annahmen!$B$34-Annahmen!$B$25))+(Annahmen!$B$29+G7*(Annahmen!$B$38-Annahmen!$B$29)))+Annahmen!$B$13/(1-Annahmen!$B$15*(1-G6))*((Annahmen!$B$22+G7*(Annahmen!$B$31-Annahmen!$B$22))+(Annahmen!$B$26+G7*(Annahmen!$B$35-Annahmen!$B$26))+(Annahmen!$B$29+G7*(Annahmen!$B$38-Annahmen!$B$29)))+Annahmen!$B$14/(1-Annahmen!$B$15*(1-G6))*((Annahmen!$B$23+G7*(Annahmen!$B$32-Annahmen!$B$23))+(Annahmen!$B$27+G7*(Annahmen!$B$36-Annahmen!$B$27))+(Annahmen!$B$29+G7*(Annahmen!$B$38-Annahmen!$B$29)))+Annahmen!$B$15*G6*((Annahmen!$B$24+G7*(Annahmen!$B$33-Annahmen!$B$24))+(Annahmen!$B$28+G7*(Annahmen!$B$37-Annahmen!$B$28))+(Annahmen!$B$29+G7*(Annahmen!$B$38-Annahmen!$B$29))) -> 19.033333 | H8: =Annahmen!$B$12/(1-Annahmen!$B$15*(1-H6))*((Annahmen!$B$21+H7*(Annahmen!$B$30-Annahmen!$B$21))+(Annahmen!$B$25+H7*(Annahmen!$B$34-Annahmen!$B$25))+(Annahmen!$B$29+H7*(Annahmen!$B$38-Annahmen!$B$29)))+Annahmen!$B$13/(1-Annahmen!$B$15*(1-H6))*((Annahmen!$B$22+H7*(Annahmen!$B$31-Annahmen!$B$22))+(Annahmen!$B$26+H7*(Annahmen!$B$35-Annahmen!$B$26))+(Annahmen!$B$29+H7*(Annahmen!$B$38-Annahmen!$B$29)))+Annahmen!$B$14/(1-Annahmen!$B$15*(1-H6))*((Annahmen!$B$23+H7*(Annahmen!$B$32-Annahmen!$B$23))+(Annahmen!$B$27+H7*(Annahmen!$B$36-Annahmen!$B$27))+(Annahmen!$B$29+H7*(Annahmen!$B$38-Annahmen!$B$29)))+Annahmen!$B$15*H6*((Annahmen!$B$24+H7*(Annahmen!$B$33-Annahmen!$B$24))+(Annahmen!$B$28+H7*(Annahmen!$B$37-Annahmen!$B$28))+(Annahmen!$B$29+H7*(Annahmen!$B$38-Annahmen!$B$29))) -> 19.033333 | I8: =Annahmen!$B$12/(1-Annahmen!$B$15*(1-I6))*((Annahmen!$B$21+I7*(Annahmen!$B$30-Annahmen!$B$21))+(Annahmen!$B$25+I7*(Annahmen!$B$34-Annahmen!$B$25))+(Annahmen!$B$29+I7*(Annahmen!$B$38-Annahmen!$B$29)))+Annahmen!$B$13/(1-Annahmen!$B$15*(1-I6))*((Annahmen!$B$22+I7*(Annahmen!$B$31-Annahmen!$B$22))+(Annahmen!$B$26+I7*(Annahmen!$B$35-Annahmen!$B$26))+(Annahmen!$B$29+I7*(Annahmen!$B$38-Annahmen!$B$29)))+Annahmen!$B$14/(1-Annahmen!$B$15*(1-I6))*((Annahmen!$B$23+I7*(Annahmen!$B$32-Annahmen!$B$23))+(Annahmen!$B$27+I7*(Annahmen!$B$36-Annahmen!$B$27))+(Annahmen!$B$29+I7*(Annahmen!$B$38-Annahmen!$B$29)))+Annahmen!$B$15*I6*((Annahmen!$B$24+I7*(Annahmen!$B$33-Annahmen!$B$24))+(Annahmen!$B$28+I7*(Annahmen!$B$37-Annahmen!$B$28))+(Annahmen!$B$29+I7*(Annahmen!$B$38-Annahmen!$B$29))) -> 18.275 | ... Y8: =Annahmen!$B$12/(1-Annahmen!$B$15*(1-Y6))*((Annahmen!$B$21+Y7*(Annahmen!$B$30-Annahmen!$B$21))+(Annahmen!$B$25+Y7*(Annahmen!$B$34-Annahmen!$B$25))+(Annahmen!$B$29+Y7*(Annahmen!$B$38-Annahmen!$B$29)))+Annahmen!$B$13/(1-Annahmen!$B$15*(1-Y6))*((Annahmen!$B$22+Y7*(Annahmen!$B$31-Annahmen!$B$22))+(Annahmen!$B$26+Y7*(Annahmen!$B$35-Annahmen!$B$26))+(Annahmen!$B$29+Y7*(Annahmen!$B$38-Annahmen!$B$29)))+Annahmen!$B$14/(1-Annahmen!$B$15*(1-Y6))*((Annahmen!$B$23+Y7*(Annahmen!$B$32-Annahmen!$B$23))+(Annahmen!$B$27+Y7*(Annahmen!$B$36-Annahmen!$B$27))+(Annahmen!$B$29+Y7*(Annahmen!$B$38-Annahmen!$B$29)))+Annahmen!$B$15*Y6*((Annahmen!$B$24+Y7*(Annahmen!$B$33-Annahmen!$B$24))+(Annahmen!$B$28+Y7*(Annahmen!$B$37-Annahmen!$B$28))+(Annahmen!$B$29+Y7*(Annahmen!$B$38-Annahmen!$B$29))) -> 18.275
A9: Laufende Stunden (Bestand) | B9: =0*(Annahmen!$B$25+B7*(Annahmen!$B$34-Annahmen!$B$25))+0*(Annahmen!$B$26+B7*(Annahmen!$B$35-Annahmen!$B$26))+0*(Annahmen!$B$27+B7*(Annahmen!$B$36-Annahmen!$B$27))+0*(Annahmen!$B$28+B7*(Annahmen!$B$37-Annahmen!$B$28)) -> 0 | C9: =B14*(Annahmen!$B$25+C7*(Annahmen!$B$34-Annahmen!$B$25))+B15*(Annahmen!$B$26+C7*(Annahmen!$B$35-Annahmen!$B$26))+B16*(Annahmen!$B$27+C7*(Annahmen!$B$36-Annahmen!$B$27))+B17*(Annahmen!$B$28+C7*(Annahmen!$B$37-Annahmen!$B$28)) -> 6.4166667 | D9: =C14*(Annahmen!$B$25+D7*(Annahmen!$B$34-Annahmen!$B$25))+C15*(Annahmen!$B$26+D7*(Annahmen!$B$35-Annahmen!$B$26))+C16*(Annahmen!$B$27+D7*(Annahmen!$B$36-Annahmen!$B$27))+C17*(Annahmen!$B$28+D7*(Annahmen!$B$37-Annahmen!$B$28)) -> 12.685833 | E9: =D14*(Annahmen!$B$25+E7*(Annahmen!$B$34-Annahmen!$B$25))+D15*(Annahmen!$B$26+E7*(Annahmen!$B$35-Annahmen!$B$26))+D16*(Annahmen!$B$27+E7*(Annahmen!$B$36-Annahmen!$B$27))+D17*(Annahmen!$B$28+E7*(Annahmen!$B$37-Annahmen!$B$28)) -> 13.237503 | F9: =E14*(Annahmen!$B$25+F7*(Annahmen!$B$34-Annahmen!$B$25))+E15*(Annahmen!$B$26+F7*(Annahmen!$B$35-Annahmen!$B$26))+E16*(Annahmen!$B$27+F7*(Annahmen!$B$36-Annahmen!$B$27))+E17*(Annahmen!$B$28+F7*(Annahmen!$B$37-Annahmen!$B$28)) -> 19.668301 | G9: =F14*(Annahmen!$B$25+G7*(Annahmen!$B$34-Annahmen!$B$25))+F15*(Annahmen!$B$26+G7*(Annahmen!$B$35-Annahmen!$B$26))+F16*(Annahmen!$B$27+G7*(Annahmen!$B$36-Annahmen!$B$27))+F17*(Annahmen!$B$28+G7*(Annahmen!$B$37-Annahmen!$B$28)) -> 25.952309 | H9: =G14*(Annahmen!$B$25+H7*(Annahmen!$B$34-Annahmen!$B$25))+G15*(Annahmen!$B$26+H7*(Annahmen!$B$35-Annahmen!$B$26))+G16*(Annahmen!$B$27+H7*(Annahmen!$B$36-Annahmen!$B$27))+G17*(Annahmen!$B$28+H7*(Annahmen!$B$37-Annahmen!$B$28)) -> 32.093023 | I9: =H14*(Annahmen!$B$25+I7*(Annahmen!$B$34-Annahmen!$B$25))+H15*(Annahmen!$B$26+I7*(Annahmen!$B$35-Annahmen!$B$26))+H16*(Annahmen!$B$27+I7*(Annahmen!$B$36-Annahmen!$B$27))+H17*(Annahmen!$B$28+I7*(Annahmen!$B$37-Annahmen!$B$28)) -> 38.093848 | J9: =I14*(Annahmen!$B$25+J7*(Annahmen!$B$34-Annahmen!$B$25))+I15*(Annahmen!$B$26+J7*(Annahmen!$B$35-Annahmen!$B$26))+I16*(Annahmen!$B$27+J7*(Annahmen!$B$36-Annahmen!$B$27))+I17*(Annahmen!$B$28+J7*(Annahmen!$B$37-Annahmen!$B$28)) -> 44.274775 | ... Y9: =X14*(Annahmen!$B$25+Y7*(Annahmen!$B$34-Annahmen!$B$25))+X15*(Annahmen!$B$26+Y7*(Annahmen!$B$35-Annahmen!$B$26))+X16*(Annahmen!$B$27+Y7*(Annahmen!$B$36-Annahmen!$B$27))+X17*(Annahmen!$B$28+Y7*(Annahmen!$B$37-Annahmen!$B$28)) -> 117.16539
A10: Möglich nach Stunden | B10: =MAX(0,(Annahmen!$B$41-B9)/B8) -> 4.5842697 | C10: =MAX(0,(Annahmen!$B$41-C9)/C8) -> 4.411236 | D10: =MAX(0,(Annahmen!$B$41-D9)/D8) -> 4.2421798 | E10: =MAX(0,(Annahmen!$B$41-E9)/E8) -> 8.2362082 | F10: =MAX(0,(Annahmen!$B$41-F9)/F8) -> 7.898338 | G10: =MAX(0,(Annahmen!$B$41-G9)/G8) -> 7.5681799 | H10: =MAX(0,(Annahmen!$B$41-H9)/H8) -> 7.2455505 | I10: =MAX(0,(Annahmen!$B$41-I9)/I8) -> 7.2178469 | ... Y10: =MAX(0,(Annahmen!$B$41-Y9)/Y8) -> 2.8910866
A11: Abschlüsse | B11: =MIN(B5,B10) -> 1 | C11: =MIN(C5,C10) -> 1 | D11: =MIN(D5,D10) -> 2 | E11: =MIN(E5,E10) -> 2 | F11: =MIN(F5,F10) -> 2 | G11: =MIN(G5,G10) -> 2 | H11: =MIN(H5,H10) -> 2 | I11: =MIN(I5,I10) -> 2 | ... Y11: =MIN(Y5,Y10) -> 2
A12: Abschlüsse kumuliert | B12: =0+B11 -> 1 | C12: =B12+C11 -> 2 | D12: =C12+D11 -> 4 | E12: =D12+E11 -> 6 | F12: =E12+F11 -> 8 | G12: =F12+G11 -> 10 | H12: =G12+H11 -> 12 | I12: =H12+I11 -> 14 | J12: =I12+J11 -> 16 | ... Y12: =X12+Y11 -> 46
A14: Aktive Pflege-Kunden | B14: =0*(1-Annahmen!$B$17)+B11*Annahmen!$B$12/(1-Annahmen!$B$15*(1-B6)) -> 0.33333333 | C14: =B14*(1-Annahmen!$B$17)+C11*Annahmen!$B$12/(1-Annahmen!$B$15*(1-C6)) -> 0.66333333 | D14: =C14*(1-Annahmen!$B$17)+D11*Annahmen!$B$12/(1-Annahmen!$B$15*(1-D6)) -> 1.3233667 | E14: =D14*(1-Annahmen!$B$17)+E11*Annahmen!$B$12/(1-Annahmen!$B$15*(1-E6)) -> 1.9767997 | F14: =E14*(1-Annahmen!$B$17)+F11*Annahmen!$B$12/(1-Annahmen!$B$15*(1-F6)) -> 2.6236983 | G14: =F14*(1-Annahmen!$B$17)+G11*Annahmen!$B$12/(1-Annahmen!$B$15*(1-G6)) -> 3.264128 | H14: =G14*(1-Annahmen!$B$17)+H11*Annahmen!$B$12/(1-Annahmen!$B$15*(1-H6)) -> 3.8981534 | I14: =H14*(1-Annahmen!$B$17)+I11*Annahmen!$B$12/(1-Annahmen!$B$15*(1-I6)) -> 4.3591719 | J14: =I14*(1-Annahmen!$B$17)+J11*Annahmen!$B$12/(1-Annahmen!$B$15*(1-J6)) -> 4.8155802 | ... Y14: =X14*(1-Annahmen!$B$17)+Y11*Annahmen!$B$12/(1-Annahmen!$B$15*(1-Y6)) -> 11.138762
A15: Aktive Programm-Kunden | B15: =0*(1-Annahmen!$B$18)+B11*Annahmen!$B$13/(1-Annahmen!$B$15*(1-B6)) -> 0.33333333 | C15: =B15*(1-Annahmen!$B$18)+C11*Annahmen!$B$13/(1-Annahmen!$B$15*(1-C6)) -> 0.66 | D15: =C15*(1-Annahmen!$B$18)+D11*Annahmen!$B$13/(1-Annahmen!$B$15*(1-D6)) -> 1.3134667 | E15: =D15*(1-Annahmen!$B$18)+E11*Annahmen!$B$13/(1-Annahmen!$B$15*(1-E6)) -> 1.953864 | F15: =E15*(1-Annahmen!$B$18)+F11*Annahmen!$B$13/(1-Annahmen!$B$15*(1-F6)) -> 2.5814534 | G15: =F15*(1-Annahmen!$B$18)+G11*Annahmen!$B$13/(1-Annahmen!$B$15*(1-G6)) -> 3.196491 | H15: =G15*(1-Annahmen!$B$18)+H11*Annahmen!$B$13/(1-Annahmen!$B$15*(1-H6)) -> 3.7992278 | I15: =H15*(1-Annahmen!$B$18)+I11*Annahmen!$B$13/(1-Annahmen!$B$15*(1-I6)) -> 4.2232433 | J15: =I15*(1-Annahmen!$B$18)+J11*Annahmen!$B$13/(1-Annahmen!$B$15*(1-J6)) -> 4.6387784 | ... Y15: =X15*(1-Annahmen!$B$18)+Y11*Annahmen!$B$13/(1-Annahmen!$B$15*(1-Y6)) -> 9.9618308
A16: Aktive SEO-Kunden | B16: =0*(1-Annahmen!$B$19)+B11*Annahmen!$B$14/(1-Annahmen!$B$15*(1-B6)) -> 0.33333333 | C16: =B16*(1-Annahmen!$B$19)+C11*Annahmen!$B$14/(1-Annahmen!$B$15*(1-C6)) -> 0.65666667 | D16: =C16*(1-Annahmen!$B$19)+D11*Annahmen!$B$14/(1-Annahmen!$B$15*(1-D6)) -> 1.3036333 | E16: =D16*(1-Annahmen!$B$19)+E11*Annahmen!$B$14/(1-Annahmen!$B$15*(1-E6)) -> 1.931191 | F16: =E16*(1-Annahmen!$B$19)+F11*Annahmen!$B$14/(1-Annahmen!$B$15*(1-F6)) -> 2.5399219 | G16: =F16*(1-Annahmen!$B$19)+G11*Annahmen!$B$14/(1-Annahmen!$B$15*(1-G6)) -> 3.1303909 | H16: =G16*(1-Annahmen!$B$19)+H11*Annahmen!$B$14/(1-Annahmen!$B$15*(1-H6)) -> 3.7031459 | I16: =H16*(1-Annahmen!$B$19)+I11*Annahmen!$B$14/(1-Annahmen!$B$15*(1-I6)) -> 4.0920515 | J16: =I16*(1-Annahmen!$B$19)+J11*Annahmen!$B$14/(1-Annahmen!$B$15*(1-J6)) -> 4.46929 | ... Y16: =X16*(1-Annahmen!$B$19)+Y11*Annahmen!$B$14/(1-Annahmen!$B$15*(1-Y6)) -> 8.9426634
A17: Aktive Recruiting-Kunden | B17: =0*(1-Annahmen!$B$20)+B11*Annahmen!$B$15*B6 -> 0 | C17: =B17*(1-Annahmen!$B$20)+C11*Annahmen!$B$15*C6 -> 0 | D17: =C17*(1-Annahmen!$B$20)+D11*Annahmen!$B$15*D6 -> 0 | E17: =D17*(1-Annahmen!$B$20)+E11*Annahmen!$B$15*E6 -> 0 | F17: =E17*(1-Annahmen!$B$20)+F11*Annahmen!$B$15*F6 -> 0 | G17: =F17*(1-Annahmen!$B$20)+G11*Annahmen!$B$15*G6 -> 0 | H17: =G17*(1-Annahmen!$B$20)+H11*Annahmen!$B$15*H6 -> 0 | I17: =H17*(1-Annahmen!$B$20)+I11*Annahmen!$B$15*I6 -> 0.5 | J17: =I17*(1-Annahmen!$B$20)+J11*Annahmen!$B$15*J6 -> 0.975 | ... Y17: =X17*(1-Annahmen!$B$20)+Y11*Annahmen!$B$15*Y6 -> 5.8187966
A19: MRR | B19: =B14*Annahmen!$B$6+B15*Annahmen!$B$7+B16*Annahmen!$B$9+B17*Annahmen!$B$10 -> 593 | C19: =C14*Annahmen!$B$6+C15*Annahmen!$B$7+C16*Annahmen!$B$9+C17*Annahmen!$B$10 -> 1172.6367 | D19: =D14*Annahmen!$B$6+D15*Annahmen!$B$7+D16*Annahmen!$B$9+D17*Annahmen!$B$10 -> 2332.227 | E19: =E14*Annahmen!$B$6+E15*Annahmen!$B$7+E16*Annahmen!$B$9+E17*Annahmen!$B$10 -> 3465.7167 | F19: =F14*Annahmen!$B$6+F15*Annahmen!$B$7+F16*Annahmen!$B$9+F17*Annahmen!$B$10 -> 4573.7241 | G19: =G14*Annahmen!$B$6+G15*Annahmen!$B$7+G16*Annahmen!$B$9+G17*Annahmen!$B$10 -> 5656.8524 | H19: =H14*Annahmen!$B$6+H15*Annahmen!$B$7+H16*Annahmen!$B$9+H17*Annahmen!$B$10 -> 6715.6896 | I19: =I14*Annahmen!$B$6+I15*Annahmen!$B$7+I16*Annahmen!$B$9+I17*Annahmen!$B$10 -> 7849.3091 | ... Y19: =Y14*Annahmen!$B$6+Y15*Annahmen!$B$7+Y16*Annahmen!$B$9+Y17*Annahmen!$B$10 -> 21870.188
A20: Einmalumsatz | B20: =B11*(Annahmen!$B$12/(1-Annahmen!$B$15*(1-B6))*Annahmen!$B$5+Annahmen!$B$13/(1-Annahmen!$B$15*(1-B6))*Annahmen!$B$8+Annahmen!$B$15*B6*Annahmen!$B$11) -> 1230 | C20: =C11*(Annahmen!$B$12/(1-Annahmen!$B$15*(1-C6))*Annahmen!$B$5+Annahmen!$B$13/(1-Annahmen!$B$15*(1-C6))*Annahmen!$B$8+Annahmen!$B$15*C6*Annahmen!$B$11) -> 1230 | D20: =D11*(Annahmen!$B$12/(1-Annahmen!$B$15*(1-D6))*Annahmen!$B$5+Annahmen!$B$13/(1-Annahmen!$B$15*(1-D6))*Annahmen!$B$8+Annahmen!$B$15*D6*Annahmen!$B$11) -> 2460 | E20: =E11*(Annahmen!$B$12/(1-Annahmen!$B$15*(1-E6))*Annahmen!$B$5+Annahmen!$B$13/(1-Annahmen!$B$15*(1-E6))*Annahmen!$B$8+Annahmen!$B$15*E6*Annahmen!$B$11) -> 2460 | F20: =F11*(Annahmen!$B$12/(1-Annahmen!$B$15*(1-F6))*Annahmen!$B$5+Annahmen!$B$13/(1-Annahmen!$B$15*(1-F6))*Annahmen!$B$8+Annahmen!$B$15*F6*Annahmen!$B$11) -> 2460 | G20: =G11*(Annahmen!$B$12/(1-Annahmen!$B$15*(1-G6))*Annahmen!$B$5+Annahmen!$B$13/(1-Annahmen!$B$15*(1-G6))*Annahmen!$B$8+Annahmen!$B$15*G6*Annahmen!$B$11) -> 2460 | H20: =H11*(Annahmen!$B$12/(1-Annahmen!$B$15*(1-H6))*Annahmen!$B$5+Annahmen!$B$13/(1-Annahmen!$B$15*(1-H6))*Annahmen!$B$8+Annahmen!$B$15*H6*Annahmen!$B$11) -> 2460 | I20: =I11*(Annahmen!$B$12/(1-Annahmen!$B$15*(1-I6))*Annahmen!$B$5+Annahmen!$B$13/(1-Annahmen!$B$15*(1-I6))*Annahmen!$B$8+Annahmen!$B$15*I6*Annahmen!$B$11) -> 2590 | ... Y20: =Y11*(Annahmen!$B$12/(1-Annahmen!$B$15*(1-Y6))*Annahmen!$B$5+Annahmen!$B$13/(1-Annahmen!$B$15*(1-Y6))*Annahmen!$B$8+Annahmen!$B$15*Y6*Annahmen!$B$11) -> 2590
A21: Umsatz | B21: =B19+B20 -> 1823 | C21: =C19+C20 -> 2402.6367 | D21: =D19+D20 -> 4792.227 | E21: =E19+E20 -> 5925.7167 | F21: =F19+F20 -> 7033.7241 | G21: =G19+G20 -> 8116.8524 | H21: =H19+H20 -> 9175.6896 | I21: =I19+I20 -> 10439.309 | ... Y21: =Y19+Y20 -> 24460.188
A22: Kosten | B22: =Annahmen!$B$42+Annahmen!$B$43+B7*Annahmen!$B$40 -> 355 | C22: =Annahmen!$B$42+Annahmen!$B$43+C7*Annahmen!$B$40 -> 355 | D22: =Annahmen!$B$42+Annahmen!$B$43+D7*Annahmen!$B$40 -> 355 | E22: =Annahmen!$B$42+Annahmen!$B$43+E7*Annahmen!$B$40 -> 505 | F22: =Annahmen!$B$42+Annahmen!$B$43+F7*Annahmen!$B$40 -> 505 | G22: =Annahmen!$B$42+Annahmen!$B$43+G7*Annahmen!$B$40 -> 505 | H22: =Annahmen!$B$42+Annahmen!$B$43+H7*Annahmen!$B$40 -> 505 | I22: =Annahmen!$B$42+Annahmen!$B$43+I7*Annahmen!$B$40 -> 505 | ... Y22: =Annahmen!$B$42+Annahmen!$B$43+Y7*Annahmen!$B$40 -> 505
A23: Ergebnis vor Steuern (= Einkommen Gründer) | B23: =B21-B22 -> 1468 | C23: =C21-C22 -> 2047.6367 | D23: =D21-D22 -> 4437.227 | E23: =E21-E22 -> 5420.7167 | F23: =F21-F22 -> 6528.7241 | G23: =G21-G22 -> 7611.8524 | H23: =H21-H22 -> 8670.6896 | I23: =I21-I22 -> 9934.3091 | ... Y23: =Y21-Y22 -> 23955.188
A24: Kasse kumuliert | B24: =B23 -> 1468 | C24: =B24+C23 -> 3515.6367 | D24: =C24+D23 -> 7952.8636 | E24: =D24+E23 -> 13373.58 | F24: =E24+F23 -> 19902.304 | G24: =F24+G23 -> 27514.157 | H24: =G24+H23 -> 36184.846 | I24: =H24+I23 -> 46119.156 | J24: =I24+J23 -> 57150.858 | ... Y24: =X24+Y23 -> 333427.31
A25: Belegte Stunden | B25: =B9+B11*B8 -> 37.083333 | C25: =C9+C11*C8 -> 43.5 | D25: =D9+D11*D8 -> 86.8525 | E25: =E9+E11*E8 -> 51.30417 | F25: =F9+F11*F8 -> 57.734968 | G25: =G9+G11*G8 -> 64.018976 | H25: =H9+H11*H8 -> 70.159689 | I25: =I9+I11*I8 -> 74.643848 | ... Y25: =Y9+Y11*Y8 -> 153.71539

Sheet Solo Basis
A1: Solo-Plan · Szenario Basis · von Hand (24 Monate ab Nov 2026)
A2: Abschlüsse = Minimum aus Vertriebstempo und freien Stunden. Kundenzahlen sind Erwartungswerte.
A4: Monat | B4: Nov 26 | C4: Dez 26 | D4: Jan 27 | E4: Feb 27 | F4: Mär 27 | G4: Apr 27 | H4: Mai 27 | I4: Jun 27 | J4: Jul 27 | K4: Aug 27 | L4: Sep 27 | M4: Okt 27 | N4: Nov 27 | O4: Dez 27 | P4: Jan 28 | Q4: Feb 28 | R4: Mär 28 | S4: Apr 28 | T4: Mai 28 | U4: Jun 28 | V4: Jul 28 | W4: Aug 28 | X4: Sep 28 | Y4: Okt 28
A5: Abschluss-Ziel (Vertrieb) | B5: =Annahmen!$C$48 -> 2 | C5: =Annahmen!$C$48 -> 2 | D5: =Annahmen!$C$49 -> 3 | E5: =Annahmen!$C$49 -> 3 | F5: =Annahmen!$C$49 -> 3 | G5: =Annahmen!$C$49 -> 3 | H5: =Annahmen!$C$49 -> 3 | I5: =Annahmen!$C$49 -> 3 | J5: =Annahmen!$C$49 -> 3 | K5: =Annahmen!$C$49 -> 3 | ... Y5: =Annahmen!$C$49 -> 3
A6: Recruiting im Verkauf (1 = ja) | B6: =IF(1>=Annahmen!$B$16,1,0) -> 0 | C6: =IF(2>=Annahmen!$B$16,1,0) -> 0 | D6: =IF(3>=Annahmen!$B$16,1,0) -> 0 | E6: =IF(4>=Annahmen!$B$16,1,0) -> 0 | F6: =IF(5>=Annahmen!$B$16,1,0) -> 0 | G6: =IF(6>=Annahmen!$B$16,1,0) -> 0 | H6: =IF(7>=Annahmen!$B$16,1,0) -> 0 | I6: =IF(8>=Annahmen!$B$16,1,0) -> 1 | J6: =IF(9>=Annahmen!$B$16,1,0) -> 1 | K6: =IF(10>=Annahmen!$B$16,1,0) -> 1 | L6: =IF(11>=Annahmen!$B$16,1,0) -> 1 | M6: =IF(12>=Annahmen!$B$16,1,0) -> 1 | N6: =IF(13>=Annahmen!$B$16,1,0) -> 1 | O6: =IF(14>=Annahmen!$B$16,1,0) -> 1 | P6: =IF(15>=Annahmen!$B$16,1,0) -> 1 | Q6: =IF(16>=Annahmen!$B$16,1,0) -> 1 | R6: =IF(17>=Annahmen!$B$16,1,0) -> 1 | S6: =IF(18>=Annahmen!$B$16,1,0) -> 1 | T6: =IF(19>=Annahmen!$B$16,1,0) -> 1 | U6: =IF(20>=Annahmen!$B$16,1,0) -> 1 | V6: =IF(21>=Annahmen!$B$16,1,0) -> 1 | W6: =IF(22>=Annahmen!$B$16,1,0) -> 1 | X6: =IF(23>=Annahmen!$B$16,1,0) -> 1 | Y6: =IF(24>=Annahmen!$B$16,1,0) -> 1
A7: Automatisierung aktiv (1 = ja) | B7: =0 -> 0 | C7: =0 -> 0 | D7: =0 -> 0 | E7: =0 -> 0 | F7: =0 -> 0 | G7: =0 -> 0 | H7: =0 -> 0 | I7: =0 -> 0 | ... Y7: =0 -> 0
A8: Std. je neuem Abschluss | B8: =Annahmen!$B$12/(1-Annahmen!$B$15*(1-B6))*((Annahmen!$B$21+B7*(Annahmen!$B$30-Annahmen!$B$21))+(Annahmen!$B$25+B7*(Annahmen!$B$34-Annahmen!$B$25))+(Annahmen!$B$29+B7*(Annahmen!$B$38-Annahmen!$B$29)))+Annahmen!$B$13/(1-Annahmen!$B$15*(1-B6))*((Annahmen!$B$22+B7*(Annahmen!$B$31-Annahmen!$B$22))+(Annahmen!$B$26+B7*(Annahmen!$B$35-Annahmen!$B$26))+(Annahmen!$B$29+B7*(Annahmen!$B$38-Annahmen!$B$29)))+Annahmen!$B$14/(1-Annahmen!$B$15*(1-B6))*((Annahmen!$B$23+B7*(Annahmen!$B$32-Annahmen!$B$23))+(Annahmen!$B$27+B7*(Annahmen!$B$36-Annahmen!$B$27))+(Annahmen!$B$29+B7*(Annahmen!$B$38-Annahmen!$B$29)))+Annahmen!$B$15*B6*((Annahmen!$B$24+B7*(Annahmen!$B$33-Annahmen!$B$24))+(Annahmen!$B$28+B7*(Annahmen!$B$37-Annahmen!$B$28))+(Annahmen!$B$29+B7*(Annahmen!$B$38-Annahmen!$B$29))) -> 37.083333 | C8: =Annahmen!$B$12/(1-Annahmen!$B$15*(1-C6))*((Annahmen!$B$21+C7*(Annahmen!$B$30-Annahmen!$B$21))+(Annahmen!$B$25+C7*(Annahmen!$B$34-Annahmen!$B$25))+(Annahmen!$B$29+C7*(Annahmen!$B$38-Annahmen!$B$29)))+Annahmen!$B$13/(1-Annahmen!$B$15*(1-C6))*((Annahmen!$B$22+C7*(Annahmen!$B$31-Annahmen!$B$22))+(Annahmen!$B$26+C7*(Annahmen!$B$35-Annahmen!$B$26))+(Annahmen!$B$29+C7*(Annahmen!$B$38-Annahmen!$B$29)))+Annahmen!$B$14/(1-Annahmen!$B$15*(1-C6))*((Annahmen!$B$23+C7*(Annahmen!$B$32-Annahmen!$B$23))+(Annahmen!$B$27+C7*(Annahmen!$B$36-Annahmen!$B$27))+(Annahmen!$B$29+C7*(Annahmen!$B$38-Annahmen!$B$29)))+Annahmen!$B$15*C6*((Annahmen!$B$24+C7*(Annahmen!$B$33-Annahmen!$B$24))+(Annahmen!$B$28+C7*(Annahmen!$B$37-Annahmen!$B$28))+(Annahmen!$B$29+C7*(Annahmen!$B$38-Annahmen!$B$29))) -> 37.083333 | D8: =Annahmen!$B$12/(1-Annahmen!$B$15*(1-D6))*((Annahmen!$B$21+D7*(Annahmen!$B$30-Annahmen!$B$21))+(Annahmen!$B$25+D7*(Annahmen!$B$34-Annahmen!$B$25))+(Annahmen!$B$29+D7*(Annahmen!$B$38-Annahmen!$B$29)))+Annahmen!$B$13/(1-Annahmen!$B$15*(1-D6))*((Annahmen!$B$22+D7*(Annahmen!$B$31-Annahmen!$B$22))+(Annahmen!$B$26+D7*(Annahmen!$B$35-Annahmen!$B$26))+(Annahmen!$B$29+D7*(Annahmen!$B$38-Annahmen!$B$29)))+Annahmen!$B$14/(1-Annahmen!$B$15*(1-D6))*((Annahmen!$B$23+D7*(Annahmen!$B$32-Annahmen!$B$23))+(Annahmen!$B$27+D7*(Annahmen!$B$36-Annahmen!$B$27))+(Annahmen!$B$29+D7*(Annahmen!$B$38-Annahmen!$B$29)))+Annahmen!$B$15*D6*((Annahmen!$B$24+D7*(Annahmen!$B$33-Annahmen!$B$24))+(Annahmen!$B$28+D7*(Annahmen!$B$37-Annahmen!$B$28))+(Annahmen!$B$29+D7*(Annahmen!$B$38-Annahmen!$B$29))) -> 37.083333 | E8: =Annahmen!$B$12/(1-Annahmen!$B$15*(1-E6))*((Annahmen!$B$21+E7*(Annahmen!$B$30-Annahmen!$B$21))+(Annahmen!$B$25+E7*(Annahmen!$B$34-Annahmen!$B$25))+(Annahmen!$B$29+E7*(Annahmen!$B$38-Annahmen!$B$29)))+Annahmen!$B$13/(1-Annahmen!$B$15*(1-E6))*((Annahmen!$B$22+E7*(Annahmen!$B$31-Annahmen!$B$22))+(Annahmen!$B$26+E7*(Annahmen!$B$35-Annahmen!$B$26))+(Annahmen!$B$29+E7*(Annahmen!$B$38-Annahmen!$B$29)))+Annahmen!$B$14/(1-Annahmen!$B$15*(1-E6))*((Annahmen!$B$23+E7*(Annahmen!$B$32-Annahmen!$B$23))+(Annahmen!$B$27+E7*(Annahmen!$B$36-Annahmen!$B$27))+(Annahmen!$B$29+E7*(Annahmen!$B$38-Annahmen!$B$29)))+Annahmen!$B$15*E6*((Annahmen!$B$24+E7*(Annahmen!$B$33-Annahmen!$B$24))+(Annahmen!$B$28+E7*(Annahmen!$B$37-Annahmen!$B$28))+(Annahmen!$B$29+E7*(Annahmen!$B$38-Annahmen!$B$29))) -> 37.083333 | F8: =Annahmen!$B$12/(1-Annahmen!$B$15*(1-F6))*((Annahmen!$B$21+F7*(Annahmen!$B$30-Annahmen!$B$21))+(Annahmen!$B$25+F7*(Annahmen!$B$34-Annahmen!$B$25))+(Annahmen!$B$29+F7*(Annahmen!$B$38-Annahmen!$B$29)))+Annahmen!$B$13/(1-Annahmen!$B$15*(1-F6))*((Annahmen!$B$22+F7*(Annahmen!$B$31-Annahmen!$B$22))+(Annahmen!$B$26+F7*(Annahmen!$B$35-Annahmen!$B$26))+(Annahmen!$B$29+F7*(Annahmen!$B$38-Annahmen!$B$29)))+Annahmen!$B$14/(1-Annahmen!$B$15*(1-F6))*((Annahmen!$B$23+F7*(Annahmen!$B$32-Annahmen!$B$23))+(Annahmen!$B$27+F7*(Annahmen!$B$36-Annahmen!$B$27))+(Annahmen!$B$29+F7*(Annahmen!$B$38-Annahmen!$B$29)))+Annahmen!$B$15*F6*((Annahmen!$B$24+F7*(Annahmen!$B$33-Annahmen!$B$24))+(Annahmen!$B$28+F7*(Annahmen!$B$37-Annahmen!$B$28))+(Annahmen!$B$29+F7*(Annahmen!$B$38-Annahmen!$B$29))) -> 37.083333 | G8: =Annahmen!$B$12/(1-Annahmen!$B$15*(1-G6))*((Annahmen!$B$21+G7*(Annahmen!$B$30-Annahmen!$B$21))+(Annahmen!$B$25+G7*(Annahmen!$B$34-Annahmen!$B$25))+(Annahmen!$B$29+G7*(Annahmen!$B$38-Annahmen!$B$29)))+Annahmen!$B$13/(1-Annahmen!$B$15*(1-G6))*((Annahmen!$B$22+G7*(Annahmen!$B$31-Annahmen!$B$22))+(Annahmen!$B$26+G7*(Annahmen!$B$35-Annahmen!$B$26))+(Annahmen!$B$29+G7*(Annahmen!$B$38-Annahmen!$B$29)))+Annahmen!$B$14/(1-Annahmen!$B$15*(1-G6))*((Annahmen!$B$23+G7*(Annahmen!$B$32-Annahmen!$B$23))+(Annahmen!$B$27+G7*(Annahmen!$B$36-Annahmen!$B$27))+(Annahmen!$B$29+G7*(Annahmen!$B$38-Annahmen!$B$29)))+Annahmen!$B$15*G6*((Annahmen!$B$24+G7*(Annahmen!$B$33-Annahmen!$B$24))+(Annahmen!$B$28+G7*(Annahmen!$B$37-Annahmen!$B$28))+(Annahmen!$B$29+G7*(Annahmen!$B$38-Annahmen!$B$29))) -> 37.083333 | H8: =Annahmen!$B$12/(1-Annahmen!$B$15*(1-H6))*((Annahmen!$B$21+H7*(Annahmen!$B$30-Annahmen!$B$21))+(Annahmen!$B$25+H7*(Annahmen!$B$34-Annahmen!$B$25))+(Annahmen!$B$29+H7*(Annahmen!$B$38-Annahmen!$B$29)))+Annahmen!$B$13/(1-Annahmen!$B$15*(1-H6))*((Annahmen!$B$22+H7*(Annahmen!$B$31-Annahmen!$B$22))+(Annahmen!$B$26+H7*(Annahmen!$B$35-Annahmen!$B$26))+(Annahmen!$B$29+H7*(Annahmen!$B$38-Annahmen!$B$29)))+Annahmen!$B$14/(1-Annahmen!$B$15*(1-H6))*((Annahmen!$B$23+H7*(Annahmen!$B$32-Annahmen!$B$23))+(Annahmen!$B$27+H7*(Annahmen!$B$36-Annahmen!$B$27))+(Annahmen!$B$29+H7*(Annahmen!$B$38-Annahmen!$B$29)))+Annahmen!$B$15*H6*((Annahmen!$B$24+H7*(Annahmen!$B$33-Annahmen!$B$24))+(Annahmen!$B$28+H7*(Annahmen!$B$37-Annahmen!$B$28))+(Annahmen!$B$29+H7*(Annahmen!$B$38-Annahmen!$B$29))) -> 37.083333 | I8: =Annahmen!$B$12/(1-Annahmen!$B$15*(1-I6))*((Annahmen!$B$21+I7*(Annahmen!$B$30-Annahmen!$B$21))+(Annahmen!$B$25+I7*(Annahmen!$B$34-Annahmen!$B$25))+(Annahmen!$B$29+I7*(Annahmen!$B$38-Annahmen!$B$29)))+Annahmen!$B$13/(1-Annahmen!$B$15*(1-I6))*((Annahmen!$B$22+I7*(Annahmen!$B$31-Annahmen!$B$22))+(Annahmen!$B$26+I7*(Annahmen!$B$35-Annahmen!$B$26))+(Annahmen!$B$29+I7*(Annahmen!$B$38-Annahmen!$B$29)))+Annahmen!$B$14/(1-Annahmen!$B$15*(1-I6))*((Annahmen!$B$23+I7*(Annahmen!$B$32-Annahmen!$B$23))+(Annahmen!$B$27+I7*(Annahmen!$B$36-Annahmen!$B$27))+(Annahmen!$B$29+I7*(Annahmen!$B$38-Annahmen!$B$29)))+Annahmen!$B$15*I6*((Annahmen!$B$24+I7*(Annahmen!$B$33-Annahmen!$B$24))+(Annahmen!$B$28+I7*(Annahmen!$B$37-Annahmen!$B$28))+(Annahmen!$B$29+I7*(Annahmen!$B$38-Annahmen!$B$29))) -> 34.5625 | ... Y8: =Annahmen!$B$12/(1-Annahmen!$B$15*(1-Y6))*((Annahmen!$B$21+Y7*(Annahmen!$B$30-Annahmen!$B$21))+(Annahmen!$B$25+Y7*(Annahmen!$B$34-Annahmen!$B$25))+(Annahmen!$B$29+Y7*(Annahmen!$B$38-Annahmen!$B$29)))+Annahmen!$B$13/(1-Annahmen!$B$15*(1-Y6))*((Annahmen!$B$22+Y7*(Annahmen!$B$31-Annahmen!$B$22))+(Annahmen!$B$26+Y7*(Annahmen!$B$35-Annahmen!$B$26))+(Annahmen!$B$29+Y7*(Annahmen!$B$38-Annahmen!$B$29)))+Annahmen!$B$14/(1-Annahmen!$B$15*(1-Y6))*((Annahmen!$B$23+Y7*(Annahmen!$B$32-Annahmen!$B$23))+(Annahmen!$B$27+Y7*(Annahmen!$B$36-Annahmen!$B$27))+(Annahmen!$B$29+Y7*(Annahmen!$B$38-Annahmen!$B$29)))+Annahmen!$B$15*Y6*((Annahmen!$B$24+Y7*(Annahmen!$B$33-Annahmen!$B$24))+(Annahmen!$B$28+Y7*(Annahmen!$B$37-Annahmen!$B$28))+(Annahmen!$B$29+Y7*(Annahmen!$B$38-Annahmen!$B$29))) -> 34.5625
A9: Laufende Stunden (Bestand) | B9: =0*(Annahmen!$B$25+B7*(Annahmen!$B$34-Annahmen!$B$25))+0*(Annahmen!$B$26+B7*(Annahmen!$B$35-Annahmen!$B$26))+0*(Annahmen!$B$27+B7*(Annahmen!$B$36-Annahmen!$B$27))+0*(Annahmen!$B$28+B7*(Annahmen!$B$37-Annahmen!$B$28)) -> 0 | C9: =B14*(Annahmen!$B$25+C7*(Annahmen!$B$34-Annahmen!$B$25))+B15*(Annahmen!$B$26+C7*(Annahmen!$B$35-Annahmen!$B$26))+B16*(Annahmen!$B$27+C7*(Annahmen!$B$36-Annahmen!$B$27))+B17*(Annahmen!$B$28+C7*(Annahmen!$B$37-Annahmen!$B$28)) -> 12.833333 | D9: =C14*(Annahmen!$B$25+D7*(Annahmen!$B$34-Annahmen!$B$25))+C15*(Annahmen!$B$26+D7*(Annahmen!$B$35-Annahmen!$B$26))+C16*(Annahmen!$B$27+D7*(Annahmen!$B$36-Annahmen!$B$27))+C17*(Annahmen!$B$28+D7*(Annahmen!$B$37-Annahmen!$B$28)) -> 25.371667 | E9: =D14*(Annahmen!$B$25+E7*(Annahmen!$B$34-Annahmen!$B$25))+D15*(Annahmen!$B$26+E7*(Annahmen!$B$35-Annahmen!$B$26))+D16*(Annahmen!$B$27+E7*(Annahmen!$B$36-Annahmen!$B$27))+D17*(Annahmen!$B$28+E7*(Annahmen!$B$37-Annahmen!$B$28)) -> 44.03875 | F9: =E14*(Annahmen!$B$25+F7*(Annahmen!$B$34-Annahmen!$B$25))+E15*(Annahmen!$B$26+F7*(Annahmen!$B$35-Annahmen!$B$26))+E16*(Annahmen!$B$27+F7*(Annahmen!$B$36-Annahmen!$B$27))+E17*(Annahmen!$B$28+F7*(Annahmen!$B$37-Annahmen!$B$28)) -> 62.277322 | G9: =F14*(Annahmen!$B$25+G7*(Annahmen!$B$34-Annahmen!$B$25))+F15*(Annahmen!$B$26+G7*(Annahmen!$B$35-Annahmen!$B$26))+F16*(Annahmen!$B$27+G7*(Annahmen!$B$36-Annahmen!$B$27))+F17*(Annahmen!$B$28+G7*(Annahmen!$B$37-Annahmen!$B$28)) -> 79.487313 | H9: =G14*(Annahmen!$B$25+H7*(Annahmen!$B$34-Annahmen!$B$25))+G15*(Annahmen!$B$26+H7*(Annahmen!$B$35-Annahmen!$B$26))+G16*(Annahmen!$B$27+H7*(Annahmen!$B$36-Annahmen!$B$27))+G17*(Annahmen!$B$28+H7*(Annahmen!$B$37-Annahmen!$B$28)) -> 93.325207 | I9: =H14*(Annahmen!$B$25+I7*(Annahmen!$B$34-Annahmen!$B$25))+H15*(Annahmen!$B$26+I7*(Annahmen!$B$35-Annahmen!$B$26))+H16*(Annahmen!$B$27+I7*(Annahmen!$B$36-Annahmen!$B$27))+H17*(Annahmen!$B$28+I7*(Annahmen!$B$37-Annahmen!$B$28)) -> 104.45237 | J9: =I14*(Annahmen!$B$25+J7*(Annahmen!$B$34-Annahmen!$B$25))+I15*(Annahmen!$B$26+J7*(Annahmen!$B$35-Annahmen!$B$26))+I16*(Annahmen!$B$27+J7*(Annahmen!$B$36-Annahmen!$B$27))+I17*(Annahmen!$B$28+J7*(Annahmen!$B$37-Annahmen!$B$28)) -> 114.50425 | ... Y9: =X14*(Annahmen!$B$25+Y7*(Annahmen!$B$34-Annahmen!$B$25))+X15*(Annahmen!$B$26+Y7*(Annahmen!$B$35-Annahmen!$B$26))+X16*(Annahmen!$B$27+Y7*(Annahmen!$B$36-Annahmen!$B$27))+X17*(Annahmen!$B$28+Y7*(Annahmen!$B$37-Annahmen!$B$28)) -> 148.87407
A10: Möglich nach Stunden | B10: =MAX(0,(Annahmen!$B$41-B9)/B8) -> 4.5842697 | C10: =MAX(0,(Annahmen!$B$41-C9)/C8) -> 4.2382022 | D10: =MAX(0,(Annahmen!$B$41-D9)/D8) -> 3.9000899 | E10: =MAX(0,(Annahmen!$B$41-E9)/E8) -> 3.3967079 | F10: =MAX(0,(Annahmen!$B$41-F9)/F8) -> 2.9048812 | G10: =MAX(0,(Annahmen!$B$41-G9)/G8) -> 2.4407916 | H10: =MAX(0,(Annahmen!$B$41-H9)/H8) -> 2.0676349 | I10: =MAX(0,(Annahmen!$B$41-I9)/I8) -> 1.8964955 | ... Y10: =MAX(0,(Annahmen!$B$41-Y9)/Y8) -> 0.61123843
A11: Abschlüsse | B11: =MIN(B5,B10) -> 2 | C11: =MIN(C5,C10) -> 2 | D11: =MIN(D5,D10) -> 3 | E11: =MIN(E5,E10) -> 3 | F11: =MIN(F5,F10) -> 2.9048812 | G11: =MIN(G5,G10) -> 2.4407916 | H11: =MIN(H5,H10) -> 2.0676349 | I11: =MIN(I5,I10) -> 1.8964955 | ... Y11: =MIN(Y5,Y10) -> 0.61123843
A12: Abschlüsse kumuliert | B12: =0+B11 -> 2 | C12: =B12+C11 -> 4 | D12: =C12+D11 -> 7 | E12: =D12+E11 -> 10 | F12: =E12+F11 -> 12.904881 | G12: =F12+G11 -> 15.345673 | H12: =G12+H11 -> 17.413308 | I12: =H12+I11 -> 19.309803 | J12: =I12+J11 -> 20.915467 | ... Y12: =X12+Y11 -> 33.200057
A14: Aktive Pflege-Kunden | B14: =0*(1-Annahmen!$B$17)+B11*Annahmen!$B$12/(1-Annahmen!$B$15*(1-B6)) -> 0.66666667 | C14: =B14*(1-Annahmen!$B$17)+C11*Annahmen!$B$12/(1-Annahmen!$B$15*(1-C6)) -> 1.3266667 | D14: =C14*(1-Annahmen!$B$17)+D11*Annahmen!$B$12/(1-Annahmen!$B$15*(1-D6)) -> 2.3134 | E14: =D14*(1-Annahmen!$B$17)+E11*Annahmen!$B$12/(1-Annahmen!$B$15*(1-E6)) -> 3.290266 | F14: =E14*(1-Annahmen!$B$17)+F11*Annahmen!$B$12/(1-Annahmen!$B$15*(1-F6)) -> 4.2256571 | G14: =F14*(1-Annahmen!$B$17)+G11*Annahmen!$B$12/(1-Annahmen!$B$15*(1-G6)) -> 4.9969977 | H14: =G14*(1-Annahmen!$B$17)+H11*Annahmen!$B$12/(1-Annahmen!$B$15*(1-H6)) -> 5.6362393 | I14: =H14*(1-Annahmen!$B$17)+I11*Annahmen!$B$12/(1-Annahmen!$B$15*(1-I6)) -> 6.0540008 | J14: =I14*(1-Annahmen!$B$17)+J11*Annahmen!$B$12/(1-Annahmen!$B$15*(1-J6)) -> 6.3948767 | ... Y14: =X14*(1-Annahmen!$B$17)+Y11*Annahmen!$B$12/(1-Annahmen!$B$15*(1-Y6)) -> 8.3340259
A15: Aktive Programm-Kunden | B15: =0*(1-Annahmen!$B$18)+B11*Annahmen!$B$13/(1-Annahmen!$B$15*(1-B6)) -> 0.66666667 | C15: =B15*(1-Annahmen!$B$18)+C11*Annahmen!$B$13/(1-Annahmen!$B$15*(1-C6)) -> 1.32 | D15: =C15*(1-Annahmen!$B$18)+D11*Annahmen!$B$13/(1-Annahmen!$B$15*(1-D6)) -> 2.2936 | E15: =D15*(1-Annahmen!$B$18)+E11*Annahmen!$B$13/(1-Annahmen!$B$15*(1-E6)) -> 3.247728 | F15: =E15*(1-Annahmen!$B$18)+F11*Annahmen!$B$13/(1-Annahmen!$B$15*(1-F6)) -> 4.1510672 | G15: =F15*(1-Annahmen!$B$18)+G11*Annahmen!$B$13/(1-Annahmen!$B$15*(1-G6)) -> 4.881643 | H15: =G15*(1-Annahmen!$B$18)+H11*Annahmen!$B$13/(1-Annahmen!$B$15*(1-H6)) -> 5.4732218 | I15: =H15*(1-Annahmen!$B$18)+I11*Annahmen!$B$13/(1-Annahmen!$B$15*(1-I6)) -> 5.8378812 | J15: =I15*(1-Annahmen!$B$18)+J11*Annahmen!$B$13/(1-Annahmen!$B$15*(1-J6)) -> 6.1225395 | ... Y15: =X15*(1-Annahmen!$B$18)+Y11*Annahmen!$B$13/(1-Annahmen!$B$15*(1-Y6)) -> 7.1403069
A16: Aktive SEO-Kunden | B16: =0*(1-Annahmen!$B$19)+B11*Annahmen!$B$14/(1-Annahmen!$B$15*(1-B6)) -> 0.66666667 | C16: =B16*(1-Annahmen!$B$19)+C11*Annahmen!$B$14/(1-Annahmen!$B$15*(1-C6)) -> 1.3133333 | D16: =C16*(1-Annahmen!$B$19)+D11*Annahmen!$B$14/(1-Annahmen!$B$15*(1-D6)) -> 2.2739333 | E16: =D16*(1-Annahmen!$B$19)+E11*Annahmen!$B$14/(1-Annahmen!$B$15*(1-E6)) -> 3.2057153 | F16: =E16*(1-Annahmen!$B$19)+F11*Annahmen!$B$14/(1-Annahmen!$B$15*(1-F6)) -> 4.0778376 | G16: =F16*(1-Annahmen!$B$19)+G11*Annahmen!$B$14/(1-Annahmen!$B$15*(1-G6)) -> 4.7690997 | H16: =G16*(1-Annahmen!$B$19)+H11*Annahmen!$B$14/(1-Annahmen!$B$15*(1-H6)) -> 5.3152383 | I16: =H16*(1-Annahmen!$B$19)+I11*Annahmen!$B$14/(1-Annahmen!$B$15*(1-I6)) -> 5.629905 | J16: =I16*(1-Annahmen!$B$19)+J11*Annahmen!$B$14/(1-Annahmen!$B$15*(1-J6)) -> 5.8624238 | ... Y16: =X16*(1-Annahmen!$B$19)+Y11*Annahmen!$B$14/(1-Annahmen!$B$15*(1-Y6)) -> 6.1345576
A17: Aktive Recruiting-Kunden | B17: =0*(1-Annahmen!$B$20)+B11*Annahmen!$B$15*B6 -> 0 | C17: =B17*(1-Annahmen!$B$20)+C11*Annahmen!$B$15*C6 -> 0 | D17: =C17*(1-Annahmen!$B$20)+D11*Annahmen!$B$15*D6 -> 0 | E17: =D17*(1-Annahmen!$B$20)+E11*Annahmen!$B$15*E6 -> 0 | F17: =E17*(1-Annahmen!$B$20)+F11*Annahmen!$B$15*F6 -> 0 | G17: =F17*(1-Annahmen!$B$20)+G11*Annahmen!$B$15*G6 -> 0 | H17: =G17*(1-Annahmen!$B$20)+H11*Annahmen!$B$15*H6 -> 0 | I17: =H17*(1-Annahmen!$B$20)+I11*Annahmen!$B$15*I6 -> 0.47412389 | J17: =I17*(1-Annahmen!$B$20)+J11*Annahmen!$B$15*J6 -> 0.85183358 | ... Y17: =X17*(1-Annahmen!$B$20)+Y11*Annahmen!$B$15*Y6 -> 2.475738
A19: MRR | B19: =B14*Annahmen!$B$6+B15*Annahmen!$B$7+B16*Annahmen!$B$9+B17*Annahmen!$B$10 -> 1186 | C19: =C14*Annahmen!$B$6+C15*Annahmen!$B$7+C16*Annahmen!$B$9+C17*Annahmen!$B$10 -> 2345.2733 | D19: =D14*Annahmen!$B$6+D15*Annahmen!$B$7+D16*Annahmen!$B$9+D17*Annahmen!$B$10 -> 4071.4539 | E19: =E14*Annahmen!$B$6+E15*Annahmen!$B$7+E16*Annahmen!$B$9+E17*Annahmen!$B$10 -> 5758.7966 | F19: =F14*Annahmen!$B$6+F15*Annahmen!$B$7+F16*Annahmen!$B$9+F17*Annahmen!$B$10 -> 7351.8158 | G19: =G14*Annahmen!$B$6+G15*Annahmen!$B$7+G16*Annahmen!$B$9+G17*Annahmen!$B$10 -> 8633.8798 | H19: =H14*Annahmen!$B$6+H15*Annahmen!$B$7+H16*Annahmen!$B$9+H17*Annahmen!$B$10 -> 9665.9583 | I19: =I14*Annahmen!$B$6+I15*Annahmen!$B$7+I16*Annahmen!$B$9+I17*Annahmen!$B$10 -> 10666.913 | ... Y19: =Y14*Annahmen!$B$6+Y15*Annahmen!$B$7+Y16*Annahmen!$B$9+Y17*Annahmen!$B$10 -> 14217.816
A20: Einmalumsatz | B20: =B11*(Annahmen!$B$12/(1-Annahmen!$B$15*(1-B6))*Annahmen!$B$5+Annahmen!$B$13/(1-Annahmen!$B$15*(1-B6))*Annahmen!$B$8+Annahmen!$B$15*B6*Annahmen!$B$11) -> 2460 | C20: =C11*(Annahmen!$B$12/(1-Annahmen!$B$15*(1-C6))*Annahmen!$B$5+Annahmen!$B$13/(1-Annahmen!$B$15*(1-C6))*Annahmen!$B$8+Annahmen!$B$15*C6*Annahmen!$B$11) -> 2460 | D20: =D11*(Annahmen!$B$12/(1-Annahmen!$B$15*(1-D6))*Annahmen!$B$5+Annahmen!$B$13/(1-Annahmen!$B$15*(1-D6))*Annahmen!$B$8+Annahmen!$B$15*D6*Annahmen!$B$11) -> 3690 | E20: =E11*(Annahmen!$B$12/(1-Annahmen!$B$15*(1-E6))*Annahmen!$B$5+Annahmen!$B$13/(1-Annahmen!$B$15*(1-E6))*Annahmen!$B$8+Annahmen!$B$15*E6*Annahmen!$B$11) -> 3690 | F20: =F11*(Annahmen!$B$12/(1-Annahmen!$B$15*(1-F6))*Annahmen!$B$5+Annahmen!$B$13/(1-Annahmen!$B$15*(1-F6))*Annahmen!$B$8+Annahmen!$B$15*F6*Annahmen!$B$11) -> 3573.0039 | G20: =G11*(Annahmen!$B$12/(1-Annahmen!$B$15*(1-G6))*Annahmen!$B$5+Annahmen!$B$13/(1-Annahmen!$B$15*(1-G6))*Annahmen!$B$8+Annahmen!$B$15*G6*Annahmen!$B$11) -> 3002.1736 | H20: =H11*(Annahmen!$B$12/(1-Annahmen!$B$15*(1-H6))*Annahmen!$B$5+Annahmen!$B$13/(1-Annahmen!$B$15*(1-H6))*Annahmen!$B$8+Annahmen!$B$15*H6*Annahmen!$B$11) -> 2543.1909 | I20: =I11*(Annahmen!$B$12/(1-Annahmen!$B$15*(1-I6))*Annahmen!$B$5+Annahmen!$B$13/(1-Annahmen!$B$15*(1-I6))*Annahmen!$B$8+Annahmen!$B$15*I6*Annahmen!$B$11) -> 2455.9617 | ... Y20: =Y11*(Annahmen!$B$12/(1-Annahmen!$B$15*(1-Y6))*Annahmen!$B$5+Annahmen!$B$13/(1-Annahmen!$B$15*(1-Y6))*Annahmen!$B$8+Annahmen!$B$15*Y6*Annahmen!$B$11) -> 791.55376
A21: Umsatz | B21: =B19+B20 -> 3646 | C21: =C19+C20 -> 4805.2733 | D21: =D19+D20 -> 7761.4539 | E21: =E19+E20 -> 9448.7966 | F21: =F19+F20 -> 10924.82 | G21: =G19+G20 -> 11636.053 | H21: =H19+H20 -> 12209.149 | I21: =I19+I20 -> 13122.875 | ... Y21: =Y19+Y20 -> 15009.37
A22: Kosten | B22: =Annahmen!$B$42+Annahmen!$B$43+B7*Annahmen!$B$40 -> 355 | C22: =Annahmen!$B$42+Annahmen!$B$43+C7*Annahmen!$B$40 -> 355 | D22: =Annahmen!$B$42+Annahmen!$B$43+D7*Annahmen!$B$40 -> 355 | E22: =Annahmen!$B$42+Annahmen!$B$43+E7*Annahmen!$B$40 -> 355 | F22: =Annahmen!$B$42+Annahmen!$B$43+F7*Annahmen!$B$40 -> 355 | G22: =Annahmen!$B$42+Annahmen!$B$43+G7*Annahmen!$B$40 -> 355 | H22: =Annahmen!$B$42+Annahmen!$B$43+H7*Annahmen!$B$40 -> 355 | I22: =Annahmen!$B$42+Annahmen!$B$43+I7*Annahmen!$B$40 -> 355 | ... Y22: =Annahmen!$B$42+Annahmen!$B$43+Y7*Annahmen!$B$40 -> 355
A23: Ergebnis vor Steuern (= Einkommen Gründer) | B23: =B21-B22 -> 3291 | C23: =C21-C22 -> 4450.2733 | D23: =D21-D22 -> 7406.4539 | E23: =E21-E22 -> 9093.7966 | F23: =F21-F22 -> 10569.82 | G23: =G21-G22 -> 11281.053 | H23: =H21-H22 -> 11854.149 | I23: =I21-I22 -> 12767.875 | ... Y23: =Y21-Y22 -> 14654.37
A24: Kasse kumuliert | B24: =B23 -> 3291 | C24: =B24+C23 -> 7741.2733 | D24: =C24+D23 -> 15147.727 | E24: =D24+E23 -> 24241.524 | F24: =E24+F23 -> 34811.344 | G24: =F24+G23 -> 46092.397 | H24: =G24+H23 -> 57946.546 | I24: =H24+I23 -> 70714.421 | J24: =I24+J23 -> 83887.233 | ... Y24: =X24+Y23 -> 298609.7
A25: Belegte Stunden | B25: =B9+B11*B8 -> 74.166667 | C25: =C9+C11*C8 -> 87 | D25: =D9+D11*D8 -> 136.62167 | E25: =E9+E11*E8 -> 155.28875 | F25: =F9+F11*F8 -> 170 | G25: =G9+G11*G8 -> 170 | H25: =H9+H11*H8 -> 170 | I25: =I9+I11*I8 -> 170 | ... Y25: =Y9+Y11*Y8 -> 170

Sheet Solo Basis auto
A1: Solo-Plan · Szenario Basis · automatisiert ab Kunde 5 (24 Monate ab Nov 2026)
A2: Abschlüsse = Minimum aus Vertriebstempo und freien Stunden. Kundenzahlen sind Erwartungswerte.
A4: Monat | B4: Nov 26 | C4: Dez 26 | D4: Jan 27 | E4: Feb 27 | F4: Mär 27 | G4: Apr 27 | H4: Mai 27 | I4: Jun 27 | J4: Jul 27 | K4: Aug 27 | L4: Sep 27 | M4: Okt 27 | N4: Nov 27 | O4: Dez 27 | P4: Jan 28 | Q4: Feb 28 | R4: Mär 28 | S4: Apr 28 | T4: Mai 28 | U4: Jun 28 | V4: Jul 28 | W4: Aug 28 | X4: Sep 28 | Y4: Okt 28
A5: Abschluss-Ziel (Vertrieb) | B5: =Annahmen!$C$48 -> 2 | C5: =Annahmen!$C$48 -> 2 | D5: =Annahmen!$C$49 -> 3 | E5: =Annahmen!$C$49 -> 3 | F5: =Annahmen!$C$49 -> 3 | G5: =Annahmen!$C$49 -> 3 | H5: =Annahmen!$C$49 -> 3 | I5: =Annahmen!$C$49 -> 3 | J5: =Annahmen!$C$49 -> 3 | K5: =Annahmen!$C$49 -> 3 | ... Y5: =Annahmen!$C$49 -> 3
A6: Recruiting im Verkauf (1 = ja) | B6: =IF(1>=Annahmen!$B$16,1,0) -> 0 | C6: =IF(2>=Annahmen!$B$16,1,0) -> 0 | D6: =IF(3>=Annahmen!$B$16,1,0) -> 0 | E6: =IF(4>=Annahmen!$B$16,1,0) -> 0 | F6: =IF(5>=Annahmen!$B$16,1,0) -> 0 | G6: =IF(6>=Annahmen!$B$16,1,0) -> 0 | H6: =IF(7>=Annahmen!$B$16,1,0) -> 0 | I6: =IF(8>=Annahmen!$B$16,1,0) -> 1 | J6: =IF(9>=Annahmen!$B$16,1,0) -> 1 | K6: =IF(10>=Annahmen!$B$16,1,0) -> 1 | L6: =IF(11>=Annahmen!$B$16,1,0) -> 1 | M6: =IF(12>=Annahmen!$B$16,1,0) -> 1 | N6: =IF(13>=Annahmen!$B$16,1,0) -> 1 | O6: =IF(14>=Annahmen!$B$16,1,0) -> 1 | P6: =IF(15>=Annahmen!$B$16,1,0) -> 1 | Q6: =IF(16>=Annahmen!$B$16,1,0) -> 1 | R6: =IF(17>=Annahmen!$B$16,1,0) -> 1 | S6: =IF(18>=Annahmen!$B$16,1,0) -> 1 | T6: =IF(19>=Annahmen!$B$16,1,0) -> 1 | U6: =IF(20>=Annahmen!$B$16,1,0) -> 1 | V6: =IF(21>=Annahmen!$B$16,1,0) -> 1 | W6: =IF(22>=Annahmen!$B$16,1,0) -> 1 | X6: =IF(23>=Annahmen!$B$16,1,0) -> 1 | Y6: =IF(24>=Annahmen!$B$16,1,0) -> 1
A7: Automatisierung aktiv (1 = ja) | B7: =IF(0>=Annahmen!$B$39-1,1,0) -> 0 | C7: =IF(B12>=Annahmen!$B$39-1,1,0) -> 0 | D7: =IF(C12>=Annahmen!$B$39-1,1,0) -> 1 | E7: =IF(D12>=Annahmen!$B$39-1,1,0) -> 1 | F7: =IF(E12>=Annahmen!$B$39-1,1,0) -> 1 | G7: =IF(F12>=Annahmen!$B$39-1,1,0) -> 1 | H7: =IF(G12>=Annahmen!$B$39-1,1,0) -> 1 | I7: =IF(H12>=Annahmen!$B$39-1,1,0) -> 1 | J7: =IF(I12>=Annahmen!$B$39-1,1,0) -> 1 | ... Y7: =IF(X12>=Annahmen!$B$39-1,1,0) -> 1
A8: Std. je neuem Abschluss | B8: =Annahmen!$B$12/(1-Annahmen!$B$15*(1-B6))*((Annahmen!$B$21+B7*(Annahmen!$B$30-Annahmen!$B$21))+(Annahmen!$B$25+B7*(Annahmen!$B$34-Annahmen!$B$25))+(Annahmen!$B$29+B7*(Annahmen!$B$38-Annahmen!$B$29)))+Annahmen!$B$13/(1-Annahmen!$B$15*(1-B6))*((Annahmen!$B$22+B7*(Annahmen!$B$31-Annahmen!$B$22))+(Annahmen!$B$26+B7*(Annahmen!$B$35-Annahmen!$B$26))+(Annahmen!$B$29+B7*(Annahmen!$B$38-Annahmen!$B$29)))+Annahmen!$B$14/(1-Annahmen!$B$15*(1-B6))*((Annahmen!$B$23+B7*(Annahmen!$B$32-Annahmen!$B$23))+(Annahmen!$B$27+B7*(Annahmen!$B$36-Annahmen!$B$27))+(Annahmen!$B$29+B7*(Annahmen!$B$38-Annahmen!$B$29)))+Annahmen!$B$15*B6*((Annahmen!$B$24+B7*(Annahmen!$B$33-Annahmen!$B$24))+(Annahmen!$B$28+B7*(Annahmen!$B$37-Annahmen!$B$28))+(Annahmen!$B$29+B7*(Annahmen!$B$38-Annahmen!$B$29))) -> 37.083333 | C8: =Annahmen!$B$12/(1-Annahmen!$B$15*(1-C6))*((Annahmen!$B$21+C7*(Annahmen!$B$30-Annahmen!$B$21))+(Annahmen!$B$25+C7*(Annahmen!$B$34-Annahmen!$B$25))+(Annahmen!$B$29+C7*(Annahmen!$B$38-Annahmen!$B$29)))+Annahmen!$B$13/(1-Annahmen!$B$15*(1-C6))*((Annahmen!$B$22+C7*(Annahmen!$B$31-Annahmen!$B$22))+(Annahmen!$B$26+C7*(Annahmen!$B$35-Annahmen!$B$26))+(Annahmen!$B$29+C7*(Annahmen!$B$38-Annahmen!$B$29)))+Annahmen!$B$14/(1-Annahmen!$B$15*(1-C6))*((Annahmen!$B$23+C7*(Annahmen!$B$32-Annahmen!$B$23))+(Annahmen!$B$27+C7*(Annahmen!$B$36-Annahmen!$B$27))+(Annahmen!$B$29+C7*(Annahmen!$B$38-Annahmen!$B$29)))+Annahmen!$B$15*C6*((Annahmen!$B$24+C7*(Annahmen!$B$33-Annahmen!$B$24))+(Annahmen!$B$28+C7*(Annahmen!$B$37-Annahmen!$B$28))+(Annahmen!$B$29+C7*(Annahmen!$B$38-Annahmen!$B$29))) -> 37.083333 | D8: =Annahmen!$B$12/(1-Annahmen!$B$15*(1-D6))*((Annahmen!$B$21+D7*(Annahmen!$B$30-Annahmen!$B$21))+(Annahmen!$B$25+D7*(Annahmen!$B$34-Annahmen!$B$25))+(Annahmen!$B$29+D7*(Annahmen!$B$38-Annahmen!$B$29)))+Annahmen!$B$13/(1-Annahmen!$B$15*(1-D6))*((Annahmen!$B$22+D7*(Annahmen!$B$31-Annahmen!$B$22))+(Annahmen!$B$26+D7*(Annahmen!$B$35-Annahmen!$B$26))+(Annahmen!$B$29+D7*(Annahmen!$B$38-Annahmen!$B$29)))+Annahmen!$B$14/(1-Annahmen!$B$15*(1-D6))*((Annahmen!$B$23+D7*(Annahmen!$B$32-Annahmen!$B$23))+(Annahmen!$B$27+D7*(Annahmen!$B$36-Annahmen!$B$27))+(Annahmen!$B$29+D7*(Annahmen!$B$38-Annahmen!$B$29)))+Annahmen!$B$15*D6*((Annahmen!$B$24+D7*(Annahmen!$B$33-Annahmen!$B$24))+(Annahmen!$B$28+D7*(Annahmen!$B$37-Annahmen!$B$28))+(Annahmen!$B$29+D7*(Annahmen!$B$38-Annahmen!$B$29))) -> 19.033333 | E8: =Annahmen!$B$12/(1-Annahmen!$B$15*(1-E6))*((Annahmen!$B$21+E7*(Annahmen!$B$30-Annahmen!$B$21))+(Annahmen!$B$25+E7*(Annahmen!$B$34-Annahmen!$B$25))+(Annahmen!$B$29+E7*(Annahmen!$B$38-Annahmen!$B$29)))+Annahmen!$B$13/(1-Annahmen!$B$15*(1-E6))*((Annahmen!$B$22+E7*(Annahmen!$B$31-Annahmen!$B$22))+(Annahmen!$B$26+E7*(Annahmen!$B$35-Annahmen!$B$26))+(Annahmen!$B$29+E7*(Annahmen!$B$38-Annahmen!$B$29)))+Annahmen!$B$14/(1-Annahmen!$B$15*(1-E6))*((Annahmen!$B$23+E7*(Annahmen!$B$32-Annahmen!$B$23))+(Annahmen!$B$27+E7*(Annahmen!$B$36-Annahmen!$B$27))+(Annahmen!$B$29+E7*(Annahmen!$B$38-Annahmen!$B$29)))+Annahmen!$B$15*E6*((Annahmen!$B$24+E7*(Annahmen!$B$33-Annahmen!$B$24))+(Annahmen!$B$28+E7*(Annahmen!$B$37-Annahmen!$B$28))+(Annahmen!$B$29+E7*(Annahmen!$B$38-Annahmen!$B$29))) -> 19.033333 | F8: =Annahmen!$B$12/(1-Annahmen!$B$15*(1-F6))*((Annahmen!$B$21+F7*(Annahmen!$B$30-Annahmen!$B$21))+(Annahmen!$B$25+F7*(Annahmen!$B$34-Annahmen!$B$25))+(Annahmen!$B$29+F7*(Annahmen!$B$38-Annahmen!$B$29)))+Annahmen!$B$13/(1-Annahmen!$B$15*(1-F6))*((Annahmen!$B$22+F7*(Annahmen!$B$31-Annahmen!$B$22))+(Annahmen!$B$26+F7*(Annahmen!$B$35-Annahmen!$B$26))+(Annahmen!$B$29+F7*(Annahmen!$B$38-Annahmen!$B$29)))+Annahmen!$B$14/(1-Annahmen!$B$15*(1-F6))*((Annahmen!$B$23+F7*(Annahmen!$B$32-Annahmen!$B$23))+(Annahmen!$B$27+F7*(Annahmen!$B$36-Annahmen!$B$27))+(Annahmen!$B$29+F7*(Annahmen!$B$38-Annahmen!$B$29)))+Annahmen!$B$15*F6*((Annahmen!$B$24+F7*(Annahmen!$B$33-Annahmen!$B$24))+(Annahmen!$B$28+F7*(Annahmen!$B$37-Annahmen!$B$28))+(Annahmen!$B$29+F7*(Annahmen!$B$38-Annahmen!$B$29))) -> 19.033333 | G8: =Annahmen!$B$12/(1-Annahmen!$B$15*(1-G6))*((Annahmen!$B$21+G7*(Annahmen!$B$30-Annahmen!$B$21))+(Annahmen!$B$25+G7*(Annahmen!$B$34-Annahmen!$B$25))+(Annahmen!$B$29+G7*(Annahmen!$B$38-Annahmen!$B$29)))+Annahmen!$B$13/(1-Annahmen!$B$15*(1-G6))*((Annahmen!$B$22+G7*(Annahmen!$B$31-Annahmen!$B$22))+(Annahmen!$B$26+G7*(Annahmen!$B$35-Annahmen!$B$26))+(Annahmen!$B$29+G7*(Annahmen!$B$38-Annahmen!$B$29)))+Annahmen!$B$14/(1-Annahmen!$B$15*(1-G6))*((Annahmen!$B$23+G7*(Annahmen!$B$32-Annahmen!$B$23))+(Annahmen!$B$27+G7*(Annahmen!$B$36-Annahmen!$B$27))+(Annahmen!$B$29+G7*(Annahmen!$B$38-Annahmen!$B$29)))+Annahmen!$B$15*G6*((Annahmen!$B$24+G7*(Annahmen!$B$33-Annahmen!$B$24))+(Annahmen!$B$28+G7*(Annahmen!$B$37-Annahmen!$B$28))+(Annahmen!$B$29+G7*(Annahmen!$B$38-Annahmen!$B$29))) -> 19.033333 | H8: =Annahmen!$B$12/(1-Annahmen!$B$15*(1-H6))*((Annahmen!$B$21+H7*(Annahmen!$B$30-Annahmen!$B$21))+(Annahmen!$B$25+H7*(Annahmen!$B$34-Annahmen!$B$25))+(Annahmen!$B$29+H7*(Annahmen!$B$38-Annahmen!$B$29)))+Annahmen!$B$13/(1-Annahmen!$B$15*(1-H6))*((Annahmen!$B$22+H7*(Annahmen!$B$31-Annahmen!$B$22))+(Annahmen!$B$26+H7*(Annahmen!$B$35-Annahmen!$B$26))+(Annahmen!$B$29+H7*(Annahmen!$B$38-Annahmen!$B$29)))+Annahmen!$B$14/(1-Annahmen!$B$15*(1-H6))*((Annahmen!$B$23+H7*(Annahmen!$B$32-Annahmen!$B$23))+(Annahmen!$B$27+H7*(Annahmen!$B$36-Annahmen!$B$27))+(Annahmen!$B$29+H7*(Annahmen!$B$38-Annahmen!$B$29)))+Annahmen!$B$15*H6*((Annahmen!$B$24+H7*(Annahmen!$B$33-Annahmen!$B$24))+(Annahmen!$B$28+H7*(Annahmen!$B$37-Annahmen!$B$28))+(Annahmen!$B$29+H7*(Annahmen!$B$38-Annahmen!$B$29))) -> 19.033333 | I8: =Annahmen!$B$12/(1-Annahmen!$B$15*(1-I6))*((Annahmen!$B$21+I7*(Annahmen!$B$30-Annahmen!$B$21))+(Annahmen!$B$25+I7*(Annahmen!$B$34-Annahmen!$B$25))+(Annahmen!$B$29+I7*(Annahmen!$B$38-Annahmen!$B$29)))+Annahmen!$B$13/(1-Annahmen!$B$15*(1-I6))*((Annahmen!$B$22+I7*(Annahmen!$B$31-Annahmen!$B$22))+(Annahmen!$B$26+I7*(Annahmen!$B$35-Annahmen!$B$26))+(Annahmen!$B$29+I7*(Annahmen!$B$38-Annahmen!$B$29)))+Annahmen!$B$14/(1-Annahmen!$B$15*(1-I6))*((Annahmen!$B$23+I7*(Annahmen!$B$32-Annahmen!$B$23))+(Annahmen!$B$27+I7*(Annahmen!$B$36-Annahmen!$B$27))+(Annahmen!$B$29+I7*(Annahmen!$B$38-Annahmen!$B$29)))+Annahmen!$B$15*I6*((Annahmen!$B$24+I7*(Annahmen!$B$33-Annahmen!$B$24))+(Annahmen!$B$28+I7*(Annahmen!$B$37-Annahmen!$B$28))+(Annahmen!$B$29+I7*(Annahmen!$B$38-Annahmen!$B$29))) -> 18.275 | ... Y8: =Annahmen!$B$12/(1-Annahmen!$B$15*(1-Y6))*((Annahmen!$B$21+Y7*(Annahmen!$B$30-Annahmen!$B$21))+(Annahmen!$B$25+Y7*(Annahmen!$B$34-Annahmen!$B$25))+(Annahmen!$B$29+Y7*(Annahmen!$B$38-Annahmen!$B$29)))+Annahmen!$B$13/(1-Annahmen!$B$15*(1-Y6))*((Annahmen!$B$22+Y7*(Annahmen!$B$31-Annahmen!$B$22))+(Annahmen!$B$26+Y7*(Annahmen!$B$35-Annahmen!$B$26))+(Annahmen!$B$29+Y7*(Annahmen!$B$38-Annahmen!$B$29)))+Annahmen!$B$14/(1-Annahmen!$B$15*(1-Y6))*((Annahmen!$B$23+Y7*(Annahmen!$B$32-Annahmen!$B$23))+(Annahmen!$B$27+Y7*(Annahmen!$B$36-Annahmen!$B$27))+(Annahmen!$B$29+Y7*(Annahmen!$B$38-Annahmen!$B$29)))+Annahmen!$B$15*Y6*((Annahmen!$B$24+Y7*(Annahmen!$B$33-Annahmen!$B$24))+(Annahmen!$B$28+Y7*(Annahmen!$B$37-Annahmen!$B$28))+(Annahmen!$B$29+Y7*(Annahmen!$B$38-Annahmen!$B$29))) -> 18.275
A9: Laufende Stunden (Bestand) | B9: =0*(Annahmen!$B$25+B7*(Annahmen!$B$34-Annahmen!$B$25))+0*(Annahmen!$B$26+B7*(Annahmen!$B$35-Annahmen!$B$26))+0*(Annahmen!$B$27+B7*(Annahmen!$B$36-Annahmen!$B$27))+0*(Annahmen!$B$28+B7*(Annahmen!$B$37-Annahmen!$B$28)) -> 0 | C9: =B14*(Annahmen!$B$25+C7*(Annahmen!$B$34-Annahmen!$B$25))+B15*(Annahmen!$B$26+C7*(Annahmen!$B$35-Annahmen!$B$26))+B16*(Annahmen!$B$27+C7*(Annahmen!$B$36-Annahmen!$B$27))+B17*(Annahmen!$B$28+C7*(Annahmen!$B$37-Annahmen!$B$28)) -> 12.833333 | D9: =C14*(Annahmen!$B$25+D7*(Annahmen!$B$34-Annahmen!$B$25))+C15*(Annahmen!$B$26+D7*(Annahmen!$B$35-Annahmen!$B$26))+C16*(Annahmen!$B$27+D7*(Annahmen!$B$36-Annahmen!$B$27))+C17*(Annahmen!$B$28+D7*(Annahmen!$B$37-Annahmen!$B$28)) -> 13.312667 | E9: =D14*(Annahmen!$B$25+E7*(Annahmen!$B$34-Annahmen!$B$25))+D15*(Annahmen!$B$26+E7*(Annahmen!$B$35-Annahmen!$B$26))+D16*(Annahmen!$B$27+E7*(Annahmen!$B$36-Annahmen!$B$27))+D17*(Annahmen!$B$28+E7*(Annahmen!$B$37-Annahmen!$B$28)) -> 23.10834 | F9: =E14*(Annahmen!$B$25+F7*(Annahmen!$B$34-Annahmen!$B$25))+E15*(Annahmen!$B$26+F7*(Annahmen!$B$35-Annahmen!$B$26))+E16*(Annahmen!$B$27+F7*(Annahmen!$B$36-Annahmen!$B$27))+E17*(Annahmen!$B$28+F7*(Annahmen!$B$37-Annahmen!$B$28)) -> 32.680269 | G9: =F14*(Annahmen!$B$25+G7*(Annahmen!$B$34-Annahmen!$B$25))+F15*(Annahmen!$B$26+G7*(Annahmen!$B$35-Annahmen!$B$26))+F16*(Annahmen!$B$27+G7*(Annahmen!$B$36-Annahmen!$B$27))+F17*(Annahmen!$B$28+G7*(Annahmen!$B$37-Annahmen!$B$28)) -> 42.033782 | H9: =G14*(Annahmen!$B$25+H7*(Annahmen!$B$34-Annahmen!$B$25))+G15*(Annahmen!$B$26+H7*(Annahmen!$B$35-Annahmen!$B$26))+G16*(Annahmen!$B$27+H7*(Annahmen!$B$36-Annahmen!$B$27))+G17*(Annahmen!$B$28+H7*(Annahmen!$B$37-Annahmen!$B$28)) -> 51.174077 | I9: =H14*(Annahmen!$B$25+I7*(Annahmen!$B$34-Annahmen!$B$25))+H15*(Annahmen!$B$26+I7*(Annahmen!$B$35-Annahmen!$B$26))+H16*(Annahmen!$B$27+I7*(Annahmen!$B$36-Annahmen!$B$27))+H17*(Annahmen!$B$28+I7*(Annahmen!$B$37-Annahmen!$B$28)) -> 60.106223 | J9: =I14*(Annahmen!$B$25+J7*(Annahmen!$B$34-Annahmen!$B$25))+I15*(Annahmen!$B$26+J7*(Annahmen!$B$35-Annahmen!$B$26))+I16*(Annahmen!$B$27+J7*(Annahmen!$B$36-Annahmen!$B$27))+I17*(Annahmen!$B$28+J7*(Annahmen!$B$37-Annahmen!$B$28)) -> 69.310161 | ... Y9: =X14*(Annahmen!$B$25+Y7*(Annahmen!$B$34-Annahmen!$B$25))+X15*(Annahmen!$B$26+Y7*(Annahmen!$B$35-Annahmen!$B$26))+X16*(Annahmen!$B$27+Y7*(Annahmen!$B$36-Annahmen!$B$27))+X17*(Annahmen!$B$28+Y7*(Annahmen!$B$37-Annahmen!$B$28)) -> 145.71632
A10: Möglich nach Stunden | B10: =MAX(0,(Annahmen!$B$41-B9)/B8) -> 4.5842697 | C10: =MAX(0,(Annahmen!$B$41-C9)/C8) -> 4.2382022 | D10: =MAX(0,(Annahmen!$B$41-D9)/D8) -> 8.2322592 | E10: =MAX(0,(Annahmen!$B$41-E9)/E8) -> 7.7176004 | F10: =MAX(0,(Annahmen!$B$41-F9)/F8) -> 7.2146969 | G10: =MAX(0,(Annahmen!$B$41-G9)/G8) -> 6.7232689 | H10: =MAX(0,(Annahmen!$B$41-H9)/H8) -> 6.2430432 | I10: =MAX(0,(Annahmen!$B$41-I9)/I8) -> 6.0133394 | ... Y10: =MAX(0,(Annahmen!$B$41-Y9)/Y8) -> 1.3287922
A11: Abschlüsse | B11: =MIN(B5,B10) -> 2 | C11: =MIN(C5,C10) -> 2 | D11: =MIN(D5,D10) -> 3 | E11: =MIN(E5,E10) -> 3 | F11: =MIN(F5,F10) -> 3 | G11: =MIN(G5,G10) -> 3 | H11: =MIN(H5,H10) -> 3 | I11: =MIN(I5,I10) -> 3 | ... Y11: =MIN(Y5,Y10) -> 1.3287922
A12: Abschlüsse kumuliert | B12: =0+B11 -> 2 | C12: =B12+C11 -> 4 | D12: =C12+D11 -> 7 | E12: =D12+E11 -> 10 | F12: =E12+F11 -> 13 | G12: =F12+G11 -> 16 | H12: =G12+H11 -> 19 | I12: =H12+I11 -> 22 | J12: =I12+J11 -> 25 | ... Y12: =X12+Y11 -> 58.378299
A14: Aktive Pflege-Kunden | B14: =0*(1-Annahmen!$B$17)+B11*Annahmen!$B$12/(1-Annahmen!$B$15*(1-B6)) -> 0.66666667 | C14: =B14*(1-Annahmen!$B$17)+C11*Annahmen!$B$12/(1-Annahmen!$B$15*(1-C6)) -> 1.3266667 | D14: =C14*(1-Annahmen!$B$17)+D11*Annahmen!$B$12/(1-Annahmen!$B$15*(1-D6)) -> 2.3134 | E14: =D14*(1-Annahmen!$B$17)+E11*Annahmen!$B$12/(1-Annahmen!$B$15*(1-E6)) -> 3.290266 | F14: =E14*(1-Annahmen!$B$17)+F11*Annahmen!$B$12/(1-Annahmen!$B$15*(1-F6)) -> 4.2573633 | G14: =F14*(1-Annahmen!$B$17)+G11*Annahmen!$B$12/(1-Annahmen!$B$15*(1-G6)) -> 5.2147897 | H14: =G14*(1-Annahmen!$B$17)+H11*Annahmen!$B$12/(1-Annahmen!$B$15*(1-H6)) -> 6.1626418 | I14: =H14*(1-Annahmen!$B$17)+I11*Annahmen!$B$12/(1-Annahmen!$B$15*(1-I6)) -> 6.8510154 | J14: =I14*(1-Annahmen!$B$17)+J11*Annahmen!$B$12/(1-Annahmen!$B$15*(1-J6)) -> 7.5325052 | ... Y14: =X14*(1-Annahmen!$B$17)+Y11*Annahmen!$B$12/(1-Annahmen!$B$15*(1-Y6)) -> 14.165305
A15: Aktive Programm-Kunden | B15: =0*(1-Annahmen!$B$18)+B11*Annahmen!$B$13/(1-Annahmen!$B$15*(1-B6)) -> 0.66666667 | C15: =B15*(1-Annahmen!$B$18)+C11*Annahmen!$B$13/(1-Annahmen!$B$15*(1-C6)) -> 1.32 | D15: =C15*(1-Annahmen!$B$18)+D11*Annahmen!$B$13/(1-Annahmen!$B$15*(1-D6)) -> 2.2936 | E15: =D15*(1-Annahmen!$B$18)+E11*Annahmen!$B$13/(1-Annahmen!$B$15*(1-E6)) -> 3.247728 | F15: =E15*(1-Annahmen!$B$18)+F11*Annahmen!$B$13/(1-Annahmen!$B$15*(1-F6)) -> 4.1827734 | G15: =F15*(1-Annahmen!$B$18)+G11*Annahmen!$B$13/(1-Annahmen!$B$15*(1-G6)) -> 5.099118 | H15: =G15*(1-Annahmen!$B$18)+H11*Annahmen!$B$13/(1-Annahmen!$B$15*(1-H6)) -> 5.9971356 | I15: =H15*(1-Annahmen!$B$18)+I11*Annahmen!$B$13/(1-Annahmen!$B$15*(1-I6)) -> 6.6271929 | J15: =I15*(1-Annahmen!$B$18)+J11*Annahmen!$B$13/(1-Annahmen!$B$15*(1-J6)) -> 7.244649 | ... Y15: =X15*(1-Annahmen!$B$18)+Y11*Annahmen!$B$13/(1-Annahmen!$B$15*(1-Y6)) -> 12.438337
A16: Aktive SEO-Kunden | B16: =0*(1-Annahmen!$B$19)+B11*Annahmen!$B$14/(1-Annahmen!$B$15*(1-B6)) -> 0.66666667 | C16: =B16*(1-Annahmen!$B$19)+C11*Annahmen!$B$14/(1-Annahmen!$B$15*(1-C6)) -> 1.3133333 | D16: =C16*(1-Annahmen!$B$19)+D11*Annahmen!$B$14/(1-Annahmen!$B$15*(1-D6)) -> 2.2739333 | E16: =D16*(1-Annahmen!$B$19)+E11*Annahmen!$B$14/(1-Annahmen!$B$15*(1-E6)) -> 3.2057153 | F16: =E16*(1-Annahmen!$B$19)+F11*Annahmen!$B$14/(1-Annahmen!$B$15*(1-F6)) -> 4.1095439 | G16: =F16*(1-Annahmen!$B$19)+G11*Annahmen!$B$14/(1-Annahmen!$B$15*(1-G6)) -> 4.9862576 | H16: =G16*(1-Annahmen!$B$19)+H11*Annahmen!$B$14/(1-Annahmen!$B$15*(1-H6)) -> 5.8366698 | I16: =H16*(1-Annahmen!$B$19)+I11*Annahmen!$B$14/(1-Annahmen!$B$15*(1-I6)) -> 6.4115697 | J16: =I16*(1-Annahmen!$B$19)+J11*Annahmen!$B$14/(1-Annahmen!$B$15*(1-J6)) -> 6.9692226 | ... Y16: =X16*(1-Annahmen!$B$19)+Y11*Annahmen!$B$14/(1-Annahmen!$B$15*(1-Y6)) -> 10.954883
A17: Aktive Recruiting-Kunden | B17: =0*(1-Annahmen!$B$20)+B11*Annahmen!$B$15*B6 -> 0 | C17: =B17*(1-Annahmen!$B$20)+C11*Annahmen!$B$15*C6 -> 0 | D17: =C17*(1-Annahmen!$B$20)+D11*Annahmen!$B$15*D6 -> 0 | E17: =D17*(1-Annahmen!$B$20)+E11*Annahmen!$B$15*E6 -> 0 | F17: =E17*(1-Annahmen!$B$20)+F11*Annahmen!$B$15*F6 -> 0 | G17: =F17*(1-Annahmen!$B$20)+G11*Annahmen!$B$15*G6 -> 0 | H17: =G17*(1-Annahmen!$B$20)+H11*Annahmen!$B$15*H6 -> 0 | I17: =H17*(1-Annahmen!$B$20)+I11*Annahmen!$B$15*I6 -> 0.75 | J17: =I17*(1-Annahmen!$B$20)+J11*Annahmen!$B$15*J6 -> 1.4625 | ... Y17: =X17*(1-Annahmen!$B$20)+Y11*Annahmen!$B$15*Y6 -> 6.2680238
A19: MRR | B19: =B14*Annahmen!$B$6+B15*Annahmen!$B$7+B16*Annahmen!$B$9+B17*Annahmen!$B$10 -> 1186 | C19: =C14*Annahmen!$B$6+C15*Annahmen!$B$7+C16*Annahmen!$B$9+C17*Annahmen!$B$10 -> 2345.2733 | D19: =D14*Annahmen!$B$6+D15*Annahmen!$B$7+D16*Annahmen!$B$9+D17*Annahmen!$B$10 -> 4071.4539 | E19: =E14*Annahmen!$B$6+E15*Annahmen!$B$7+E16*Annahmen!$B$9+E17*Annahmen!$B$10 -> 5758.7966 | F19: =F14*Annahmen!$B$6+F15*Annahmen!$B$7+F16*Annahmen!$B$9+F17*Annahmen!$B$10 -> 7408.2213 | G19: =G14*Annahmen!$B$6+G15*Annahmen!$B$7+G16*Annahmen!$B$9+G17*Annahmen!$B$10 -> 9020.6248 | H19: =H14*Annahmen!$B$6+H15*Annahmen!$B$7+H16*Annahmen!$B$9+H17*Annahmen!$B$10 -> 10596.882 | I19: =I14*Annahmen!$B$6+I15*Annahmen!$B$7+I16*Annahmen!$B$9+I17*Annahmen!$B$10 -> 12285.596 | ... Y19: =Y14*Annahmen!$B$6+Y15*Annahmen!$B$7+Y16*Annahmen!$B$9+Y17*Annahmen!$B$10 -> 26427.305
A20: Einmalumsatz | B20: =B11*(Annahmen!$B$12/(1-Annahmen!$B$15*(1-B6))*Annahmen!$B$5+Annahmen!$B$13/(1-Annahmen!$B$15*(1-B6))*Annahmen!$B$8+Annahmen!$B$15*B6*Annahmen!$B$11) -> 2460 | C20: =C11*(Annahmen!$B$12/(1-Annahmen!$B$15*(1-C6))*Annahmen!$B$5+Annahmen!$B$13/(1-Annahmen!$B$15*(1-C6))*Annahmen!$B$8+Annahmen!$B$15*C6*Annahmen!$B$11) -> 2460 | D20: =D11*(Annahmen!$B$12/(1-Annahmen!$B$15*(1-D6))*Annahmen!$B$5+Annahmen!$B$13/(1-Annahmen!$B$15*(1-D6))*Annahmen!$B$8+Annahmen!$B$15*D6*Annahmen!$B$11) -> 3690 | E20: =E11*(Annahmen!$B$12/(1-Annahmen!$B$15*(1-E6))*Annahmen!$B$5+Annahmen!$B$13/(1-Annahmen!$B$15*(1-E6))*Annahmen!$B$8+Annahmen!$B$15*E6*Annahmen!$B$11) -> 3690 | F20: =F11*(Annahmen!$B$12/(1-Annahmen!$B$15*(1-F6))*Annahmen!$B$5+Annahmen!$B$13/(1-Annahmen!$B$15*(1-F6))*Annahmen!$B$8+Annahmen!$B$15*F6*Annahmen!$B$11) -> 3690 | G20: =G11*(Annahmen!$B$12/(1-Annahmen!$B$15*(1-G6))*Annahmen!$B$5+Annahmen!$B$13/(1-Annahmen!$B$15*(1-G6))*Annahmen!$B$8+Annahmen!$B$15*G6*Annahmen!$B$11) -> 3690 | H20: =H11*(Annahmen!$B$12/(1-Annahmen!$B$15*(1-H6))*Annahmen!$B$5+Annahmen!$B$13/(1-Annahmen!$B$15*(1-H6))*Annahmen!$B$8+Annahmen!$B$15*H6*Annahmen!$B$11) -> 3690 | I20: =I11*(Annahmen!$B$12/(1-Annahmen!$B$15*(1-I6))*Annahmen!$B$5+Annahmen!$B$13/(1-Annahmen!$B$15*(1-I6))*Annahmen!$B$8+Annahmen!$B$15*I6*Annahmen!$B$11) -> 3885 | ... Y20: =Y11*(Annahmen!$B$12/(1-Annahmen!$B$15*(1-Y6))*Annahmen!$B$5+Annahmen!$B$13/(1-Annahmen!$B$15*(1-Y6))*Annahmen!$B$8+Annahmen!$B$15*Y6*Annahmen!$B$11) -> 1720.7859
A21: Umsatz | B21: =B19+B20 -> 3646 | C21: =C19+C20 -> 4805.2733 | D21: =D19+D20 -> 7761.4539 | E21: =E19+E20 -> 9448.7966 | F21: =F19+F20 -> 11098.221 | G21: =G19+G20 -> 12710.625 | H21: =H19+H20 -> 14286.882 | I21: =I19+I20 -> 16170.596 | ... Y21: =Y19+Y20 -> 28148.091
A22: Kosten | B22: =Annahmen!$B$42+Annahmen!$B$43+B7*Annahmen!$B$40 -> 355 | C22: =Annahmen!$B$42+Annahmen!$B$43+C7*Annahmen!$B$40 -> 355 | D22: =Annahmen!$B$42+Annahmen!$B$43+D7*Annahmen!$B$40 -> 505 | E22: =Annahmen!$B$42+Annahmen!$B$43+E7*Annahmen!$B$40 -> 505 | F22: =Annahmen!$B$42+Annahmen!$B$43+F7*Annahmen!$B$40 -> 505 | G22: =Annahmen!$B$42+Annahmen!$B$43+G7*Annahmen!$B$40 -> 505 | H22: =Annahmen!$B$42+Annahmen!$B$43+H7*Annahmen!$B$40 -> 505 | I22: =Annahmen!$B$42+Annahmen!$B$43+I7*Annahmen!$B$40 -> 505 | ... Y22: =Annahmen!$B$42+Annahmen!$B$43+Y7*Annahmen!$B$40 -> 505
A23: Ergebnis vor Steuern (= Einkommen Gründer) | B23: =B21-B22 -> 3291 | C23: =C21-C22 -> 4450.2733 | D23: =D21-D22 -> 7256.4539 | E23: =E21-E22 -> 8943.7966 | F23: =F21-F22 -> 10593.221 | G23: =G21-G22 -> 12205.625 | H23: =H21-H22 -> 13781.882 | I23: =I21-I22 -> 15665.596 | ... Y23: =Y21-Y22 -> 27643.091
A24: Kasse kumuliert | B24: =B23 -> 3291 | C24: =B24+C23 -> 7741.2733 | D24: =C24+D23 -> 14997.727 | E24: =D24+E23 -> 23941.524 | F24: =E24+F23 -> 34534.745 | G24: =F24+G23 -> 46740.37 | H24: =G24+H23 -> 60522.252 | I24: =H24+I23 -> 76187.848 | J24: =I24+J23 -> 93488.094 | ... Y24: =X24+Y23 -> 472405.56
A25: Belegte Stunden | B25: =B9+B11*B8 -> 74.166667 | C25: =C9+C11*C8 -> 87 | D25: =D9+D11*D8 -> 70.412667 | E25: =E9+E11*E8 -> 80.20834 | F25: =F9+F11*F8 -> 89.780269 | G25: =G9+G11*G8 -> 99.133782 | H25: =H9+H11*H8 -> 108.27408 | I25: =I9+I11*I8 -> 114.93122 | ... Y25: =Y9+Y11*Y8 -> 170

Sheet Solo Optimistisch
A1: Solo-Plan · Szenario Optimistisch · von Hand (24 Monate ab Nov 2026)
A2: Abschlüsse = Minimum aus Vertriebstempo und freien Stunden. Kundenzahlen sind Erwartungswerte.
A4: Monat | B4: Nov 26 | C4: Dez 26 | D4: Jan 27 | E4: Feb 27 | F4: Mär 27 | G4: Apr 27 | H4: Mai 27 | I4: Jun 27 | J4: Jul 27 | K4: Aug 27 | L4: Sep 27 | M4: Okt 27 | N4: Nov 27 | O4: Dez 27 | P4: Jan 28 | Q4: Feb 28 | R4: Mär 28 | S4: Apr 28 | T4: Mai 28 | U4: Jun 28 | V4: Jul 28 | W4: Aug 28 | X4: Sep 28 | Y4: Okt 28
A5: Abschluss-Ziel (Vertrieb) | B5: =Annahmen!$D$48 -> 3 | C5: =Annahmen!$D$48 -> 3 | D5: =Annahmen!$D$49 -> 4 | E5: =Annahmen!$D$49 -> 4 | F5: =Annahmen!$D$49 -> 4 | G5: =Annahmen!$D$49 -> 4 | H5: =Annahmen!$D$49 -> 4 | I5: =Annahmen!$D$49 -> 4 | J5: =Annahmen!$D$49 -> 4 | K5: =Annahmen!$D$49 -> 4 | ... Y5: =Annahmen!$D$49 -> 4
A6: Recruiting im Verkauf (1 = ja) | B6: =IF(1>=Annahmen!$B$16,1,0) -> 0 | C6: =IF(2>=Annahmen!$B$16,1,0) -> 0 | D6: =IF(3>=Annahmen!$B$16,1,0) -> 0 | E6: =IF(4>=Annahmen!$B$16,1,0) -> 0 | F6: =IF(5>=Annahmen!$B$16,1,0) -> 0 | G6: =IF(6>=Annahmen!$B$16,1,0) -> 0 | H6: =IF(7>=Annahmen!$B$16,1,0) -> 0 | I6: =IF(8>=Annahmen!$B$16,1,0) -> 1 | J6: =IF(9>=Annahmen!$B$16,1,0) -> 1 | K6: =IF(10>=Annahmen!$B$16,1,0) -> 1 | L6: =IF(11>=Annahmen!$B$16,1,0) -> 1 | M6: =IF(12>=Annahmen!$B$16,1,0) -> 1 | N6: =IF(13>=Annahmen!$B$16,1,0) -> 1 | O6: =IF(14>=Annahmen!$B$16,1,0) -> 1 | P6: =IF(15>=Annahmen!$B$16,1,0) -> 1 | Q6: =IF(16>=Annahmen!$B$16,1,0) -> 1 | R6: =IF(17>=Annahmen!$B$16,1,0) -> 1 | S6: =IF(18>=Annahmen!$B$16,1,0) -> 1 | T6: =IF(19>=Annahmen!$B$16,1,0) -> 1 | U6: =IF(20>=Annahmen!$B$16,1,0) -> 1 | V6: =IF(21>=Annahmen!$B$16,1,0) -> 1 | W6: =IF(22>=Annahmen!$B$16,1,0) -> 1 | X6: =IF(23>=Annahmen!$B$16,1,0) -> 1 | Y6: =IF(24>=Annahmen!$B$16,1,0) -> 1
A7: Automatisierung aktiv (1 = ja) | B7: =0 -> 0 | C7: =0 -> 0 | D7: =0 -> 0 | E7: =0 -> 0 | F7: =0 -> 0 | G7: =0 -> 0 | H7: =0 -> 0 | I7: =0 -> 0 | ... Y7: =0 -> 0
A8: Std. je neuem Abschluss | B8: =Annahmen!$B$12/(1-Annahmen!$B$15*(1-B6))*((Annahmen!$B$21+B7*(Annahmen!$B$30-Annahmen!$B$21))+(Annahmen!$B$25+B7*(Annahmen!$B$34-Annahmen!$B$25))+(Annahmen!$B$29+B7*(Annahmen!$B$38-Annahmen!$B$29)))+Annahmen!$B$13/(1-Annahmen!$B$15*(1-B6))*((Annahmen!$B$22+B7*(Annahmen!$B$31-Annahmen!$B$22))+(Annahmen!$B$26+B7*(Annahmen!$B$35-Annahmen!$B$26))+(Annahmen!$B$29+B7*(Annahmen!$B$38-Annahmen!$B$29)))+Annahmen!$B$14/(1-Annahmen!$B$15*(1-B6))*((Annahmen!$B$23+B7*(Annahmen!$B$32-Annahmen!$B$23))+(Annahmen!$B$27+B7*(Annahmen!$B$36-Annahmen!$B$27))+(Annahmen!$B$29+B7*(Annahmen!$B$38-Annahmen!$B$29)))+Annahmen!$B$15*B6*((Annahmen!$B$24+B7*(Annahmen!$B$33-Annahmen!$B$24))+(Annahmen!$B$28+B7*(Annahmen!$B$37-Annahmen!$B$28))+(Annahmen!$B$29+B7*(Annahmen!$B$38-Annahmen!$B$29))) -> 37.083333 | C8: =Annahmen!$B$12/(1-Annahmen!$B$15*(1-C6))*((Annahmen!$B$21+C7*(Annahmen!$B$30-Annahmen!$B$21))+(Annahmen!$B$25+C7*(Annahmen!$B$34-Annahmen!$B$25))+(Annahmen!$B$29+C7*(Annahmen!$B$38-Annahmen!$B$29)))+Annahmen!$B$13/(1-Annahmen!$B$15*(1-C6))*((Annahmen!$B$22+C7*(Annahmen!$B$31-Annahmen!$B$22))+(Annahmen!$B$26+C7*(Annahmen!$B$35-Annahmen!$B$26))+(Annahmen!$B$29+C7*(Annahmen!$B$38-Annahmen!$B$29)))+Annahmen!$B$14/(1-Annahmen!$B$15*(1-C6))*((Annahmen!$B$23+C7*(Annahmen!$B$32-Annahmen!$B$23))+(Annahmen!$B$27+C7*(Annahmen!$B$36-Annahmen!$B$27))+(Annahmen!$B$29+C7*(Annahmen!$B$38-Annahmen!$B$29)))+Annahmen!$B$15*C6*((Annahmen!$B$24+C7*(Annahmen!$B$33-Annahmen!$B$24))+(Annahmen!$B$28+C7*(Annahmen!$B$37-Annahmen!$B$28))+(Annahmen!$B$29+C7*(Annahmen!$B$38-Annahmen!$B$29))) -> 37.083333 | D8: =Annahmen!$B$12/(1-Annahmen!$B$15*(1-D6))*((Annahmen!$B$21+D7*(Annahmen!$B$30-Annahmen!$B$21))+(Annahmen!$B$25+D7*(Annahmen!$B$34-Annahmen!$B$25))+(Annahmen!$B$29+D7*(Annahmen!$B$38-Annahmen!$B$29)))+Annahmen!$B$13/(1-Annahmen!$B$15*(1-D6))*((Annahmen!$B$22+D7*(Annahmen!$B$31-Annahmen!$B$22))+(Annahmen!$B$26+D7*(Annahmen!$B$35-Annahmen!$B$26))+(Annahmen!$B$29+D7*(Annahmen!$B$38-Annahmen!$B$29)))+Annahmen!$B$14/(1-Annahmen!$B$15*(1-D6))*((Annahmen!$B$23+D7*(Annahmen!$B$32-Annahmen!$B$23))+(Annahmen!$B$27+D7*(Annahmen!$B$36-Annahmen!$B$27))+(Annahmen!$B$29+D7*(Annahmen!$B$38-Annahmen!$B$29)))+Annahmen!$B$15*D6*((Annahmen!$B$24+D7*(Annahmen!$B$33-Annahmen!$B$24))+(Annahmen!$B$28+D7*(Annahmen!$B$37-Annahmen!$B$28))+(Annahmen!$B$29+D7*(Annahmen!$B$38-Annahmen!$B$29))) -> 37.083333 | E8: =Annahmen!$B$12/(1-Annahmen!$B$15*(1-E6))*((Annahmen!$B$21+E7*(Annahmen!$B$30-Annahmen!$B$21))+(Annahmen!$B$25+E7*(Annahmen!$B$34-Annahmen!$B$25))+(Annahmen!$B$29+E7*(Annahmen!$B$38-Annahmen!$B$29)))+Annahmen!$B$13/(1-Annahmen!$B$15*(1-E6))*((Annahmen!$B$22+E7*(Annahmen!$B$31-Annahmen!$B$22))+(Annahmen!$B$26+E7*(Annahmen!$B$35-Annahmen!$B$26))+(Annahmen!$B$29+E7*(Annahmen!$B$38-Annahmen!$B$29)))+Annahmen!$B$14/(1-Annahmen!$B$15*(1-E6))*((Annahmen!$B$23+E7*(Annahmen!$B$32-Annahmen!$B$23))+(Annahmen!$B$27+E7*(Annahmen!$B$36-Annahmen!$B$27))+(Annahmen!$B$29+E7*(Annahmen!$B$38-Annahmen!$B$29)))+Annahmen!$B$15*E6*((Annahmen!$B$24+E7*(Annahmen!$B$33-Annahmen!$B$24))+(Annahmen!$B$28+E7*(Annahmen!$B$37-Annahmen!$B$28))+(Annahmen!$B$29+E7*(Annahmen!$B$38-Annahmen!$B$29))) -> 37.083333 | F8: =Annahmen!$B$12/(1-Annahmen!$B$15*(1-F6))*((Annahmen!$B$21+F7*(Annahmen!$B$30-Annahmen!$B$21))+(Annahmen!$B$25+F7*(Annahmen!$B$34-Annahmen!$B$25))+(Annahmen!$B$29+F7*(Annahmen!$B$38-Annahmen!$B$29)))+Annahmen!$B$13/(1-Annahmen!$B$15*(1-F6))*((Annahmen!$B$22+F7*(Annahmen!$B$31-Annahmen!$B$22))+(Annahmen!$B$26+F7*(Annahmen!$B$35-Annahmen!$B$26))+(Annahmen!$B$29+F7*(Annahmen!$B$38-Annahmen!$B$29)))+Annahmen!$B$14/(1-Annahmen!$B$15*(1-F6))*((Annahmen!$B$23+F7*(Annahmen!$B$32-Annahmen!$B$23))+(Annahmen!$B$27+F7*(Annahmen!$B$36-Annahmen!$B$27))+(Annahmen!$B$29+F7*(Annahmen!$B$38-Annahmen!$B$29)))+Annahmen!$B$15*F6*((Annahmen!$B$24+F7*(Annahmen!$B$33-Annahmen!$B$24))+(Annahmen!$B$28+F7*(Annahmen!$B$37-Annahmen!$B$28))+(Annahmen!$B$29+F7*(Annahmen!$B$38-Annahmen!$B$29))) -> 37.083333 | G8: =Annahmen!$B$12/(1-Annahmen!$B$15*(1-G6))*((Annahmen!$B$21+G7*(Annahmen!$B$30-Annahmen!$B$21))+(Annahmen!$B$25+G7*(Annahmen!$B$34-Annahmen!$B$25))+(Annahmen!$B$29+G7*(Annahmen!$B$38-Annahmen!$B$29)))+Annahmen!$B$13/(1-Annahmen!$B$15*(1-G6))*((Annahmen!$B$22+G7*(Annahmen!$B$31-Annahmen!$B$22))+(Annahmen!$B$26+G7*(Annahmen!$B$35-Annahmen!$B$26))+(Annahmen!$B$29+G7*(Annahmen!$B$38-Annahmen!$B$29)))+Annahmen!$B$14/(1-Annahmen!$B$15*(1-G6))*((Annahmen!$B$23+G7*(Annahmen!$B$32-Annahmen!$B$23))+(Annahmen!$B$27+G7*(Annahmen!$B$36-Annahmen!$B$27))+(Annahmen!$B$29+G7*(Annahmen!$B$38-Annahmen!$B$29)))+Annahmen!$B$15*G6*((Annahmen!$B$24+G7*(Annahmen!$B$33-Annahmen!$B$24))+(Annahmen!$B$28+G7*(Annahmen!$B$37-Annahmen!$B$28))+(Annahmen!$B$29+G7*(Annahmen!$B$38-Annahmen!$B$29))) -> 37.083333 | H8: =Annahmen!$B$12/(1-Annahmen!$B$15*(1-H6))*((Annahmen!$B$21+H7*(Annahmen!$B$30-Annahmen!$B$21))+(Annahmen!$B$25+H7*(Annahmen!$B$34-Annahmen!$B$25))+(Annahmen!$B$29+H7*(Annahmen!$B$38-Annahmen!$B$29)))+Annahmen!$B$13/(1-Annahmen!$B$15*(1-H6))*((Annahmen!$B$22+H7*(Annahmen!$B$31-Annahmen!$B$22))+(Annahmen!$B$26+H7*(Annahmen!$B$35-Annahmen!$B$26))+(Annahmen!$B$29+H7*(Annahmen!$B$38-Annahmen!$B$29)))+Annahmen!$B$14/(1-Annahmen!$B$15*(1-H6))*((Annahmen!$B$23+H7*(Annahmen!$B$32-Annahmen!$B$23))+(Annahmen!$B$27+H7*(Annahmen!$B$36-Annahmen!$B$27))+(Annahmen!$B$29+H7*(Annahmen!$B$38-Annahmen!$B$29)))+Annahmen!$B$15*H6*((Annahmen!$B$24+H7*(Annahmen!$B$33-Annahmen!$B$24))+(Annahmen!$B$28+H7*(Annahmen!$B$37-Annahmen!$B$28))+(Annahmen!$B$29+H7*(Annahmen!$B$38-Annahmen!$B$29))) -> 37.083333 | I8: =Annahmen!$B$12/(1-Annahmen!$B$15*(1-I6))*((Annahmen!$B$21+I7*(Annahmen!$B$30-Annahmen!$B$21))+(Annahmen!$B$25+I7*(Annahmen!$B$34-Annahmen!$B$25))+(Annahmen!$B$29+I7*(Annahmen!$B$38-Annahmen!$B$29)))+Annahmen!$B$13/(1-Annahmen!$B$15*(1-I6))*((Annahmen!$B$22+I7*(Annahmen!$B$31-Annahmen!$B$22))+(Annahmen!$B$26+I7*(Annahmen!$B$35-Annahmen!$B$26))+(Annahmen!$B$29+I7*(Annahmen!$B$38-Annahmen!$B$29)))+Annahmen!$B$14/(1-Annahmen!$B$15*(1-I6))*((Annahmen!$B$23+I7*(Annahmen!$B$32-Annahmen!$B$23))+(Annahmen!$B$27+I7*(Annahmen!$B$36-Annahmen!$B$27))+(Annahmen!$B$29+I7*(Annahmen!$B$38-Annahmen!$B$29)))+Annahmen!$B$15*I6*((Annahmen!$B$24+I7*(Annahmen!$B$33-Annahmen!$B$24))+(Annahmen!$B$28+I7*(Annahmen!$B$37-Annahmen!$B$28))+(Annahmen!$B$29+I7*(Annahmen!$B$38-Annahmen!$B$29))) -> 34.5625 | ... Y8: =Annahmen!$B$12/(1-Annahmen!$B$15*(1-Y6))*((Annahmen!$B$21+Y7*(Annahmen!$B$30-Annahmen!$B$21))+(Annahmen!$B$25+Y7*(Annahmen!$B$34-Annahmen!$B$25))+(Annahmen!$B$29+Y7*(Annahmen!$B$38-Annahmen!$B$29)))+Annahmen!$B$13/(1-Annahmen!$B$15*(1-Y6))*((Annahmen!$B$22+Y7*(Annahmen!$B$31-Annahmen!$B$22))+(Annahmen!$B$26+Y7*(Annahmen!$B$35-Annahmen!$B$26))+(Annahmen!$B$29+Y7*(Annahmen!$B$38-Annahmen!$B$29)))+Annahmen!$B$14/(1-Annahmen!$B$15*(1-Y6))*((Annahmen!$B$23+Y7*(Annahmen!$B$32-Annahmen!$B$23))+(Annahmen!$B$27+Y7*(Annahmen!$B$36-Annahmen!$B$27))+(Annahmen!$B$29+Y7*(Annahmen!$B$38-Annahmen!$B$29)))+Annahmen!$B$15*Y6*((Annahmen!$B$24+Y7*(Annahmen!$B$33-Annahmen!$B$24))+(Annahmen!$B$28+Y7*(Annahmen!$B$37-Annahmen!$B$28))+(Annahmen!$B$29+Y7*(Annahmen!$B$38-Annahmen!$B$29))) -> 34.5625
A9: Laufende Stunden (Bestand) | B9: =0*(Annahmen!$B$25+B7*(Annahmen!$B$34-Annahmen!$B$25))+0*(Annahmen!$B$26+B7*(Annahmen!$B$35-Annahmen!$B$26))+0*(Annahmen!$B$27+B7*(Annahmen!$B$36-Annahmen!$B$27))+0*(Annahmen!$B$28+B7*(Annahmen!$B$37-Annahmen!$B$28)) -> 0 | C9: =B14*(Annahmen!$B$25+C7*(Annahmen!$B$34-Annahmen!$B$25))+B15*(Annahmen!$B$26+C7*(Annahmen!$B$35-Annahmen!$B$26))+B16*(Annahmen!$B$27+C7*(Annahmen!$B$36-Annahmen!$B$27))+B17*(Annahmen!$B$28+C7*(Annahmen!$B$37-Annahmen!$B$28)) -> 19.25 | D9: =C14*(Annahmen!$B$25+D7*(Annahmen!$B$34-Annahmen!$B$25))+C15*(Annahmen!$B$26+D7*(Annahmen!$B$35-Annahmen!$B$26))+C16*(Annahmen!$B$27+D7*(Annahmen!$B$36-Annahmen!$B$27))+C17*(Annahmen!$B$28+D7*(Annahmen!$B$37-Annahmen!$B$28)) -> 38.0575 | E9: =D14*(Annahmen!$B$25+E7*(Annahmen!$B$34-Annahmen!$B$25))+D15*(Annahmen!$B$26+E7*(Annahmen!$B$35-Annahmen!$B$26))+D16*(Annahmen!$B$27+E7*(Annahmen!$B$36-Annahmen!$B$27))+D17*(Annahmen!$B$28+E7*(Annahmen!$B$37-Annahmen!$B$28)) -> 60.013625 | F9: =E14*(Annahmen!$B$25+F7*(Annahmen!$B$34-Annahmen!$B$25))+E15*(Annahmen!$B$26+F7*(Annahmen!$B$35-Annahmen!$B$26))+E16*(Annahmen!$B$27+F7*(Annahmen!$B$36-Annahmen!$B$27))+E17*(Annahmen!$B$28+F7*(Annahmen!$B$37-Annahmen!$B$28)) -> 77.666779 | G9: =F14*(Annahmen!$B$25+G7*(Annahmen!$B$34-Annahmen!$B$25))+F15*(Annahmen!$B$26+G7*(Annahmen!$B$35-Annahmen!$B$26))+F16*(Annahmen!$B$27+G7*(Annahmen!$B$36-Annahmen!$B$27))+F17*(Annahmen!$B$28+G7*(Annahmen!$B$37-Annahmen!$B$28)) -> 91.860928 | H9: =G14*(Annahmen!$B$25+H7*(Annahmen!$B$34-Annahmen!$B$25))+G15*(Annahmen!$B$26+H7*(Annahmen!$B$35-Annahmen!$B$26))+G16*(Annahmen!$B$27+H7*(Annahmen!$B$36-Annahmen!$B$27))+G17*(Annahmen!$B$28+H7*(Annahmen!$B$37-Annahmen!$B$28)) -> 103.27449 | I9: =H14*(Annahmen!$B$25+I7*(Annahmen!$B$34-Annahmen!$B$25))+H15*(Annahmen!$B$26+I7*(Annahmen!$B$35-Annahmen!$B$26))+H16*(Annahmen!$B$27+I7*(Annahmen!$B$36-Annahmen!$B$27))+H17*(Annahmen!$B$28+I7*(Annahmen!$B$37-Annahmen!$B$28)) -> 112.4528 | J9: =I14*(Annahmen!$B$25+J7*(Annahmen!$B$34-Annahmen!$B$25))+I15*(Annahmen!$B$26+J7*(Annahmen!$B$35-Annahmen!$B$26))+I16*(Annahmen!$B$27+J7*(Annahmen!$B$36-Annahmen!$B$27))+I17*(Annahmen!$B$28+J7*(Annahmen!$B$37-Annahmen!$B$28)) -> 120.80332 | ... Y9: =X14*(Annahmen!$B$25+Y7*(Annahmen!$B$34-Annahmen!$B$25))+X15*(Annahmen!$B$26+Y7*(Annahmen!$B$35-Annahmen!$B$26))+X16*(Annahmen!$B$27+Y7*(Annahmen!$B$36-Annahmen!$B$27))+X17*(Annahmen!$B$28+Y7*(Annahmen!$B$37-Annahmen!$B$28)) -> 149.20528
A10: Möglich nach Stunden | B10: =MAX(0,(Annahmen!$B$41-B9)/B8) -> 4.5842697 | C10: =MAX(0,(Annahmen!$B$41-C9)/C8) -> 4.0651685 | D10: =MAX(0,(Annahmen!$B$41-D9)/D8) -> 3.558 | E10: =MAX(0,(Annahmen!$B$41-E9)/E8) -> 2.9659247 | F10: =MAX(0,(Annahmen!$B$41-F9)/F8) -> 2.4898846 | G10: =MAX(0,(Annahmen!$B$41-G9)/G8) -> 2.107121 | H10: =MAX(0,(Annahmen!$B$41-H9)/H8) -> 1.7993396 | I10: =MAX(0,(Annahmen!$B$41-I9)/I8) -> 1.6650183 | ... Y10: =MAX(0,(Annahmen!$B$41-Y9)/Y8) -> 0.60165542
A11: Abschlüsse | B11: =MIN(B5,B10) -> 3 | C11: =MIN(C5,C10) -> 3 | D11: =MIN(D5,D10) -> 3.558 | E11: =MIN(E5,E10) -> 2.9659247 | F11: =MIN(F5,F10) -> 2.4898846 | G11: =MIN(G5,G10) -> 2.107121 | H11: =MIN(H5,H10) -> 1.7993396 | I11: =MIN(I5,I10) -> 1.6650183 | ... Y11: =MIN(Y5,Y10) -> 0.60165542
A12: Abschlüsse kumuliert | B12: =0+B11 -> 3 | C12: =B12+C11 -> 6 | D12: =C12+D11 -> 9.558 | E12: =D12+E11 -> 12.523925 | F12: =E12+F11 -> 15.013809 | G12: =F12+G11 -> 17.12093 | H12: =G12+H11 -> 18.92027 | I12: =H12+I11 -> 20.585288 | J12: =I12+J11 -> 22.0087 | ... Y12: =X12+Y11 -> 33.589091
A14: Aktive Pflege-Kunden | B14: =0*(1-Annahmen!$B$17)+B11*Annahmen!$B$12/(1-Annahmen!$B$15*(1-B6)) -> 1 | C14: =B14*(1-Annahmen!$B$17)+C11*Annahmen!$B$12/(1-Annahmen!$B$15*(1-C6)) -> 1.99 | D14: =C14*(1-Annahmen!$B$17)+D11*Annahmen!$B$12/(1-Annahmen!$B$15*(1-D6)) -> 3.1561 | E14: =D14*(1-Annahmen!$B$17)+E11*Annahmen!$B$12/(1-Annahmen!$B$15*(1-E6)) -> 4.1131806 | F14: =E14*(1-Annahmen!$B$17)+F11*Annahmen!$B$12/(1-Annahmen!$B$15*(1-F6)) -> 4.9020103 | G14: =F14*(1-Annahmen!$B$17)+G11*Annahmen!$B$12/(1-Annahmen!$B$15*(1-G6)) -> 5.5553639 | H14: =G14*(1-Annahmen!$B$17)+H11*Annahmen!$B$12/(1-Annahmen!$B$15*(1-H6)) -> 6.0995901 | I14: =H14*(1-Annahmen!$B$17)+I11*Annahmen!$B$12/(1-Annahmen!$B$15*(1-I6)) -> 6.4548488 | J14: =I14*(1-Annahmen!$B$17)+J11*Annahmen!$B$12/(1-Annahmen!$B$15*(1-J6)) -> 6.7461533 | ... Y14: =X14*(1-Annahmen!$B$17)+Y11*Annahmen!$B$12/(1-Annahmen!$B$15*(1-Y6)) -> 8.4773792
A15: Aktive Programm-Kunden | B15: =0*(1-Annahmen!$B$18)+B11*Annahmen!$B$13/(1-Annahmen!$B$15*(1-B6)) -> 1 | C15: =B15*(1-Annahmen!$B$18)+C11*Annahmen!$B$13/(1-Annahmen!$B$15*(1-C6)) -> 1.98 | D15: =C15*(1-Annahmen!$B$18)+D11*Annahmen!$B$13/(1-Annahmen!$B$15*(1-D6)) -> 3.1264 | E15: =D15*(1-Annahmen!$B$18)+E11*Annahmen!$B$13/(1-Annahmen!$B$15*(1-E6)) -> 4.0525136 | F15: =E15*(1-Annahmen!$B$18)+F11*Annahmen!$B$13/(1-Annahmen!$B$15*(1-F6)) -> 4.8014248 | G15: =F15*(1-Annahmen!$B$18)+G11*Annahmen!$B$13/(1-Annahmen!$B$15*(1-G6)) -> 5.40777 | H15: =G15*(1-Annahmen!$B$18)+H11*Annahmen!$B$13/(1-Annahmen!$B$15*(1-H6)) -> 5.8993945 | I15: =H15*(1-Annahmen!$B$18)+I11*Annahmen!$B$13/(1-Annahmen!$B$15*(1-I6)) -> 6.1976612 | J15: =I15*(1-Annahmen!$B$18)+J11*Annahmen!$B$13/(1-Annahmen!$B$15*(1-J6)) -> 6.429561 | ... Y15: =X15*(1-Annahmen!$B$18)+Y11*Annahmen!$B$13/(1-Annahmen!$B$15*(1-Y6)) -> 7.2238395
A16: Aktive SEO-Kunden | B16: =0*(1-Annahmen!$B$19)+B11*Annahmen!$B$14/(1-Annahmen!$B$15*(1-B6)) -> 1 | C16: =B16*(1-Annahmen!$B$19)+C11*Annahmen!$B$14/(1-Annahmen!$B$15*(1-C6)) -> 1.97 | D16: =C16*(1-Annahmen!$B$19)+D11*Annahmen!$B$14/(1-Annahmen!$B$15*(1-D6)) -> 3.0969 | E16: =D16*(1-Annahmen!$B$19)+E11*Annahmen!$B$14/(1-Annahmen!$B$15*(1-E6)) -> 3.9926346 | F16: =E16*(1-Annahmen!$B$19)+F11*Annahmen!$B$14/(1-Annahmen!$B$15*(1-F6)) -> 4.7028171 | G16: =F16*(1-Annahmen!$B$19)+G11*Annahmen!$B$14/(1-Annahmen!$B$15*(1-G6)) -> 5.2641062 | H16: =G16*(1-Annahmen!$B$19)+H11*Annahmen!$B$14/(1-Annahmen!$B$15*(1-H6)) -> 5.7059629 | I16: =H16*(1-Annahmen!$B$19)+I11*Annahmen!$B$14/(1-Annahmen!$B$15*(1-I6)) -> 5.9510386 | J16: =I16*(1-Annahmen!$B$19)+J11*Annahmen!$B$14/(1-Annahmen!$B$15*(1-J6)) -> 6.1283605 | ... Y16: =X16*(1-Annahmen!$B$19)+Y11*Annahmen!$B$14/(1-Annahmen!$B$15*(1-Y6)) -> 6.1737065
A17: Aktive Recruiting-Kunden | B17: =0*(1-Annahmen!$B$20)+B11*Annahmen!$B$15*B6 -> 0 | C17: =B17*(1-Annahmen!$B$20)+C11*Annahmen!$B$15*C6 -> 0 | D17: =C17*(1-Annahmen!$B$20)+D11*Annahmen!$B$15*D6 -> 0 | E17: =D17*(1-Annahmen!$B$20)+E11*Annahmen!$B$15*E6 -> 0 | F17: =E17*(1-Annahmen!$B$20)+F11*Annahmen!$B$15*F6 -> 0 | G17: =F17*(1-Annahmen!$B$20)+G11*Annahmen!$B$15*G6 -> 0 | H17: =G17*(1-Annahmen!$B$20)+H11*Annahmen!$B$15*H6 -> 0 | I17: =H17*(1-Annahmen!$B$20)+I11*Annahmen!$B$15*I6 -> 0.41625459 | J17: =I17*(1-Annahmen!$B$20)+J11*Annahmen!$B$15*J6 -> 0.75129486 | ... Y17: =X17*(1-Annahmen!$B$20)+Y11*Annahmen!$B$15*Y6 -> 2.323726
A19: MRR | B19: =B14*Annahmen!$B$6+B15*Annahmen!$B$7+B16*Annahmen!$B$9+B17*Annahmen!$B$10 -> 1779 | C19: =C14*Annahmen!$B$6+C15*Annahmen!$B$7+C16*Annahmen!$B$9+C17*Annahmen!$B$10 -> 3517.91 | D19: =D14*Annahmen!$B$6+D15*Annahmen!$B$7+D16*Annahmen!$B$9+D17*Annahmen!$B$10 -> 5548.5749 | E19: =E14*Annahmen!$B$6+E15*Annahmen!$B$7+E16*Annahmen!$B$9+E17*Annahmen!$B$10 -> 7182.4706 | F19: =F14*Annahmen!$B$6+F15*Annahmen!$B$7+F16*Annahmen!$B$9+F17*Annahmen!$B$10 -> 8497.3991 | G19: =G14*Annahmen!$B$6+G15*Annahmen!$B$7+G16*Annahmen!$B$9+G17*Annahmen!$B$10 -> 9555.9017 | H19: =H14*Annahmen!$B$6+H15*Annahmen!$B$7+H16*Annahmen!$B$9+H17*Annahmen!$B$10 -> 10408.252 | I19: =I14*Annahmen!$B$6+I15*Annahmen!$B$7+I16*Annahmen!$B$9+I17*Annahmen!$B$10 -> 11243.983 | ... Y19: =Y14*Annahmen!$B$6+Y15*Annahmen!$B$7+Y16*Annahmen!$B$9+Y17*Annahmen!$B$10 -> 14227.379
A20: Einmalumsatz | B20: =B11*(Annahmen!$B$12/(1-Annahmen!$B$15*(1-B6))*Annahmen!$B$5+Annahmen!$B$13/(1-Annahmen!$B$15*(1-B6))*Annahmen!$B$8+Annahmen!$B$15*B6*Annahmen!$B$11) -> 3690 | C20: =C11*(Annahmen!$B$12/(1-Annahmen!$B$15*(1-C6))*Annahmen!$B$5+Annahmen!$B$13/(1-Annahmen!$B$15*(1-C6))*Annahmen!$B$8+Annahmen!$B$15*C6*Annahmen!$B$11) -> 3690 | D20: =D11*(Annahmen!$B$12/(1-Annahmen!$B$15*(1-D6))*Annahmen!$B$5+Annahmen!$B$13/(1-Annahmen!$B$15*(1-D6))*Annahmen!$B$8+Annahmen!$B$15*D6*Annahmen!$B$11) -> 4376.34 | E20: =E11*(Annahmen!$B$12/(1-Annahmen!$B$15*(1-E6))*Annahmen!$B$5+Annahmen!$B$13/(1-Annahmen!$B$15*(1-E6))*Annahmen!$B$8+Annahmen!$B$15*E6*Annahmen!$B$11) -> 3648.0874 | F20: =F11*(Annahmen!$B$12/(1-Annahmen!$B$15*(1-F6))*Annahmen!$B$5+Annahmen!$B$13/(1-Annahmen!$B$15*(1-F6))*Annahmen!$B$8+Annahmen!$B$15*F6*Annahmen!$B$11) -> 3062.5581 | G20: =G11*(Annahmen!$B$12/(1-Annahmen!$B$15*(1-G6))*Annahmen!$B$5+Annahmen!$B$13/(1-Annahmen!$B$15*(1-G6))*Annahmen!$B$8+Annahmen!$B$15*G6*Annahmen!$B$11) -> 2591.7589 | H20: =H11*(Annahmen!$B$12/(1-Annahmen!$B$15*(1-H6))*Annahmen!$B$5+Annahmen!$B$13/(1-Annahmen!$B$15*(1-H6))*Annahmen!$B$8+Annahmen!$B$15*H6*Annahmen!$B$11) -> 2213.1877 | I20: =I11*(Annahmen!$B$12/(1-Annahmen!$B$15*(1-I6))*Annahmen!$B$5+Annahmen!$B$13/(1-Annahmen!$B$15*(1-I6))*Annahmen!$B$8+Annahmen!$B$15*I6*Annahmen!$B$11) -> 2156.1988 | ... Y20: =Y11*(Annahmen!$B$12/(1-Annahmen!$B$15*(1-Y6))*Annahmen!$B$5+Annahmen!$B$13/(1-Annahmen!$B$15*(1-Y6))*Annahmen!$B$8+Annahmen!$B$15*Y6*Annahmen!$B$11) -> 779.14377
A21: Umsatz | B21: =B19+B20 -> 5469 | C21: =C19+C20 -> 7207.91 | D21: =D19+D20 -> 9924.9149 | E21: =E19+E20 -> 10830.558 | F21: =F19+F20 -> 11559.957 | G21: =G19+G20 -> 12147.661 | H21: =H19+H20 -> 12621.44 | I21: =I19+I20 -> 13400.181 | ... Y21: =Y19+Y20 -> 15006.523
A22: Kosten | B22: =Annahmen!$B$42+Annahmen!$B$43+B7*Annahmen!$B$40 -> 355 | C22: =Annahmen!$B$42+Annahmen!$B$43+C7*Annahmen!$B$40 -> 355 | D22: =Annahmen!$B$42+Annahmen!$B$43+D7*Annahmen!$B$40 -> 355 | E22: =Annahmen!$B$42+Annahmen!$B$43+E7*Annahmen!$B$40 -> 355 | F22: =Annahmen!$B$42+Annahmen!$B$43+F7*Annahmen!$B$40 -> 355 | G22: =Annahmen!$B$42+Annahmen!$B$43+G7*Annahmen!$B$40 -> 355 | H22: =Annahmen!$B$42+Annahmen!$B$43+H7*Annahmen!$B$40 -> 355 | I22: =Annahmen!$B$42+Annahmen!$B$43+I7*Annahmen!$B$40 -> 355 | ... Y22: =Annahmen!$B$42+Annahmen!$B$43+Y7*Annahmen!$B$40 -> 355
A23: Ergebnis vor Steuern (= Einkommen Gründer) | B23: =B21-B22 -> 5114 | C23: =C21-C22 -> 6852.91 | D23: =D21-D22 -> 9569.9149 | E23: =E21-E22 -> 10475.558 | F23: =F21-F22 -> 11204.957 | G23: =G21-G22 -> 11792.661 | H23: =H21-H22 -> 12266.44 | I23: =I21-I22 -> 13045.181 | ... Y23: =Y21-Y22 -> 14651.523
A24: Kasse kumuliert | B24: =B23 -> 5114 | C24: =B24+C23 -> 11966.91 | D24: =C24+D23 -> 21536.825 | E24: =D24+E23 -> 32012.383 | F24: =E24+F23 -> 43217.34 | G24: =F24+G23 -> 55010.001 | H24: =G24+H23 -> 67276.44 | I24: =H24+I23 -> 80321.622 | J24: =I24+J23 -> 93706.873 | ... Y24: =X24+Y23 -> 309032.19
A25: Belegte Stunden | B25: =B9+B11*B8 -> 111.25 | C25: =C9+C11*C8 -> 130.5 | D25: =D9+D11*D8 -> 170 | E25: =E9+E11*E8 -> 170 | F25: =F9+F11*F8 -> 170 | G25: =G9+G11*G8 -> 170 | H25: =H9+H11*H8 -> 170 | I25: =I9+I11*I8 -> 170 | ... Y25: =Y9+Y11*Y8 -> 170

Sheet Solo Optimistisch auto
A1: Solo-Plan · Szenario Optimistisch · automatisiert ab Kunde 5 (24 Monate ab Nov 2026)
A2: Abschlüsse = Minimum aus Vertriebstempo und freien Stunden. Kundenzahlen sind Erwartungswerte.
A4: Monat | B4: Nov 26 | C4: Dez 26 | D4: Jan 27 | E4: Feb 27 | F4: Mär 27 | G4: Apr 27 | H4: Mai 27 | I4: Jun 27 | J4: Jul 27 | K4: Aug 27 | L4: Sep 27 | M4: Okt 27 | N4: Nov 27 | O4: Dez 27 | P4: Jan 28 | Q4: Feb 28 | R4: Mär 28 | S4: Apr 28 | T4: Mai 28 | U4: Jun 28 | V4: Jul 28 | W4: Aug 28 | X4: Sep 28 | Y4: Okt 28
A5: Abschluss-Ziel (Vertrieb) | B5: =Annahmen!$D$48 -> 3 | C5: =Annahmen!$D$48 -> 3 | D5: =Annahmen!$D$49 -> 4 | E5: =Annahmen!$D$49 -> 4 | F5: =Annahmen!$D$49 -> 4 | G5: =Annahmen!$D$49 -> 4 | H5: =Annahmen!$D$49 -> 4 | I5: =Annahmen!$D$49 -> 4 | J5: =Annahmen!$D$49 -> 4 | K5: =Annahmen!$D$49 -> 4 | ... Y5: =Annahmen!$D$49 -> 4
A6: Recruiting im Verkauf (1 = ja) | B6: =IF(1>=Annahmen!$B$16,1,0) -> 0 | C6: =IF(2>=Annahmen!$B$16,1,0) -> 0 | D6: =IF(3>=Annahmen!$B$16,1,0) -> 0 | E6: =IF(4>=Annahmen!$B$16,1,0) -> 0 | F6: =IF(5>=Annahmen!$B$16,1,0) -> 0 | G6: =IF(6>=Annahmen!$B$16,1,0) -> 0 | H6: =IF(7>=Annahmen!$B$16,1,0) -> 0 | I6: =IF(8>=Annahmen!$B$16,1,0) -> 1 | J6: =IF(9>=Annahmen!$B$16,1,0) -> 1 | K6: =IF(10>=Annahmen!$B$16,1,0) -> 1 | L6: =IF(11>=Annahmen!$B$16,1,0) -> 1 | M6: =IF(12>=Annahmen!$B$16,1,0) -> 1 | N6: =IF(13>=Annahmen!$B$16,1,0) -> 1 | O6: =IF(14>=Annahmen!$B$16,1,0) -> 1 | P6: =IF(15>=Annahmen!$B$16,1,0) -> 1 | Q6: =IF(16>=Annahmen!$B$16,1,0) -> 1 | R6: =IF(17>=Annahmen!$B$16,1,0) -> 1 | S6: =IF(18>=Annahmen!$B$16,1,0) -> 1 | T6: =IF(19>=Annahmen!$B$16,1,0) -> 1 | U6: =IF(20>=Annahmen!$B$16,1,0) -> 1 | V6: =IF(21>=Annahmen!$B$16,1,0) -> 1 | W6: =IF(22>=Annahmen!$B$16,1,0) -> 1 | X6: =IF(23>=Annahmen!$B$16,1,0) -> 1 | Y6: =IF(24>=Annahmen!$B$16,1,0) -> 1
A7: Automatisierung aktiv (1 = ja) | B7: =IF(0>=Annahmen!$B$39-1,1,0) -> 0 | C7: =IF(B12>=Annahmen!$B$39-1,1,0) -> 0 | D7: =IF(C12>=Annahmen!$B$39-1,1,0) -> 1 | E7: =IF(D12>=Annahmen!$B$39-1,1,0) -> 1 | F7: =IF(E12>=Annahmen!$B$39-1,1,0) -> 1 | G7: =IF(F12>=Annahmen!$B$39-1,1,0) -> 1 | H7: =IF(G12>=Annahmen!$B$39-1,1,0) -> 1 | I7: =IF(H12>=Annahmen!$B$39-1,1,0) -> 1 | J7: =IF(I12>=Annahmen!$B$39-1,1,0) -> 1 | ... Y7: =IF(X12>=Annahmen!$B$39-1,1,0) -> 1
A8: Std. je neuem Abschluss | B8: =Annahmen!$B$12/(1-Annahmen!$B$15*(1-B6))*((Annahmen!$B$21+B7*(Annahmen!$B$30-Annahmen!$B$21))+(Annahmen!$B$25+B7*(Annahmen!$B$34-Annahmen!$B$25))+(Annahmen!$B$29+B7*(Annahmen!$B$38-Annahmen!$B$29)))+Annahmen!$B$13/(1-Annahmen!$B$15*(1-B6))*((Annahmen!$B$22+B7*(Annahmen!$B$31-Annahmen!$B$22))+(Annahmen!$B$26+B7*(Annahmen!$B$35-Annahmen!$B$26))+(Annahmen!$B$29+B7*(Annahmen!$B$38-Annahmen!$B$29)))+Annahmen!$B$14/(1-Annahmen!$B$15*(1-B6))*((Annahmen!$B$23+B7*(Annahmen!$B$32-Annahmen!$B$23))+(Annahmen!$B$27+B7*(Annahmen!$B$36-Annahmen!$B$27))+(Annahmen!$B$29+B7*(Annahmen!$B$38-Annahmen!$B$29)))+Annahmen!$B$15*B6*((Annahmen!$B$24+B7*(Annahmen!$B$33-Annahmen!$B$24))+(Annahmen!$B$28+B7*(Annahmen!$B$37-Annahmen!$B$28))+(Annahmen!$B$29+B7*(Annahmen!$B$38-Annahmen!$B$29))) -> 37.083333 | C8: =Annahmen!$B$12/(1-Annahmen!$B$15*(1-C6))*((Annahmen!$B$21+C7*(Annahmen!$B$30-Annahmen!$B$21))+(Annahmen!$B$25+C7*(Annahmen!$B$34-Annahmen!$B$25))+(Annahmen!$B$29+C7*(Annahmen!$B$38-Annahmen!$B$29)))+Annahmen!$B$13/(1-Annahmen!$B$15*(1-C6))*((Annahmen!$B$22+C7*(Annahmen!$B$31-Annahmen!$B$22))+(Annahmen!$B$26+C7*(Annahmen!$B$35-Annahmen!$B$26))+(Annahmen!$B$29+C7*(Annahmen!$B$38-Annahmen!$B$29)))+Annahmen!$B$14/(1-Annahmen!$B$15*(1-C6))*((Annahmen!$B$23+C7*(Annahmen!$B$32-Annahmen!$B$23))+(Annahmen!$B$27+C7*(Annahmen!$B$36-Annahmen!$B$27))+(Annahmen!$B$29+C7*(Annahmen!$B$38-Annahmen!$B$29)))+Annahmen!$B$15*C6*((Annahmen!$B$24+C7*(Annahmen!$B$33-Annahmen!$B$24))+(Annahmen!$B$28+C7*(Annahmen!$B$37-Annahmen!$B$28))+(Annahmen!$B$29+C7*(Annahmen!$B$38-Annahmen!$B$29))) -> 37.083333 | D8: =Annahmen!$B$12/(1-Annahmen!$B$15*(1-D6))*((Annahmen!$B$21+D7*(Annahmen!$B$30-Annahmen!$B$21))+(Annahmen!$B$25+D7*(Annahmen!$B$34-Annahmen!$B$25))+(Annahmen!$B$29+D7*(Annahmen!$B$38-Annahmen!$B$29)))+Annahmen!$B$13/(1-Annahmen!$B$15*(1-D6))*((Annahmen!$B$22+D7*(Annahmen!$B$31-Annahmen!$B$22))+(Annahmen!$B$26+D7*(Annahmen!$B$35-Annahmen!$B$26))+(Annahmen!$B$29+D7*(Annahmen!$B$38-Annahmen!$B$29)))+Annahmen!$B$14/(1-Annahmen!$B$15*(1-D6))*((Annahmen!$B$23+D7*(Annahmen!$B$32-Annahmen!$B$23))+(Annahmen!$B$27+D7*(Annahmen!$B$36-Annahmen!$B$27))+(Annahmen!$B$29+D7*(Annahmen!$B$38-Annahmen!$B$29)))+Annahmen!$B$15*D6*((Annahmen!$B$24+D7*(Annahmen!$B$33-Annahmen!$B$24))+(Annahmen!$B$28+D7*(Annahmen!$B$37-Annahmen!$B$28))+(Annahmen!$B$29+D7*(Annahmen!$B$38-Annahmen!$B$29))) -> 19.033333 | E8: =Annahmen!$B$12/(1-Annahmen!$B$15*(1-E6))*((Annahmen!$B$21+E7*(Annahmen!$B$30-Annahmen!$B$21))+(Annahmen!$B$25+E7*(Annahmen!$B$34-Annahmen!$B$25))+(Annahmen!$B$29+E7*(Annahmen!$B$38-Annahmen!$B$29)))+Annahmen!$B$13/(1-Annahmen!$B$15*(1-E6))*((Annahmen!$B$22+E7*(Annahmen!$B$31-Annahmen!$B$22))+(Annahmen!$B$26+E7*(Annahmen!$B$35-Annahmen!$B$26))+(Annahmen!$B$29+E7*(Annahmen!$B$38-Annahmen!$B$29)))+Annahmen!$B$14/(1-Annahmen!$B$15*(1-E6))*((Annahmen!$B$23+E7*(Annahmen!$B$32-Annahmen!$B$23))+(Annahmen!$B$27+E7*(Annahmen!$B$36-Annahmen!$B$27))+(Annahmen!$B$29+E7*(Annahmen!$B$38-Annahmen!$B$29)))+Annahmen!$B$15*E6*((Annahmen!$B$24+E7*(Annahmen!$B$33-Annahmen!$B$24))+(Annahmen!$B$28+E7*(Annahmen!$B$37-Annahmen!$B$28))+(Annahmen!$B$29+E7*(Annahmen!$B$38-Annahmen!$B$29))) -> 19.033333 | F8: =Annahmen!$B$12/(1-Annahmen!$B$15*(1-F6))*((Annahmen!$B$21+F7*(Annahmen!$B$30-Annahmen!$B$21))+(Annahmen!$B$25+F7*(Annahmen!$B$34-Annahmen!$B$25))+(Annahmen!$B$29+F7*(Annahmen!$B$38-Annahmen!$B$29)))+Annahmen!$B$13/(1-Annahmen!$B$15*(1-F6))*((Annahmen!$B$22+F7*(Annahmen!$B$31-Annahmen!$B$22))+(Annahmen!$B$26+F7*(Annahmen!$B$35-Annahmen!$B$26))+(Annahmen!$B$29+F7*(Annahmen!$B$38-Annahmen!$B$29)))+Annahmen!$B$14/(1-Annahmen!$B$15*(1-F6))*((Annahmen!$B$23+F7*(Annahmen!$B$32-Annahmen!$B$23))+(Annahmen!$B$27+F7*(Annahmen!$B$36-Annahmen!$B$27))+(Annahmen!$B$29+F7*(Annahmen!$B$38-Annahmen!$B$29)))+Annahmen!$B$15*F6*((Annahmen!$B$24+F7*(Annahmen!$B$33-Annahmen!$B$24))+(Annahmen!$B$28+F7*(Annahmen!$B$37-Annahmen!$B$28))+(Annahmen!$B$29+F7*(Annahmen!$B$38-Annahmen!$B$29))) -> 19.033333 | G8: =Annahmen!$B$12/(1-Annahmen!$B$15*(1-G6))*((Annahmen!$B$21+G7*(Annahmen!$B$30-Annahmen!$B$21))+(Annahmen!$B$25+G7*(Annahmen!$B$34-Annahmen!$B$25))+(Annahmen!$B$29+G7*(Annahmen!$B$38-Annahmen!$B$29)))+Annahmen!$B$13/(1-Annahmen!$B$15*(1-G6))*((Annahmen!$B$22+G7*(Annahmen!$B$31-Annahmen!$B$22))+(Annahmen!$B$26+G7*(Annahmen!$B$35-Annahmen!$B$26))+(Annahmen!$B$29+G7*(Annahmen!$B$38-Annahmen!$B$29)))+Annahmen!$B$14/(1-Annahmen!$B$15*(1-G6))*((Annahmen!$B$23+G7*(Annahmen!$B$32-Annahmen!$B$23))+(Annahmen!$B$27+G7*(Annahmen!$B$36-Annahmen!$B$27))+(Annahmen!$B$29+G7*(Annahmen!$B$38-Annahmen!$B$29)))+Annahmen!$B$15*G6*((Annahmen!$B$24+G7*(Annahmen!$B$33-Annahmen!$B$24))+(Annahmen!$B$28+G7*(Annahmen!$B$37-Annahmen!$B$28))+(Annahmen!$B$29+G7*(Annahmen!$B$38-Annahmen!$B$29))) -> 19.033333 | H8: =Annahmen!$B$12/(1-Annahmen!$B$15*(1-H6))*((Annahmen!$B$21+H7*(Annahmen!$B$30-Annahmen!$B$21))+(Annahmen!$B$25+H7*(Annahmen!$B$34-Annahmen!$B$25))+(Annahmen!$B$29+H7*(Annahmen!$B$38-Annahmen!$B$29)))+Annahmen!$B$13/(1-Annahmen!$B$15*(1-H6))*((Annahmen!$B$22+H7*(Annahmen!$B$31-Annahmen!$B$22))+(Annahmen!$B$26+H7*(Annahmen!$B$35-Annahmen!$B$26))+(Annahmen!$B$29+H7*(Annahmen!$B$38-Annahmen!$B$29)))+Annahmen!$B$14/(1-Annahmen!$B$15*(1-H6))*((Annahmen!$B$23+H7*(Annahmen!$B$32-Annahmen!$B$23))+(Annahmen!$B$27+H7*(Annahmen!$B$36-Annahmen!$B$27))+(Annahmen!$B$29+H7*(Annahmen!$B$38-Annahmen!$B$29)))+Annahmen!$B$15*H6*((Annahmen!$B$24+H7*(Annahmen!$B$33-Annahmen!$B$24))+(Annahmen!$B$28+H7*(Annahmen!$B$37-Annahmen!$B$28))+(Annahmen!$B$29+H7*(Annahmen!$B$38-Annahmen!$B$29))) -> 19.033333 | I8: =Annahmen!$B$12/(1-Annahmen!$B$15*(1-I6))*((Annahmen!$B$21+I7*(Annahmen!$B$30-Annahmen!$B$21))+(Annahmen!$B$25+I7*(Annahmen!$B$34-Annahmen!$B$25))+(Annahmen!$B$29+I7*(Annahmen!$B$38-Annahmen!$B$29)))+Annahmen!$B$13/(1-Annahmen!$B$15*(1-I6))*((Annahmen!$B$22+I7*(Annahmen!$B$31-Annahmen!$B$22))+(Annahmen!$B$26+I7*(Annahmen!$B$35-Annahmen!$B$26))+(Annahmen!$B$29+I7*(Annahmen!$B$38-Annahmen!$B$29)))+Annahmen!$B$14/(1-Annahmen!$B$15*(1-I6))*((Annahmen!$B$23+I7*(Annahmen!$B$32-Annahmen!$B$23))+(Annahmen!$B$27+I7*(Annahmen!$B$36-Annahmen!$B$27))+(Annahmen!$B$29+I7*(Annahmen!$B$38-Annahmen!$B$29)))+Annahmen!$B$15*I6*((Annahmen!$B$24+I7*(Annahmen!$B$33-Annahmen!$B$24))+(Annahmen!$B$28+I7*(Annahmen!$B$37-Annahmen!$B$28))+(Annahmen!$B$29+I7*(Annahmen!$B$38-Annahmen!$B$29))) -> 18.275 | ... Y8: =Annahmen!$B$12/(1-Annahmen!$B$15*(1-Y6))*((Annahmen!$B$21+Y7*(Annahmen!$B$30-Annahmen!$B$21))+(Annahmen!$B$25+Y7*(Annahmen!$B$34-Annahmen!$B$25))+(Annahmen!$B$29+Y7*(Annahmen!$B$38-Annahmen!$B$29)))+Annahmen!$B$13/(1-Annahmen!$B$15*(1-Y6))*((Annahmen!$B$22+Y7*(Annahmen!$B$31-Annahmen!$B$22))+(Annahmen!$B$26+Y7*(Annahmen!$B$35-Annahmen!$B$26))+(Annahmen!$B$29+Y7*(Annahmen!$B$38-Annahmen!$B$29)))+Annahmen!$B$14/(1-Annahmen!$B$15*(1-Y6))*((Annahmen!$B$23+Y7*(Annahmen!$B$32-Annahmen!$B$23))+(Annahmen!$B$27+Y7*(Annahmen!$B$36-Annahmen!$B$27))+(Annahmen!$B$29+Y7*(Annahmen!$B$38-Annahmen!$B$29)))+Annahmen!$B$15*Y6*((Annahmen!$B$24+Y7*(Annahmen!$B$33-Annahmen!$B$24))+(Annahmen!$B$28+Y7*(Annahmen!$B$37-Annahmen!$B$28))+(Annahmen!$B$29+Y7*(Annahmen!$B$38-Annahmen!$B$29))) -> 18.275
A9: Laufende Stunden (Bestand) | B9: =0*(Annahmen!$B$25+B7*(Annahmen!$B$34-Annahmen!$B$25))+0*(Annahmen!$B$26+B7*(Annahmen!$B$35-Annahmen!$B$26))+0*(Annahmen!$B$27+B7*(Annahmen!$B$36-Annahmen!$B$27))+0*(Annahmen!$B$28+B7*(Annahmen!$B$37-Annahmen!$B$28)) -> 0 | C9: =B14*(Annahmen!$B$25+C7*(Annahmen!$B$34-Annahmen!$B$25))+B15*(Annahmen!$B$26+C7*(Annahmen!$B$35-Annahmen!$B$26))+B16*(Annahmen!$B$27+C7*(Annahmen!$B$36-Annahmen!$B$27))+B17*(Annahmen!$B$28+C7*(Annahmen!$B$37-Annahmen!$B$28)) -> 19.25 | D9: =C14*(Annahmen!$B$25+D7*(Annahmen!$B$34-Annahmen!$B$25))+C15*(Annahmen!$B$26+D7*(Annahmen!$B$35-Annahmen!$B$26))+C16*(Annahmen!$B$27+D7*(Annahmen!$B$36-Annahmen!$B$27))+C17*(Annahmen!$B$28+D7*(Annahmen!$B$37-Annahmen!$B$28)) -> 19.969 | E9: =D14*(Annahmen!$B$25+E7*(Annahmen!$B$34-Annahmen!$B$25))+D15*(Annahmen!$B$26+E7*(Annahmen!$B$35-Annahmen!$B$26))+D16*(Annahmen!$B$27+E7*(Annahmen!$B$36-Annahmen!$B$27))+D17*(Annahmen!$B$28+E7*(Annahmen!$B$37-Annahmen!$B$28)) -> 32.979177 | F9: =E14*(Annahmen!$B$25+F7*(Annahmen!$B$34-Annahmen!$B$25))+E15*(Annahmen!$B$26+F7*(Annahmen!$B$35-Annahmen!$B$26))+E16*(Annahmen!$B$27+F7*(Annahmen!$B$36-Annahmen!$B$27))+E17*(Annahmen!$B$28+F7*(Annahmen!$B$37-Annahmen!$B$28)) -> 45.692236 | G9: =F14*(Annahmen!$B$25+G7*(Annahmen!$B$34-Annahmen!$B$25))+F15*(Annahmen!$B$26+G7*(Annahmen!$B$35-Annahmen!$B$26))+F16*(Annahmen!$B$27+G7*(Annahmen!$B$36-Annahmen!$B$27))+F17*(Annahmen!$B$28+G7*(Annahmen!$B$37-Annahmen!$B$28)) -> 58.115255 | H9: =G14*(Annahmen!$B$25+H7*(Annahmen!$B$34-Annahmen!$B$25))+G15*(Annahmen!$B$26+H7*(Annahmen!$B$35-Annahmen!$B$26))+G16*(Annahmen!$B$27+H7*(Annahmen!$B$36-Annahmen!$B$27))+G17*(Annahmen!$B$28+H7*(Annahmen!$B$37-Annahmen!$B$28)) -> 70.255132 | I9: =H14*(Annahmen!$B$25+I7*(Annahmen!$B$34-Annahmen!$B$25))+H15*(Annahmen!$B$26+I7*(Annahmen!$B$35-Annahmen!$B$26))+H16*(Annahmen!$B$27+I7*(Annahmen!$B$36-Annahmen!$B$27))+H17*(Annahmen!$B$28+I7*(Annahmen!$B$37-Annahmen!$B$28)) -> 82.118598 | J9: =I14*(Annahmen!$B$25+J7*(Annahmen!$B$34-Annahmen!$B$25))+I15*(Annahmen!$B$26+J7*(Annahmen!$B$35-Annahmen!$B$26))+I16*(Annahmen!$B$27+J7*(Annahmen!$B$36-Annahmen!$B$27))+I17*(Annahmen!$B$28+J7*(Annahmen!$B$37-Annahmen!$B$28)) -> 94.345547 | ... Y9: =X14*(Annahmen!$B$25+Y7*(Annahmen!$B$34-Annahmen!$B$25))+X15*(Annahmen!$B$26+Y7*(Annahmen!$B$35-Annahmen!$B$26))+X16*(Annahmen!$B$27+Y7*(Annahmen!$B$36-Annahmen!$B$27))+X17*(Annahmen!$B$28+Y7*(Annahmen!$B$37-Annahmen!$B$28)) -> 148.13605
A10: Möglich nach Stunden | B10: =MAX(0,(Annahmen!$B$41-B9)/B8) -> 4.5842697 | C10: =MAX(0,(Annahmen!$B$41-C9)/C8) -> 4.0651685 | D10: =MAX(0,(Annahmen!$B$41-D9)/D8) -> 7.8825394 | E10: =MAX(0,(Annahmen!$B$41-E9)/E8) -> 7.1989925 | F10: =MAX(0,(Annahmen!$B$41-F9)/F8) -> 6.5310559 | G10: =MAX(0,(Annahmen!$B$41-G9)/G8) -> 5.8783579 | H10: =MAX(0,(Annahmen!$B$41-H9)/H8) -> 5.240536 | I10: =MAX(0,(Annahmen!$B$41-I9)/I8) -> 4.8088318 | ... Y10: =MAX(0,(Annahmen!$B$41-Y9)/Y8) -> 1.196386
A11: Abschlüsse | B11: =MIN(B5,B10) -> 3 | C11: =MIN(C5,C10) -> 3 | D11: =MIN(D5,D10) -> 4 | E11: =MIN(E5,E10) -> 4 | F11: =MIN(F5,F10) -> 4 | G11: =MIN(G5,G10) -> 4 | H11: =MIN(H5,H10) -> 4 | I11: =MIN(I5,I10) -> 4 | ... Y11: =MIN(Y5,Y10) -> 1.196386
A12: Abschlüsse kumuliert | B12: =0+B11 -> 3 | C12: =B12+C11 -> 6 | D12: =C12+D11 -> 10 | E12: =D12+E11 -> 14 | F12: =E12+F11 -> 18 | G12: =F12+G11 -> 22 | H12: =G12+H11 -> 26 | I12: =H12+I11 -> 30 | J12: =I12+J11 -> 34 | ... Y12: =X12+Y11 -> 61.246491
A14: Aktive Pflege-Kunden | B14: =0*(1-Annahmen!$B$17)+B11*Annahmen!$B$12/(1-Annahmen!$B$15*(1-B6)) -> 1 | C14: =B14*(1-Annahmen!$B$17)+C11*Annahmen!$B$12/(1-Annahmen!$B$15*(1-C6)) -> 1.99 | D14: =C14*(1-Annahmen!$B$17)+D11*Annahmen!$B$12/(1-Annahmen!$B$15*(1-D6)) -> 3.3034333 | E14: =D14*(1-Annahmen!$B$17)+E11*Annahmen!$B$12/(1-Annahmen!$B$15*(1-E6)) -> 4.6037323 | F14: =E14*(1-Annahmen!$B$17)+F11*Annahmen!$B$12/(1-Annahmen!$B$15*(1-F6)) -> 5.8910283 | G14: =F14*(1-Annahmen!$B$17)+G11*Annahmen!$B$12/(1-Annahmen!$B$15*(1-G6)) -> 7.1654514 | H14: =G14*(1-Annahmen!$B$17)+H11*Annahmen!$B$12/(1-Annahmen!$B$15*(1-H6)) -> 8.4271302 | I14: =H14*(1-Annahmen!$B$17)+I11*Annahmen!$B$12/(1-Annahmen!$B$15*(1-I6)) -> 9.3428589 | J14: =I14*(1-Annahmen!$B$17)+J11*Annahmen!$B$12/(1-Annahmen!$B$15*(1-J6)) -> 10.24943 | ... Y14: =X14*(1-Annahmen!$B$17)+Y11*Annahmen!$B$12/(1-Annahmen!$B$15*(1-Y6)) -> 15.07706
A15: Aktive Programm-Kunden | B15: =0*(1-Annahmen!$B$18)+B11*Annahmen!$B$13/(1-Annahmen!$B$15*(1-B6)) -> 1 | C15: =B15*(1-Annahmen!$B$18)+C11*Annahmen!$B$13/(1-Annahmen!$B$15*(1-C6)) -> 1.98 | D15: =C15*(1-Annahmen!$B$18)+D11*Annahmen!$B$13/(1-Annahmen!$B$15*(1-D6)) -> 3.2737333 | E15: =D15*(1-Annahmen!$B$18)+E11*Annahmen!$B$13/(1-Annahmen!$B$15*(1-E6)) -> 4.541592 | F15: =E15*(1-Annahmen!$B$18)+F11*Annahmen!$B$13/(1-Annahmen!$B$15*(1-F6)) -> 5.7840935 | G15: =F15*(1-Annahmen!$B$18)+G11*Annahmen!$B$13/(1-Annahmen!$B$15*(1-G6)) -> 7.001745 | H15: =G15*(1-Annahmen!$B$18)+H11*Annahmen!$B$13/(1-Annahmen!$B$15*(1-H6)) -> 8.1950434 | I15: =H15*(1-Annahmen!$B$18)+I11*Annahmen!$B$13/(1-Annahmen!$B$15*(1-I6)) -> 9.0311425 | J15: =I15*(1-Annahmen!$B$18)+J11*Annahmen!$B$13/(1-Annahmen!$B$15*(1-J6)) -> 9.8505197 | ... Y15: =X15*(1-Annahmen!$B$18)+Y11*Annahmen!$B$13/(1-Annahmen!$B$15*(1-Y6)) -> 13.038428
A16: Aktive SEO-Kunden | B16: =0*(1-Annahmen!$B$19)+B11*Annahmen!$B$14/(1-Annahmen!$B$15*(1-B6)) -> 1 | C16: =B16*(1-Annahmen!$B$19)+C11*Annahmen!$B$14/(1-Annahmen!$B$15*(1-C6)) -> 1.97 | D16: =C16*(1-Annahmen!$B$19)+D11*Annahmen!$B$14/(1-Annahmen!$B$15*(1-D6)) -> 3.2442333 | E16: =D16*(1-Annahmen!$B$19)+E11*Annahmen!$B$14/(1-Annahmen!$B$15*(1-E6)) -> 4.4802397 | F16: =E16*(1-Annahmen!$B$19)+F11*Annahmen!$B$14/(1-Annahmen!$B$15*(1-F6)) -> 5.6791658 | G16: =F16*(1-Annahmen!$B$19)+G11*Annahmen!$B$14/(1-Annahmen!$B$15*(1-G6)) -> 6.8421242 | H16: =G16*(1-Annahmen!$B$19)+H11*Annahmen!$B$14/(1-Annahmen!$B$15*(1-H6)) -> 7.9701938 | I16: =H16*(1-Annahmen!$B$19)+I11*Annahmen!$B$14/(1-Annahmen!$B$15*(1-I6)) -> 8.731088 | J16: =I16*(1-Annahmen!$B$19)+J11*Annahmen!$B$14/(1-Annahmen!$B$15*(1-J6)) -> 9.4691553 | ... Y16: =X16*(1-Annahmen!$B$19)+Y11*Annahmen!$B$14/(1-Annahmen!$B$15*(1-Y6)) -> 11.306798
A17: Aktive Recruiting-Kunden | B17: =0*(1-Annahmen!$B$20)+B11*Annahmen!$B$15*B6 -> 0 | C17: =B17*(1-Annahmen!$B$20)+C11*Annahmen!$B$15*C6 -> 0 | D17: =C17*(1-Annahmen!$B$20)+D11*Annahmen!$B$15*D6 -> 0 | E17: =D17*(1-Annahmen!$B$20)+E11*Annahmen!$B$15*E6 -> 0 | F17: =E17*(1-Annahmen!$B$20)+F11*Annahmen!$B$15*F6 -> 0 | G17: =F17*(1-Annahmen!$B$20)+G11*Annahmen!$B$15*G6 -> 0 | H17: =G17*(1-Annahmen!$B$20)+H11*Annahmen!$B$15*H6 -> 0 | I17: =H17*(1-Annahmen!$B$20)+I11*Annahmen!$B$15*I6 -> 1 | J17: =I17*(1-Annahmen!$B$20)+J11*Annahmen!$B$15*J6 -> 1.95 | ... Y17: =X17*(1-Annahmen!$B$20)+Y11*Annahmen!$B$15*Y6 -> 5.429965
A19: MRR | B19: =B14*Annahmen!$B$6+B15*Annahmen!$B$7+B16*Annahmen!$B$9+B17*Annahmen!$B$10 -> 1779 | C19: =C14*Annahmen!$B$6+C15*Annahmen!$B$7+C16*Annahmen!$B$9+C17*Annahmen!$B$10 -> 3517.91 | D19: =D14*Annahmen!$B$6+D15*Annahmen!$B$7+D16*Annahmen!$B$9+D17*Annahmen!$B$10 -> 5810.6809 | E19: =E14*Annahmen!$B$6+E15*Annahmen!$B$7+E16*Annahmen!$B$9+E17*Annahmen!$B$10 -> 8051.8766 | F19: =F14*Annahmen!$B$6+F15*Annahmen!$B$7+F16*Annahmen!$B$9+F17*Annahmen!$B$10 -> 10242.718 | G19: =G14*Annahmen!$B$6+G15*Annahmen!$B$7+G16*Annahmen!$B$9+G17*Annahmen!$B$10 -> 12384.397 | H19: =H14*Annahmen!$B$6+H15*Annahmen!$B$7+H16*Annahmen!$B$9+H17*Annahmen!$B$10 -> 14478.074 | I19: =I14*Annahmen!$B$6+I15*Annahmen!$B$7+I16*Annahmen!$B$9+I17*Annahmen!$B$10 -> 16721.883 | ... Y19: =Y14*Annahmen!$B$6+Y15*Annahmen!$B$7+Y16*Annahmen!$B$9+Y17*Annahmen!$B$10 -> 26725.254
A20: Einmalumsatz | B20: =B11*(Annahmen!$B$12/(1-Annahmen!$B$15*(1-B6))*Annahmen!$B$5+Annahmen!$B$13/(1-Annahmen!$B$15*(1-B6))*Annahmen!$B$8+Annahmen!$B$15*B6*Annahmen!$B$11) -> 3690 | C20: =C11*(Annahmen!$B$12/(1-Annahmen!$B$15*(1-C6))*Annahmen!$B$5+Annahmen!$B$13/(1-Annahmen!$B$15*(1-C6))*Annahmen!$B$8+Annahmen!$B$15*C6*Annahmen!$B$11) -> 3690 | D20: =D11*(Annahmen!$B$12/(1-Annahmen!$B$15*(1-D6))*Annahmen!$B$5+Annahmen!$B$13/(1-Annahmen!$B$15*(1-D6))*Annahmen!$B$8+Annahmen!$B$15*D6*Annahmen!$B$11) -> 4920 | E20: =E11*(Annahmen!$B$12/(1-Annahmen!$B$15*(1-E6))*Annahmen!$B$5+Annahmen!$B$13/(1-Annahmen!$B$15*(1-E6))*Annahmen!$B$8+Annahmen!$B$15*E6*Annahmen!$B$11) -> 4920 | F20: =F11*(Annahmen!$B$12/(1-Annahmen!$B$15*(1-F6))*Annahmen!$B$5+Annahmen!$B$13/(1-Annahmen!$B$15*(1-F6))*Annahmen!$B$8+Annahmen!$B$15*F6*Annahmen!$B$11) -> 4920 | G20: =G11*(Annahmen!$B$12/(1-Annahmen!$B$15*(1-G6))*Annahmen!$B$5+Annahmen!$B$13/(1-Annahmen!$B$15*(1-G6))*Annahmen!$B$8+Annahmen!$B$15*G6*Annahmen!$B$11) -> 4920 | H20: =H11*(Annahmen!$B$12/(1-Annahmen!$B$15*(1-H6))*Annahmen!$B$5+Annahmen!$B$13/(1-Annahmen!$B$15*(1-H6))*Annahmen!$B$8+Annahmen!$B$15*H6*Annahmen!$B$11) -> 4920 | I20: =I11*(Annahmen!$B$12/(1-Annahmen!$B$15*(1-I6))*Annahmen!$B$5+Annahmen!$B$13/(1-Annahmen!$B$15*(1-I6))*Annahmen!$B$8+Annahmen!$B$15*I6*Annahmen!$B$11) -> 5180 | ... Y20: =Y11*(Annahmen!$B$12/(1-Annahmen!$B$15*(1-Y6))*Annahmen!$B$5+Annahmen!$B$13/(1-Annahmen!$B$15*(1-Y6))*Annahmen!$B$8+Annahmen!$B$15*Y6*Annahmen!$B$11) -> 1549.3198
A21: Umsatz | B21: =B19+B20 -> 5469 | C21: =C19+C20 -> 7207.91 | D21: =D19+D20 -> 10730.681 | E21: =E19+E20 -> 12971.877 | F21: =F19+F20 -> 15162.718 | G21: =G19+G20 -> 17304.397 | H21: =H19+H20 -> 19398.074 | I21: =I19+I20 -> 21901.883 | ... Y21: =Y19+Y20 -> 28274.574
A22: Kosten | B22: =Annahmen!$B$42+Annahmen!$B$43+B7*Annahmen!$B$40 -> 355 | C22: =Annahmen!$B$42+Annahmen!$B$43+C7*Annahmen!$B$40 -> 355 | D22: =Annahmen!$B$42+Annahmen!$B$43+D7*Annahmen!$B$40 -> 505 | E22: =Annahmen!$B$42+Annahmen!$B$43+E7*Annahmen!$B$40 -> 505 | F22: =Annahmen!$B$42+Annahmen!$B$43+F7*Annahmen!$B$40 -> 505 | G22: =Annahmen!$B$42+Annahmen!$B$43+G7*Annahmen!$B$40 -> 505 | H22: =Annahmen!$B$42+Annahmen!$B$43+H7*Annahmen!$B$40 -> 505 | I22: =Annahmen!$B$42+Annahmen!$B$43+I7*Annahmen!$B$40 -> 505 | ... Y22: =Annahmen!$B$42+Annahmen!$B$43+Y7*Annahmen!$B$40 -> 505
A23: Ergebnis vor Steuern (= Einkommen Gründer) | B23: =B21-B22 -> 5114 | C23: =C21-C22 -> 6852.91 | D23: =D21-D22 -> 10225.681 | E23: =E21-E22 -> 12466.877 | F23: =F21-F22 -> 14657.718 | G23: =G21-G22 -> 16799.397 | H23: =H21-H22 -> 18893.074 | I23: =I21-I22 -> 21396.883 | ... Y23: =Y21-Y22 -> 27769.574
A24: Kasse kumuliert | B24: =B23 -> 5114 | C24: =B24+C23 -> 11966.91 | D24: =C24+D23 -> 22192.591 | E24: =D24+E23 -> 34659.468 | F24: =E24+F23 -> 49317.186 | G24: =F24+G23 -> 66116.583 | H24: =G24+H23 -> 85009.658 | I24: =H24+I23 -> 106406.54 | J24: =I24+J23 -> 129975.33 | ... Y24: =X24+Y23 -> 533672.37
A25: Belegte Stunden | B25: =B9+B11*B8 -> 111.25 | C25: =C9+C11*C8 -> 130.5 | D25: =D9+D11*D8 -> 96.102333 | E25: =E9+E11*E8 -> 109.11251 | F25: =F9+F11*F8 -> 121.82557 | G25: =G9+G11*G8 -> 134.24859 | H25: =H9+H11*H8 -> 146.38847 | I25: =I9+I11*I8 -> 155.2186 | ... Y25: =Y9+Y11*Y8 -> 170

Sheet Ausbau ab 10k
A1: Ausbau-Plan: Team ab dem Monat nach 10.000 € MRR (Solo Basis)
A2: Startbestand kommt automatisch aus „Solo Basis“ (erster Monat mit MRR ≥ 10.000 €). Blaue Werte sind Eingaben.
A4: Annahme | B4: Wert | D4: Kennzahl | E4: Jul 27 | F4: Aug 27 | G4: Sep 27 | H4: Okt 27 | I4: Nov 27 | J4: Dez 27 | K4: Jan 28 | L4: Feb 28 | M4: Mär 28 | N4: Apr 28 | O4: Mai 28 | P4: Jun 28 | Q4: Summe 12 Monate
A5: Ø Website-Auftrag | B5: 2600 | D5: Personen im Vertrieb (inkl. Gründer) | E5: 1 | F5: 1 | G5: 2 | H5: 2 | I5: 3 | J5: 3 | K5: 4 | L5: 4 | M5: 5 | N5: 5 | O5: 6 | P5: 6
A6: Pflege & Hosting / Monat | B6: 79 | D6: Terminierer | E6: 0 | F6: 1 | G6: 1 | H6: 2 | I6: 2 | J6: 3 | K6: 3 | L6: 4 | M6: 4 | N6: 5 | O6: 5 | P6: 6
A7: SEO / Monat | B7: 520 | D7: Angestellte Closer | E7: =MAX(0,E5-1) -> 0 | F7: =MAX(0,F5-1) -> 0 | G7: =MAX(0,G5-1) -> 1 | H7: =MAX(0,H5-1) -> 1 | I7: =MAX(0,I5-1) -> 2 | J7: =MAX(0,J5-1) -> 2 | K7: =MAX(0,K5-1) -> 3 | L7: =MAX(0,L5-1) -> 3 | ... P7: =MAX(0,P5-1) -> 5
A8: Ads-Betreuung / Monat | B8: 290 | D8: davon neu | E8: =E7 -> 0 | F8: =MAX(0,F7-E7) -> 0 | G8: =MAX(0,G7-F7) -> 1 | H8: =MAX(0,H7-G7) -> 0 | I8: =MAX(0,I7-H7) -> 1 | J8: =MAX(0,J7-I7) -> 0 | K8: =MAX(0,K7-J7) -> 1 | L8: =MAX(0,L7-K7) -> 0 | M8: =MAX(0,M7-L7) -> 1 | ... P8: =MAX(0,P7-O7) -> 0
A9: Ads-Einrichtung | B9: 390 | D9: Eingearbeitete Closer-Äquivalente | E9: =E7-(1-$B$42)*E8 -> 0 | F9: =F7-(1-$B$42)*F8-(1-$B$43)*E8 -> 0 | G9: =G7-(1-$B$42)*G8-(1-$B$43)*F8-(1-$B$44)*E8 -> 0.25 | H9: =H7-(1-$B$42)*H8-(1-$B$43)*G8-(1-$B$44)*F8 -> 0.5 | I9: =I7-(1-$B$42)*I8-(1-$B$43)*H8-(1-$B$44)*G8 -> 1 | J9: =J7-(1-$B$42)*J8-(1-$B$43)*I8-(1-$B$44)*H8 -> 1.5 | K9: =K7-(1-$B$42)*K8-(1-$B$43)*J8-(1-$B$44)*I8 -> 2 | L9: =L7-(1-$B$42)*L8-(1-$B$43)*K8-(1-$B$44)*J8 -> 2.5 | M9: =M7-(1-$B$42)*M8-(1-$B$43)*L8-(1-$B$44)*K8 -> 3 | N9: =N7-(1-$B$42)*N8-(1-$B$43)*M8-(1-$B$44)*L8 -> 3.5 | ... P9: =P7-(1-$B$42)*P8-(1-$B$43)*O8-(1-$B$44)*N8 -> 4.5
A10: Wachstumsprogramm / Monat | B10: 1190 | D10: Abschlüsse | E10: =$B$25+E9*$B$24 -> 3 | F10: =$B$25+F9*$B$24 -> 3 | G10: =$B$25+G9*$B$24 -> 4.25 | H10: =$B$25+H9*$B$24 -> 5.5 | I10: =$B$25+I9*$B$24 -> 8 | J10: =$B$25+J9*$B$24 -> 10.5 | K10: =$B$25+K9*$B$24 -> 13 | L10: =$B$25+L9*$B$24 -> 15.5 | ... P10: =$B$25+P9*$B$24 -> 25.5 | Q10: =SUM(E10:P10) -> 149.75
A11: Programm-Einrichtung | B11: 1490 | D11: neue Website-Kunden | E11: =E10*$B$14 -> 1.5 | F11: =F10*$B$14 -> 1.5 | G11: =G10*$B$14 -> 2.125 | H11: =H10*$B$14 -> 2.75 | I11: =I10*$B$14 -> 4 | J11: =J10*$B$14 -> 5.25 | K11: =K10*$B$14 -> 6.5 | L11: =L10*$B$14 -> 7.75 | ... P11: =P10*$B$14 -> 12.75 | Q11: =SUM(E11:P11) -> 74.875
A12: Recruiting-Einrichtung | B12: 1490 | D12: neue SEO-Kunden | E12: =E11*$B$17 -> 0.525 | F12: =F11*$B$17 -> 0.525 | G12: =G11*$B$17 -> 0.74375 | H12: =H11*$B$17 -> 0.9625 | I12: =I11*$B$17 -> 1.4 | J12: =J11*$B$17 -> 1.8375 | K12: =K11*$B$17 -> 2.275 | L12: =L11*$B$17 -> 2.7125 | ... P12: =P11*$B$17 -> 4.4625 | Q12: =SUM(E12:P12) -> 26.20625
A13: Recruiting / Monat | B13: 790 | D13: neue Ads-Kunden | E13: =E11*$B$18 -> 0.3 | F13: =F11*$B$18 -> 0.3 | G13: =G11*$B$18 -> 0.425 | H13: =H11*$B$18 -> 0.55 | I13: =I11*$B$18 -> 0.8 | J13: =J11*$B$18 -> 1.05 | K13: =K11*$B$18 -> 1.3 | L13: =L11*$B$18 -> 1.55 | ... P13: =P11*$B$18 -> 2.55 | Q13: =SUM(E13:P13) -> 14.975
A14: Anteil Website-Abschlüsse | B14: 0.5 | D14: neue Programm-Kunden | E14: =E10*$B$15 -> 0.75 | F14: =F10*$B$15 -> 0.75 | G14: =G10*$B$15 -> 1.0625 | H14: =H10*$B$15 -> 1.375 | I14: =I10*$B$15 -> 2 | J14: =J10*$B$15 -> 2.625 | K14: =K10*$B$15 -> 3.25 | L14: =L10*$B$15 -> 3.875 | ... P14: =P10*$B$15 -> 6.375 | Q14: =SUM(E14:P14) -> 37.4375
A15: Anteil Programm-Abschlüsse | B15: 0.25 | D15: neue Recruiting-Kunden | E15: =E10*$B$16 -> 0.75 | F15: =F10*$B$16 -> 0.75 | G15: =G10*$B$16 -> 1.0625 | H15: =H10*$B$16 -> 1.375 | I15: =I10*$B$16 -> 2 | J15: =J10*$B$16 -> 2.625 | K15: =K10*$B$16 -> 3.25 | L15: =L10*$B$16 -> 3.875 | ... P15: =P10*$B$16 -> 6.375 | Q15: =SUM(E15:P15) -> 37.4375
A16: Anteil Recruiting-Abschlüsse | B16: 0.25
A17: Website-Abschlüsse mit SEO | B17: 0.35 | D17: Aktive Pflege-Kunden | E17: =$B$47*(1-$B$19)+E11 -> 7.4934608 | F17: =E17*(1-$B$19)+F11 -> 8.9185262 | G17: =F17*(1-$B$19)+G11 -> 10.954341 | H17: =G17*(1-$B$19)+H11 -> 13.594798 | I17: =H17*(1-$B$19)+I11 -> 17.45885 | J17: =I17*(1-$B$19)+J11 -> 22.534261 | K17: =J17*(1-$B$19)+K11 -> 28.808918 | L17: =K17*(1-$B$19)+L11 -> 36.270829 | M17: =L17*(1-$B$19)+M11 -> 44.908121 | ... P17: =O17*(1-$B$19)+P11 -> 77.75533
A18: Website-Abschlüsse mit Ads | B18: 0.2 | D18: Aktive SEO-Kunden | E18: =$B$48*(1-$B$20)+E12 -> 5.9860079 | F18: =E18*(1-$B$20)+F12 -> 6.3314276 | G18: =F18*(1-$B$20)+G12 -> 6.8852348 | H18: =G18*(1-$B$20)+H12 -> 7.6411778 | I18: =H18*(1-$B$20)+I12 -> 8.8119424 | J18: =I18*(1-$B$20)+J12 -> 10.385084 | K18: =J18*(1-$B$20)+K12 -> 12.348532 | L18: =K18*(1-$B$20)+L12 -> 14.690576 | M18: =L18*(1-$B$20)+M12 -> 17.399858 | ... P18: =O18*(1-$B$20)+P12 -> 27.62261
A19: Kündigung Pflege | B19: 0.01 | D19: Aktive Ads-Kunden | E19: =$B$51*(1-$B$21)+E13 -> 0.3 | F19: =E19*(1-$B$21)+F13 -> 0.588 | G19: =F19*(1-$B$21)+G13 -> 0.98948 | H19: =G19*(1-$B$21)+H13 -> 1.4999008 | I19: =H19*(1-$B$21)+I13 -> 2.2399048 | J19: =I19*(1-$B$21)+J13 -> 3.2003086 | K19: =J19*(1-$B$21)+K13 -> 4.3722962 | L19: =K19*(1-$B$21)+L13 -> 5.7474044 | M19: =L19*(1-$B$21)+M13 -> 7.3175082 | ... P19: =O19*(1-$B$21)+P13 -> 13.121343
A20: Kündigung SEO | B20: 0.03 | D20: Aktive Programm-Kunden | E20: =$B$49*(1-$B$22)+E14 -> 6.4711236 | F20: =E20*(1-$B$22)+F14 -> 7.0917011 | G20: =F20*(1-$B$22)+G14 -> 8.0123671 | H20: =G20*(1-$B$22)+H14 -> 9.2271198 | I20: =H20*(1-$B$22)+I14 -> 11.042577 | J20: =I20*(1-$B$22)+J14 -> 13.446726 | K20: =J20*(1-$B$22)+K14 -> 16.427791 | L20: =K20*(1-$B$22)+L14 -> 19.974235 | M20: =L20*(1-$B$22)+M14 -> 24.074751 | ... P20: =O20*(1-$B$22)+P14 -> 39.591013
A21: Kündigung Ads | B21: 0.04 | D21: Aktive Recruiting-Kunden | E21: =$B$50*(1-$B$23)+E15 -> 1.2004177 | F21: =E21*(1-$B$23)+F15 -> 1.8903968 | G21: =F21*(1-$B$23)+G15 -> 2.858377 | H21: =G21*(1-$B$23)+H15 -> 4.0904581 | I21: =H21*(1-$B$23)+I15 -> 5.8859352 | J21: =I21*(1-$B$23)+J15 -> 8.2166385 | K21: =J21*(1-$B$23)+K15 -> 11.055807 | L21: =K21*(1-$B$23)+L15 -> 14.378016 | M21: =L21*(1-$B$23)+M15 -> 18.159115 | ... P21: =O21*(1-$B$23)+P15 -> 32.031984
A22: Kündigung Programm | B22: 0.02
A23: Kündigung Recruiting | B23: 0.05 | D23: MRR | E23: =E17*$B$6+E18*$B$7+E19*$B$8+E20*$B$10+E21*$B$13 -> 12440.675 | F23: =F17*$B$6+F18*$B$7+F19*$B$8+F20*$B$10+F21*$B$13 -> 14099.964 | G23: =G17*$B$6+G18*$B$7+G19*$B$8+G20*$B$10+G21*$B$13 -> 16525.499 | H23: =H17*$B$6+H18*$B$7+H19*$B$8+H20*$B$10+H21*$B$13 -> 19694.107 | I23: =I17*$B$6+I18*$B$7+I19*$B$8+I20*$B$10+I21*$B$13 -> 24401.587 | J23: =J17*$B$6+J18*$B$7+J19*$B$8+J20*$B$10+J21*$B$13 -> 30601.288 | K23: =K17*$B$6+K18*$B$7+K19*$B$8+K20*$B$10+K21*$B$13 -> 38248.266 | L23: =L17*$B$6+L18*$B$7+L19*$B$8+L20*$B$10+L21*$B$13 -> 47299.215 | ... P23: =P17*$B$6+P18*$B$7+P19*$B$8+P20*$B$10+P21*$B$13 -> 96730.19
A24: Abschlüsse je eingearbeitetem Closer | B24: 5 | D24: Einmalumsatz | E24: =E11*$B$5+E13*$B$9+E14*$B$11+E15*$B$12 -> 6252 | F24: =F11*$B$5+F13*$B$9+F14*$B$11+F15*$B$12 -> 6252 | G24: =G11*$B$5+G13*$B$9+G14*$B$11+G15*$B$12 -> 8857 | H24: =H11*$B$5+H13*$B$9+H14*$B$11+H15*$B$12 -> 11462 | I24: =I11*$B$5+I13*$B$9+I14*$B$11+I15*$B$12 -> 16672 | J24: =J11*$B$5+J13*$B$9+J14*$B$11+J15*$B$12 -> 21882 | K24: =K11*$B$5+K13*$B$9+K14*$B$11+K15*$B$12 -> 27092 | L24: =L11*$B$5+L13*$B$9+L14*$B$11+L15*$B$12 -> 32302 | ... P24: =P11*$B$5+P13*$B$9+P14*$B$11+P15*$B$12 -> 53142 | Q24: =SUM(E24:P24) -> 312079
A25: Abschlüsse Gründer / Monat | B25: 3 | D25: Umsatz | E25: =E23+E24 -> 18692.675 | F25: =F23+F24 -> 20351.964 | G25: =G23+G24 -> 25382.499 | H25: =H23+H24 -> 31156.107 | I25: =I23+I24 -> 41073.587 | J25: =J23+J24 -> 52483.288 | K25: =K23+K24 -> 65340.266 | L25: =L23+L24 -> 79601.215 | ... P25: =P23+P24 -> 149872.19 | Q25: =SUM(E25:P25) -> 821745.77
A26: Fixkosten je Closer | B26: 3500 | D26: Jahresumsatz-Tempo (Umsatz × 12) | E26: =E25*12 -> 224312.09 | F26: =F25*12 -> 244223.57 | G26: =G25*12 -> 304589.99 | H26: =H25*12 -> 373873.29 | I26: =I25*12 -> 492883.05 | J26: =J25*12 -> 629799.46 | K26: =K25*12 -> 784083.19 | L26: =L25*12 -> 955214.58 | ... P26: =P25*12 -> 1798466.3
A27: Fixkosten je Terminierer | B27: 2600
A28: Provision auf Umsatz | B28: 0.08 | D28: Umsetzungsstunden | E28: =E11*$B$31+E18*$B$32+E19*$B$33+E20*$B$34+E15*$B$35+E21*$B$36+E17*$B$37 -> 169.09162 | F28: =F11*$B$31+F18*$B$32+F19*$B$33+F20*$B$34+F15*$B$35+F21*$B$36+F17*$B$37 -> 185.35302 | G28: =G11*$B$31+G18*$B$32+G19*$B$33+G20*$B$34+G15*$B$35+G21*$B$36+G17*$B$37 -> 224.86056 | H28: =H11*$B$31+H18*$B$32+H19*$B$33+H20*$B$34+H15*$B$35+H21*$B$36+H17*$B$37 -> 271.76097 | I28: =I11*$B$31+I18*$B$32+I19*$B$33+I20*$B$34+I15*$B$35+I21*$B$36+I17*$B$37 -> 349.58408 | J28: =J11*$B$31+J18*$B$32+J19*$B$33+J20*$B$34+J15*$B$35+J21*$B$36+J17*$B$37 -> 442.24561 | K28: =K11*$B$31+K18*$B$32+K19*$B$33+K20*$B$34+K15*$B$35+K21*$B$36+K17*$B$37 -> 549.30269 | L28: =L11*$B$31+L18*$B$32+L19*$B$33+L20*$B$34+L15*$B$35+L21*$B$36+L17*$B$37 -> 670.32809 | ... P28: =P11*$B$31+P18*$B$32+P19*$B$33+P20*$B$34+P15*$B$35+P21*$B$36+P17*$B$37 -> 1286.0833 | Q28: =SUM(E28:P28) -> 7019.3339
A29: Anteil Abschlüsse über Werbung | B29: 0.5 | D29: Vollzeitstellen Umsetzung (140 h) | E29: =E28/140 -> 1.2077973 | F29: =F28/140 -> 1.3239501 | G29: =G28/140 -> 1.6061469 | H29: =H28/140 -> 1.9411498 | I29: =I28/140 -> 2.4970291 | J29: =J28/140 -> 3.1588972 | K29: =K28/140 -> 3.9235906 | L29: =L28/140 -> 4.7880578 | ... P29: =P28/140 -> 9.1863096
A30: Werbekosten je Abschluss | B30: 900 | D30: Kosten Umsetzung | E30: =E28*$B$38 -> 7778.2143 | F30: =F28*$B$38 -> 8526.2387 | G30: =G28*$B$38 -> 10343.586 | H30: =H28*$B$38 -> 12501.005 | I30: =I28*$B$38 -> 16080.868 | J30: =J28*$B$38 -> 20343.298 | K30: =K28*$B$38 -> 25267.924 | L30: =L28*$B$38 -> 30835.092 | ... P30: =P28*$B$38 -> 59159.834 | Q30: =SUM(E30:P30) -> 322889.36
A31: Std. je Website | B31: 20 | D31: Kosten Vertrieb | E31: =E7*$B$26+E6*$B$27+E25*$B$28 -> 1495.414 | F31: =F7*$B$26+F6*$B$27+F25*$B$28 -> 4228.1571 | G31: =G7*$B$26+G6*$B$27+G25*$B$28 -> 8130.5999 | H31: =H7*$B$26+H6*$B$27+H25*$B$28 -> 11192.489 | I31: =I7*$B$26+I6*$B$27+I25*$B$28 -> 15485.887 | J31: =J7*$B$26+J6*$B$27+J25*$B$28 -> 18998.663 | K31: =K7*$B$26+K6*$B$27+K25*$B$28 -> 23527.221 | L31: =L7*$B$26+L6*$B$27+L25*$B$28 -> 27268.097 | ... P31: =P7*$B$26+P6*$B$27+P25*$B$28 -> 45089.775 | Q31: =SUM(E31:P31) -> 264339.66
A32: Std. je SEO-Kunde / Monat | B32: 6 | D32: Werbebudget | E32: =E10*$B$29*$B$30 -> 1350 | F32: =F10*$B$29*$B$30 -> 1350 | G32: =G10*$B$29*$B$30 -> 1912.5 | H32: =H10*$B$29*$B$30 -> 2475 | I32: =I10*$B$29*$B$30 -> 3600 | J32: =J10*$B$29*$B$30 -> 4725 | K32: =K10*$B$29*$B$30 -> 5850 | L32: =L10*$B$29*$B$30 -> 6975 | ... P32: =P10*$B$29*$B$30 -> 11475 | Q32: =SUM(E32:P32) -> 67387.5
A33: Std. je Ads-Kunde / Monat | B33: 3 | D33: Gemeinkosten | E33: =$B$39+($B$40-$B$39)*0/11 -> 1500 | F33: =$B$39+($B$40-$B$39)*1/11 -> 1727.2727 | G33: =$B$39+($B$40-$B$39)*2/11 -> 1954.5455 | H33: =$B$39+($B$40-$B$39)*3/11 -> 2181.8182 | I33: =$B$39+($B$40-$B$39)*4/11 -> 2409.0909 | J33: =$B$39+($B$40-$B$39)*5/11 -> 2636.3636 | K33: =$B$39+($B$40-$B$39)*6/11 -> 2863.6364 | L33: =$B$39+($B$40-$B$39)*7/11 -> 3090.9091 | M33: =$B$39+($B$40-$B$39)*8/11 -> 3318.1818 | N33: =$B$39+($B$40-$B$39)*9/11 -> 3545.4545 | O33: =$B$39+($B$40-$B$39)*10/11 -> 3772.7273 | P33: =$B$39+($B$40-$B$39)*11/11 -> 4000 | Q33: =SUM(E33:P33) -> 33000
A34: Std. je Programm-Kunde / Monat | B34: 13 | D34: Gründergehalt | E34: =$B$41 -> 5000 | F34: =$B$41 -> 5000 | G34: =$B$41 -> 5000 | H34: =$B$41 -> 5000 | I34: =$B$41 -> 5000 | J34: =$B$41 -> 5000 | K34: =$B$41 -> 5000 | L34: =$B$41 -> 5000 | ... P34: =$B$41 -> 5000 | Q34: =SUM(E34:P34) -> 60000
A35: Std. je Recruiting-Einrichtung | B35: 10 | D35: Kosten gesamt | E35: =SUM(E30:E34) -> 17123.628 | F35: =SUM(F30:F34) -> 20831.669 | G35: =SUM(G30:G34) -> 27341.231 | H35: =SUM(H30:H34) -> 33350.311 | I35: =SUM(I30:I34) -> 42575.845 | J35: =SUM(J30:J34) -> 51703.325 | K35: =SUM(K30:K34) -> 62508.781 | L35: =SUM(L30:L34) -> 73169.098 | ... P35: =SUM(P30:P34) -> 124724.61 | Q35: =SUM(E35:P35) -> 747616.52
A36: Std. je Recruiting-Kunde / Monat | B36: 7
A37: Std. je Pflege-Kunde / Monat | B37: 0.3 | D37: Ergebnis vor Steuern | E37: =E25-E35 -> 1569.0463 | F37: =F25-F35 -> -479.7048 | G37: =G25-G35 -> -1958.7323 | H37: =H25-H35 -> -2194.2044 | I37: =I25-I35 -> -1502.258 | J37: =J25-J35 -> 779.96307 | K37: =K25-K35 -> 2831.4845 | L37: =L25-L35 -> 6432.1167 | ... P37: =P25-P35 -> 25147.581 | Q37: =SUM(E37:P37) -> 74129.245
A38: Mischsatz Umsetzung je Stunde | B38: 46 | D38: Kasse kumuliert | E38: =E37 -> 1569.0463 | F38: =E38+F37 -> 1089.3415 | G38: =F38+G37 -> -869.39087 | H38: =G38+H37 -> -3063.5952 | I38: =H38+I37 -> -4565.8532 | J38: =I38+J37 -> -3785.8901 | K38: =J38+K37 -> -954.40558 | L38: =K38+L37 -> 5477.7111 | M38: =L38+M37 -> 15240.132 | ... P38: =O38+P37 -> 74129.245
A39: Gemeinkosten erster Monat | B39: 1500
A40: Gemeinkosten zwölfter Monat | B40: 4000
A41: Gründergehalt / Monat | B41: 5000
A42: Leistung neuer Closer im Monat 1 | B42: 0.25
A43: Leistung neuer Closer im Monat 2 | B43: 0.5
A44: Leistung neuer Closer im Monat 3 | B44: 0.75
A46: Zielmonat 10.000 € MRR (aus Solo Basis) | B46: =COUNTIF('Solo Basis'!B19:Y19,"<10000")+1 -> 8
A47: Startbestand Pflege | B47: =INDEX('Solo Basis'!B14:Y14,1,$B$46) -> 6.0540008
A48: Startbestand SEO | B48: =INDEX('Solo Basis'!B16:Y16,1,$B$46) -> 5.629905
A49: Startbestand Programm | B49: =INDEX('Solo Basis'!B15:Y15,1,$B$46) -> 5.8378812
A50: Startbestand Recruiting | B50: =INDEX('Solo Basis'!B17:Y17,1,$B$46) -> 0.47412389
A51: Startbestand Ads | B51: 0
